// class version 50.0 (50)
// access flags 0x21
public class bsu implements bxe  {

  // compiled from: RenderItem.java
  // access flags 0x0
  INNERCLASS bsu$9 null null
  // access flags 0x0
  INNERCLASS bsu$8 null null
  // access flags 0x0
  INNERCLASS bsu$7 null null
  // access flags 0x0
  INNERCLASS bsu$6 null null
  // access flags 0x0
  INNERCLASS bsu$5 null null
  // access flags 0x0
  INNERCLASS bsu$4 null null
  // access flags 0x0
  INNERCLASS bsu$3 null null
  // access flags 0x0
  INNERCLASS bsu$2 null null
  // access flags 0x0
  INNERCLASS bsu$1 null null
  // access flags 0x4019
  public final static enum INNERCLASS bpl$b bpl b
  // access flags 0x4019
  public final static enum INNERCLASS bob$r bob r
  // access flags 0x4019
  public final static enum INNERCLASS bob$l bob l
  // access flags 0x4019
  public final static enum INNERCLASS bob$i bob i
  // access flags 0x4019
  public final static enum INNERCLASS apz$a apz a
  // access flags 0x4019
  public final static enum INNERCLASS alg$a alg a
  // access flags 0x4019
  public final static enum INNERCLASS alj$b alj b
  // access flags 0x4019
  public final static enum INNERCLASS anx$a anx a
  // access flags 0x4409
  public static abstract enum INNERCLASS anh$a anh a
  // access flags 0x4019
  public final static enum INNERCLASS aod$a aod a
  // access flags 0x4019
  public final static enum INNERCLASS aog$a aog a
  // access flags 0x4019
  public final static enum INNERCLASS alz$a alz a
  // access flags 0x4019
  public final static enum INNERCLASS aot$a aot a
  // access flags 0x4019
  public final static enum INNERCLASS aou$a aou a
  // access flags 0x4019
  public final static enum INNERCLASS aoj$a aoj a
  // access flags 0x4019
  public final static enum INNERCLASS apl$a apl a
  // access flags 0x4019
  public final static enum INNERCLASS apm$a apm a
  // access flags 0x4019
  public final static enum INNERCLASS apo$a apo a
  // access flags 0x4019
  public final static enum INNERCLASS anp$a anp a
  // access flags 0x4019
  public final static enum INNERCLASS apr$a apr a
  // access flags 0x4019
  public final static enum INNERCLASS adq$a adq a
  // access flags 0x4019
  public final static enum INNERCLASS amu$a amu a
  // access flags 0x4019
  public final static enum INNERCLASS are$a are a

  // access flags 0x1A
  private final static Lkn; b

  // access flags 0x2
  private Z c

  // access flags 0x1
  public F a

  // access flags 0x12
  private final Lboe; d

  // access flags 0x12
  private final Lbwf; e

  // access flags 0x12
  private final Lbdj; f

  // access flags 0x2
  private Lkn; modelLocation

  // access flags 0x2
  private Z renderItemGui

  // access flags 0x1
  public Lbyp; modelManager

  // access flags 0x2
  private Z renderModelHasEmissive

  // access flags 0x2
  private Z renderModelEmissive

  // access flags 0x1
  public <init>(Lbwf;Lbyp;Lbdj;)V
   L0
    LINENUMBER 90 L0
    ALOAD 0
    INVOKESPECIAL java/lang/Object.<init> ()V
   L1
    LINENUMBER 73 L1
    ALOAD 0
    ICONST_1
    PUTFIELD bsu.c : Z
   L2
    LINENUMBER 82 L2
    ALOAD 0
    ACONST_NULL
    PUTFIELD bsu.modelLocation : Lkn;
   L3
    LINENUMBER 83 L3
    ALOAD 0
    ICONST_0
    PUTFIELD bsu.renderItemGui : Z
   L4
    LINENUMBER 84 L4
    ALOAD 0
    ACONST_NULL
    PUTFIELD bsu.modelManager : Lbyp;
   L5
    LINENUMBER 85 L5
    ALOAD 0
    ICONST_0
    PUTFIELD bsu.renderModelHasEmissive : Z
   L6
    LINENUMBER 86 L6
    ALOAD 0
    ICONST_0
    PUTFIELD bsu.renderModelEmissive : Z
   L7
    LINENUMBER 91 L7
    ALOAD 0
    ALOAD 1
    PUTFIELD bsu.e : Lbwf;
   L8
    LINENUMBER 93 L8
    ALOAD 0
    ALOAD 2
    PUTFIELD bsu.modelManager : Lbyp;
   L9
    LINENUMBER 95 L9
    GETSTATIC Reflector.ItemModelMesherForge_Constructor : LReflectorConstructor;
    INVOKEVIRTUAL ReflectorConstructor.exists ()Z
    IFEQ L10
   L11
    LINENUMBER 96 L11
    ALOAD 0
    GETSTATIC Reflector.ItemModelMesherForge_Constructor : LReflectorConstructor;
    ICONST_1
    ANEWARRAY java/lang/Object
    DUP
    ICONST_0
    ALOAD 2
    AASTORE
    INVOKESTATIC Reflector.newInstance (LReflectorConstructor;[Ljava/lang/Object;)Ljava/lang/Object;
    CHECKCAST boe
    PUTFIELD bsu.d : Lboe;
    GOTO L12
   L10
    LINENUMBER 100 L10
   FRAME FULL [bsu bwf byp bdj] []
    ALOAD 0
    NEW boe
    DUP
    ALOAD 2
    INVOKESPECIAL boe.<init> (Lbyp;)V
    PUTFIELD bsu.d : Lboe;
   L12
    LINENUMBER 104 L12
   FRAME FULL [bsu bwf byp bdj] []
    ALOAD 0
    INVOKESPECIAL bsu.b ()V
   L13
    LINENUMBER 105 L13
    ALOAD 0
    ALOAD 3
    PUTFIELD bsu.f : Lbdj;
   L14
    LINENUMBER 106 L14
    RETURN
   L15
    LOCALVARIABLE this Lbsu; L0 L15 0
    LOCALVARIABLE p_i46552_1_ Lbwf; L0 L15 1
    LOCALVARIABLE p_i46552_2_ Lbyp; L0 L15 2
    LOCALVARIABLE p_i46552_3_ Lbdj; L0 L15 3
    MAXSTACK = 6
    MAXLOCALS = 4

  // access flags 0x1
  public a(Z)V
   L0
    LINENUMBER 113 L0
    ALOAD 0
    ILOAD 1
    PUTFIELD bsu.c : Z
   L1
    LINENUMBER 114 L1
    RETURN
   L2
    LOCALVARIABLE this Lbsu; L0 L2 0
    LOCALVARIABLE isNot Z L0 L2 1
    MAXSTACK = 2
    MAXLOCALS = 2

  // access flags 0x1
  public a()Lboe;
   L0
    LINENUMBER 118 L0
    ALOAD 0
    GETFIELD bsu.d : Lboe;
    ARETURN
   L1
    LOCALVARIABLE this Lbsu; L0 L1 0
    MAXSTACK = 1
    MAXLOCALS = 1

  // access flags 0x4
  protected a(Ladx;ILjava/lang/String;)V
   L0
    LINENUMBER 123 L0
    ALOAD 0
    GETFIELD bsu.d : Lboe;
    ALOAD 1
    ILOAD 2
    NEW byq
    DUP
    ALOAD 3
    LDC "inventory"
    INVOKESPECIAL byq.<init> (Ljava/lang/String;Ljava/lang/String;)V
    INVOKEVIRTUAL boe.a (Ladx;ILbyq;)V
   L1
    LINENUMBER 124 L1
    RETURN
   L2
    LOCALVARIABLE this Lbsu; L0 L2 0
    LOCALVARIABLE itm Ladx; L0 L2 1
    LOCALVARIABLE subType I L0 L2 2
    LOCALVARIABLE identifier Ljava/lang/String; L0 L2 3
    MAXSTACK = 7
    MAXLOCALS = 4

  // access flags 0x4
  protected a(Lakf;ILjava/lang/String;)V
   L0
    LINENUMBER 128 L0
    ALOAD 0
    ALOAD 1
    INVOKESTATIC adx.a (Lakf;)Ladx;
    ILOAD 2
    ALOAD 3
    INVOKEVIRTUAL bsu.a (Ladx;ILjava/lang/String;)V
   L1
    LINENUMBER 129 L1
    RETURN
   L2
    LOCALVARIABLE this Lbsu; L0 L2 0
    LOCALVARIABLE blk Lakf; L0 L2 1
    LOCALVARIABLE subType I L0 L2 2
    LOCALVARIABLE identifier Ljava/lang/String; L0 L2 3
    MAXSTACK = 4
    MAXLOCALS = 4

  // access flags 0x2
  private a(Lakf;Ljava/lang/String;)V
   L0
    LINENUMBER 133 L0
    ALOAD 0
    ALOAD 1
    ICONST_0
    ALOAD 2
    INVOKEVIRTUAL bsu.a (Lakf;ILjava/lang/String;)V
   L1
    LINENUMBER 134 L1
    RETURN
   L2
    LOCALVARIABLE this Lbsu; L0 L2 0
    LOCALVARIABLE blk Lakf; L0 L2 1
    LOCALVARIABLE identifier Ljava/lang/String; L0 L2 2
    MAXSTACK = 4
    MAXLOCALS = 3

  // access flags 0x2
  private a(Ladx;Ljava/lang/String;)V
   L0
    LINENUMBER 138 L0
    ALOAD 0
    ALOAD 1
    ICONST_0
    ALOAD 2
    INVOKEVIRTUAL bsu.a (Ladx;ILjava/lang/String;)V
   L1
    LINENUMBER 139 L1
    RETURN
   L2
    LOCALVARIABLE this Lbsu; L0 L2 0
    LOCALVARIABLE itm Ladx; L0 L2 1
    LOCALVARIABLE identifier Ljava/lang/String; L0 L2 2
    MAXSTACK = 4
    MAXLOCALS = 3

  // access flags 0x2
  private a(Lbyl;Ladz;)V
   L0
    LINENUMBER 143 L0
    ALOAD 0
    ALOAD 1
    ICONST_M1
    ALOAD 2
    INVOKESPECIAL bsu.a (Lbyl;ILadz;)V
   L1
    LINENUMBER 144 L1
    RETURN
   L2
    LOCALVARIABLE this Lbsu; L0 L2 0
    LOCALVARIABLE model Lbyl; L0 L2 1
    LOCALVARIABLE stack Ladz; L0 L2 2
    MAXSTACK = 4
    MAXLOCALS = 3

  // access flags 0x1
  public a(Lbyl;I)V
   L0
    LINENUMBER 149 L0
    ALOAD 0
    ALOAD 1
    ILOAD 2
    ACONST_NULL
    CHECKCAST adz
    INVOKESPECIAL bsu.a (Lbyl;ILadz;)V
   L1
    LINENUMBER 150 L1
    RETURN
   L2
    LOCALVARIABLE this Lbsu; L0 L2 0
    LOCALVARIABLE model Lbyl; L0 L2 1
    LOCALVARIABLE color I L0 L2 2
    MAXSTACK = 4
    MAXLOCALS = 3

  // access flags 0x2
  private a(Lbyl;ILadz;)V
    @Ljavax/annotation/Nullable;() // parameter 2
   L0
    LINENUMBER 154 L0
    INVOKESTATIC bon.a ()Lbon;
    ASTORE 4
   L1
    LINENUMBER 155 L1
    ALOAD 4
    INVOKEVIRTUAL bon.c ()Lbnt;
    ASTORE 5
   L2
    LINENUMBER 157 L2
    INVOKESTATIC bcx.z ()Lbcx;
    INVOKEVIRTUAL bcx.R ()Lbwd;
    INVOKEVIRTUAL bwd.isTextureBound ()Z
    ISTORE 6
   L3
    LINENUMBER 159 L3
    INVOKESTATIC Config.isMultiTexture ()Z
    IFEQ L4
    ILOAD 6
    IFEQ L4
    ICONST_1
    GOTO L5
   L4
   FRAME FULL [bsu byl I adz bon bnt I] []
    ICONST_0
   L5
   FRAME FULL [bsu byl I adz bon bnt I] [I]
    ISTORE 7
   L6
    LINENUMBER 160 L6
    ILOAD 7
    IFEQ L7
   L8
    LINENUMBER 161 L8
    ALOAD 5
    GETSTATIC ahv.a : Lahv;
    INVOKEVIRTUAL bnt.setBlockLayer (Lahv;)V
   L7
    LINENUMBER 163 L7
   FRAME FULL [bsu byl I adz bon bnt I I] []
    ALOAD 5
    BIPUSH 7
    GETSTATIC bwm.b : Lbwo;
    INVOKEVIRTUAL bnt.a (ILbwo;)V
   L9
    LINENUMBER 166 L9
    GETSTATIC ct.n : [Lct;
    ASTORE 8
   L10
    ALOAD 8
    ARRAYLENGTH
    ISTORE 9
   L11
    ICONST_0
    ISTORE 10
   L12
   FRAME FULL [bsu byl I adz bon bnt I I [Lct; I I] []
    ILOAD 10
    ILOAD 9
    IF_ICMPGE L13
    ALOAD 8
    ILOAD 10
    AALOAD
    ASTORE 11
   L14
    LINENUMBER 168 L14
    ALOAD 0
    ALOAD 5
    ALOAD 1
    ACONST_NULL
    CHECKCAST ars
    ALOAD 11
    LCONST_0
    INVOKEINTERFACE byl.a (Lars;Lct;J)Ljava/util/List;
    ILOAD 2
    ALOAD 3
    INVOKESPECIAL bsu.a (Lbnt;Ljava/util/List;ILadz;)V
   L15
    LINENUMBER 166 L15
    IINC 10 1
    GOTO L12
   L13
    LINENUMBER 171 L13
   FRAME FULL [bsu byl I adz bon bnt I I [Lct; I I] []
    ALOAD 0
    ALOAD 5
    ALOAD 1
    ACONST_NULL
    CHECKCAST ars
    ACONST_NULL
    CHECKCAST ct
    LCONST_0
    INVOKEINTERFACE byl.a (Lars;Lct;J)Ljava/util/List;
    ILOAD 2
    ALOAD 3
    INVOKESPECIAL bsu.a (Lbnt;Ljava/util/List;ILadz;)V
   L16
    LINENUMBER 172 L16
    ALOAD 4
    INVOKEVIRTUAL bon.b ()V
   L17
    LINENUMBER 174 L17
    ILOAD 7
    IFEQ L18
   L19
    LINENUMBER 177 L19
    ALOAD 5
    ACONST_NULL
    INVOKEVIRTUAL bnt.setBlockLayer (Lahv;)V
   L20
    LINENUMBER 179 L20
    INVOKESTATIC bob.bindCurrentTexture ()V
   L18
    LINENUMBER 181 L18
   FRAME FULL [bsu byl I adz bon bnt I I [Lct; I I] []
    RETURN
   L21
    LOCALVARIABLE enumfacing Lct; L14 L15 11
    LOCALVARIABLE arr$ [Lct; L10 L13 8
    LOCALVARIABLE len$ I L11 L13 9
    LOCALVARIABLE i$ I L12 L13 10
    LOCALVARIABLE this Lbsu; L0 L21 0
    LOCALVARIABLE model Lbyl; L0 L21 1
    LOCALVARIABLE color I L0 L21 2
    LOCALVARIABLE stack Ladz; L0 L21 3
    LOCALVARIABLE tessellator Lbon; L1 L21 4
    LOCALVARIABLE vertexbuffer Lbnt; L2 L21 5
    LOCALVARIABLE renderTextureMap Z L3 L21 6
    LOCALVARIABLE multiTexture Z L6 L21 7
    MAXSTACK = 7
    MAXLOCALS = 12

  // access flags 0x1
  public a(Ladz;Lbyl;)V
   L0
    LINENUMBER 185 L0
    ALOAD 1
    IFNULL L1
   L2
    LINENUMBER 187 L2
    INVOKESTATIC bob.G ()V
   L3
    LINENUMBER 188 L3
    LDC -0.5
    LDC -0.5
    LDC -0.5
    INVOKESTATIC bob.c (FFF)V
   L4
    LINENUMBER 190 L4
    ALOAD 2
    INVOKEINTERFACE byl.c ()Z
    IFEQ L5
   L6
    LINENUMBER 192 L6
    FCONST_1
    FCONST_1
    FCONST_1
    FCONST_1
    INVOKESTATIC bob.c (FFFF)V
   L7
    LINENUMBER 193 L7
    INVOKESTATIC bob.D ()V
    ALOAD 2
    INSTANCEOF codechicken/lib/render/IItemRenderer
    IFEQ L8
    ALOAD 2
    ALOAD 1
    INVOKEINTERFACE codechicken/lib/render/IItemRenderer.renderItem (Lnet/minecraft/item/ItemStack;)V
    GOTO L9
   L8
    LINENUMBER 194 L8
   FRAME FULL [bsu adz byl] []
    ALOAD 2
    INSTANCEOF codechicken/lib/render/IItemRenderer
    IFEQ L10
    ALOAD 2
    ALOAD 1
    INVOKEINTERFACE codechicken/lib/render/IItemRenderer.renderItem (Lnet/minecraft/item/ItemStack;)V
    GOTO L9
   L10
   FRAME FULL [bsu adz byl] []
    GETSTATIC bnx.a : Lbnx;
    ALOAD 1
    INVOKEVIRTUAL bnx.a (Ladz;)V
    GOTO L9
   L5
    LINENUMBER 199 L5
   FRAME FULL [bsu adz byl] []
    INVOKESTATIC Config.isCustomItems ()Z
    IFEQ L11
   L12
    LINENUMBER 201 L12
    ALOAD 1
    ALOAD 2
    ALOAD 0
    GETFIELD bsu.modelLocation : Lkn;
    ICONST_0
    INVOKESTATIC CustomItems.getCustomItemModel (Ladz;Lbyl;Lkn;Z)Lbyl;
    ASTORE 2
   L13
    LINENUMBER 203 L13
    ALOAD 0
    ACONST_NULL
    PUTFIELD bsu.modelLocation : Lkn;
   L11
    LINENUMBER 206 L11
   FRAME FULL [bsu adz byl] []
    ALOAD 0
    ICONST_0
    PUTFIELD bsu.renderModelHasEmissive : Z
   L14
    LINENUMBER 208 L14
    ALOAD 0
    ALOAD 2
    ALOAD 1
    INVOKESPECIAL bsu.a (Lbyl;Ladz;)V
   L15
    LINENUMBER 210 L15
    ALOAD 0
    GETFIELD bsu.renderModelHasEmissive : Z
    IFEQ L16
   L17
    LINENUMBER 213 L17
    GETSTATIC caf.lastBrightnessX : F
    FSTORE 3
   L18
    LINENUMBER 214 L18
    GETSTATIC caf.lastBrightnessY : F
    FSTORE 4
   L19
    LINENUMBER 215 L19
    GETSTATIC caf.r : I
    LDC 240.0
    FLOAD 4
    INVOKESTATIC caf.a (IFF)V
   L20
    LINENUMBER 217 L20
    ALOAD 0
    ICONST_1
    PUTFIELD bsu.renderModelEmissive : Z
   L21
    LINENUMBER 218 L21
    ALOAD 0
    ALOAD 2
    ALOAD 1
    INVOKESPECIAL bsu.a (Lbyl;Ladz;)V
   L22
    LINENUMBER 219 L22
    ALOAD 0
    ICONST_0
    PUTFIELD bsu.renderModelEmissive : Z
   L23
    LINENUMBER 221 L23
    GETSTATIC caf.r : I
    FLOAD 3
    FLOAD 4
    INVOKESTATIC caf.a (IFF)V
   L16
    LINENUMBER 225 L16
   FRAME FULL [bsu adz byl] []
    ALOAD 1
    INVOKEVIRTUAL adz.t ()Z
    IFEQ L9
   L24
    LINENUMBER 228 L24
    INVOKESTATIC Config.isCustomItems ()Z
    IFEQ L25
    ALOAD 0
    ALOAD 1
    ALOAD 2
    INVOKESTATIC CustomItems.renderCustomEffect (Lbsu;Ladz;Lbyl;)Z
    IFNE L9
   L25
    LINENUMBER 230 L25
   FRAME FULL [bsu adz byl] []
    ALOAD 0
    ALOAD 2
    INVOKESPECIAL bsu.a (Lbyl;)V
   L9
    LINENUMBER 234 L9
   FRAME FULL [bsu adz byl] []
    INVOKESTATIC bob.H ()V
   L1
    LINENUMBER 236 L1
   FRAME FULL [bsu adz byl] []
    RETURN
   L26
    LOCALVARIABLE lightMapX F L18 L16 3
    LOCALVARIABLE lightMapY F L19 L16 4
    LOCALVARIABLE this Lbsu; L0 L26 0
    LOCALVARIABLE stack Ladz; L0 L26 1
    LOCALVARIABLE model Lbyl; L0 L26 2
    MAXSTACK = 4
    MAXLOCALS = 5

  // access flags 0x2
  private a(Lbyl;)V
   L0
    LINENUMBER 241 L0
    INVOKESTATIC Config.isCustomItems ()Z
    IFEQ L1
   L2
    LINENUMBER 243 L2
    INVOKESTATIC CustomItems.isUseGlint ()Z
    IFNE L1
   L3
    LINENUMBER 244 L3
    RETURN
   L1
    LINENUMBER 247 L1
   FRAME FULL [bsu byl] []
    INVOKESTATIC Config.isShaders ()Z
    IFEQ L4
   L5
    LINENUMBER 249 L5
    GETSTATIC shadersmod/client/Shaders.isShadowPass : Z
    IFEQ L4
   L6
    LINENUMBER 250 L6
    RETURN
   L4
    LINENUMBER 253 L4
   FRAME FULL [bsu byl] []
    ICONST_0
    INVOKESTATIC bob.a (Z)V
   L7
    LINENUMBER 254 L7
    SIPUSH 514
    INVOKESTATIC bob.c (I)V
   L8
    LINENUMBER 255 L8
    INVOKESTATIC bob.g ()V
   L9
    LINENUMBER 256 L9
    GETSTATIC bob$r.n : Lbob$r;
    GETSTATIC bob$l.e : Lbob$l;
    INVOKESTATIC bob.a (Lbob$r;Lbob$l;)V
   L10
    LINENUMBER 257 L10
    ALOAD 0
    GETFIELD bsu.e : Lbwf;
    GETSTATIC bsu.b : Lkn;
    INVOKEVIRTUAL bwf.a (Lkn;)V
   L11
    LINENUMBER 259 L11
    INVOKESTATIC Config.isShaders ()Z
    IFEQ L12
   L13
    LINENUMBER 261 L13
    ALOAD 0
    GETFIELD bsu.renderItemGui : Z
    IFNE L12
   L14
    LINENUMBER 262 L14
    INVOKESTATIC shadersmod/client/ShadersRender.renderEnchantedGlintBegin ()V
   L12
    LINENUMBER 265 L12
   FRAME FULL [bsu byl] []
    SIPUSH 5890
    INVOKESTATIC bob.n (I)V
   L15
    LINENUMBER 266 L15
    INVOKESTATIC bob.G ()V
   L16
    LINENUMBER 267 L16
    LDC 8.0
    LDC 8.0
    LDC 8.0
    INVOKESTATIC bob.b (FFF)V
   L17
    LINENUMBER 268 L17
    INVOKESTATIC bcx.I ()J
    LDC 3000
    LREM
    L2F
    LDC 3000.0
    FDIV
    LDC 8.0
    FDIV
    FSTORE 2
   L18
    LINENUMBER 269 L18
    FLOAD 2
    FCONST_0
    FCONST_0
    INVOKESTATIC bob.c (FFF)V
   L19
    LINENUMBER 270 L19
    LDC -50.0
    FCONST_0
    FCONST_0
    FCONST_1
    INVOKESTATIC bob.b (FFFF)V
   L20
    LINENUMBER 271 L20
    ALOAD 0
    ALOAD 1
    LDC -8372020
    INVOKEVIRTUAL bsu.a (Lbyl;I)V
   L21
    LINENUMBER 272 L21
    INVOKESTATIC bob.H ()V
   L22
    LINENUMBER 273 L22
    INVOKESTATIC bob.G ()V
   L23
    LINENUMBER 274 L23
    LDC 8.0
    LDC 8.0
    LDC 8.0
    INVOKESTATIC bob.b (FFF)V
   L24
    LINENUMBER 275 L24
    INVOKESTATIC bcx.I ()J
    LDC 4873
    LREM
    L2F
    LDC 4873.0
    FDIV
    LDC 8.0
    FDIV
    FSTORE 3
   L25
    LINENUMBER 276 L25
    FLOAD 3
    FNEG
    FCONST_0
    FCONST_0
    INVOKESTATIC bob.c (FFF)V
   L26
    LINENUMBER 277 L26
    LDC 10.0
    FCONST_0
    FCONST_0
    FCONST_1
    INVOKESTATIC bob.b (FFFF)V
   L27
    LINENUMBER 278 L27
    ALOAD 0
    ALOAD 1
    LDC -8372020
    INVOKEVIRTUAL bsu.a (Lbyl;I)V
   L28
    LINENUMBER 279 L28
    INVOKESTATIC bob.H ()V
   L29
    LINENUMBER 280 L29
    SIPUSH 5888
    INVOKESTATIC bob.n (I)V
   L30
    LINENUMBER 281 L30
    GETSTATIC bob$r.l : Lbob$r;
    GETSTATIC bob$l.j : Lbob$l;
    INVOKESTATIC bob.a (Lbob$r;Lbob$l;)V
   L31
    LINENUMBER 282 L31
    INVOKESTATIC bob.f ()V
   L32
    LINENUMBER 283 L32
    SIPUSH 515
    INVOKESTATIC bob.c (I)V
   L33
    LINENUMBER 284 L33
    ICONST_1
    INVOKESTATIC bob.a (Z)V
   L34
    LINENUMBER 285 L34
    ALOAD 0
    GETFIELD bsu.e : Lbwf;
    GETSTATIC bwd.g : Lkn;
    INVOKEVIRTUAL bwf.a (Lkn;)V
   L35
    LINENUMBER 287 L35
    INVOKESTATIC Config.isShaders ()Z
    IFEQ L36
   L37
    LINENUMBER 289 L37
    ALOAD 0
    GETFIELD bsu.renderItemGui : Z
    IFNE L36
   L38
    LINENUMBER 290 L38
    INVOKESTATIC shadersmod/client/ShadersRender.renderEnchantedGlintEnd ()V
   L36
    LINENUMBER 292 L36
   FRAME FULL [bsu byl F F] []
    RETURN
   L39
    LOCALVARIABLE this Lbsu; L0 L39 0
    LOCALVARIABLE model Lbyl; L0 L39 1
    LOCALVARIABLE f F L18 L39 2
    LOCALVARIABLE f1 F L25 L39 3
    MAXSTACK = 4
    MAXLOCALS = 4

  // access flags 0x2
  private a(Lbnt;Lboy;)V
   L0
    LINENUMBER 296 L0
    ALOAD 2
    INVOKEVIRTUAL boy.e ()Lct;
    INVOKEVIRTUAL ct.n ()Ldi;
    ASTORE 3
   L1
    LINENUMBER 297 L1
    ALOAD 1
    ALOAD 3
    INVOKEVIRTUAL di.p ()I
    I2F
    ALOAD 3
    INVOKEVIRTUAL di.q ()I
    I2F
    ALOAD 3
    INVOKEVIRTUAL di.r ()I
    I2F
    INVOKEVIRTUAL bnt.b (FFF)V
   L2
    LINENUMBER 298 L2
    RETURN
   L3
    LOCALVARIABLE this Lbsu; L0 L3 0
    LOCALVARIABLE renderer Lbnt; L0 L3 1
    LOCALVARIABLE quad Lboy; L0 L3 2
    LOCALVARIABLE vec3i Ldi; L1 L3 3
    MAXSTACK = 4
    MAXLOCALS = 4

  // access flags 0x2
  private a(Lbnt;Lboy;I)V
   L0
    LINENUMBER 303 L0
    ALOAD 0
    GETFIELD bsu.renderModelEmissive : Z
    IFEQ L1
   L2
    LINENUMBER 305 L2
    ALOAD 2
    INVOKEVIRTUAL boy.getQuadEmissive ()Lboy;
    IFNONNULL L3
   L4
    LINENUMBER 306 L4
    RETURN
   L3
    LINENUMBER 308 L3
   FRAME FULL [bsu bnt boy I] []
    ALOAD 2
    INVOKEVIRTUAL boy.getQuadEmissive ()Lboy;
    ASTORE 2
    GOTO L5
   L1
    LINENUMBER 312 L1
   FRAME FULL [bsu bnt boy I] []
    ALOAD 2
    INVOKEVIRTUAL boy.getQuadEmissive ()Lboy;
    IFNULL L5
   L6
    LINENUMBER 313 L6
    ALOAD 0
    ICONST_1
    PUTFIELD bsu.renderModelHasEmissive : Z
   L5
    LINENUMBER 316 L5
   FRAME FULL [bsu bnt boy I] []
    ALOAD 1
    INVOKEVIRTUAL bnt.isMultiTexture ()Z
    IFEQ L7
   L8
    LINENUMBER 318 L8
    ALOAD 1
    ALOAD 2
    INVOKEVIRTUAL boy.getVertexDataSingle ()[I
    INVOKEVIRTUAL bnt.a ([I)V
   L9
    LINENUMBER 319 L9
    ALOAD 1
    ALOAD 2
    INVOKEVIRTUAL boy.a ()Lbwe;
    INVOKEVIRTUAL bnt.putSprite (Lbwe;)V
    GOTO L10
   L7
    LINENUMBER 324 L7
   FRAME FULL [bsu bnt boy I] []
    ALOAD 1
    ALOAD 2
    INVOKEVIRTUAL boy.b ()[I
    INVOKEVIRTUAL bnt.a ([I)V
   L10
    LINENUMBER 328 L10
   FRAME FULL [bsu bnt boy I] []
    GETSTATIC Reflector.ForgeHooksClient_putQuadColor : LReflectorMethod;
    INVOKEVIRTUAL ReflectorMethod.exists ()Z
    IFEQ L11
   L12
    LINENUMBER 329 L12
    GETSTATIC Reflector.ForgeHooksClient_putQuadColor : LReflectorMethod;
    ICONST_3
    ANEWARRAY java/lang/Object
    DUP
    ICONST_0
    ALOAD 1
    AASTORE
    DUP
    ICONST_1
    ALOAD 2
    AASTORE
    DUP
    ICONST_2
    ILOAD 3
    INVOKESTATIC java/lang/Integer.valueOf (I)Ljava/lang/Integer;
    AASTORE
    INVOKESTATIC Reflector.call (LReflectorMethod;[Ljava/lang/Object;)Ljava/lang/Object;
    POP
    GOTO L13
   L11
    LINENUMBER 332 L11
   FRAME FULL [bsu bnt boy I] []
    ALOAD 1
    ILOAD 3
    INVOKEVIRTUAL bnt.a (I)V
   L13
    LINENUMBER 333 L13
   FRAME FULL [bsu bnt boy I] []
    ALOAD 0
    ALOAD 1
    ALOAD 2
    INVOKESPECIAL bsu.a (Lbnt;Lboy;)V
   L14
    LINENUMBER 334 L14
    RETURN
   L15
    LOCALVARIABLE this Lbsu; L0 L15 0
    LOCALVARIABLE renderer Lbnt; L0 L15 1
    LOCALVARIABLE quad Lboy; L0 L15 2
    LOCALVARIABLE color I L0 L15 3
    MAXSTACK = 5
    MAXLOCALS = 4

  // access flags 0x2
  // signature (Lbnt;Ljava/util/List<Lboy;>;ILadz;)V
  // declaration: void a(bnt, java.util.List<boy>, int, adz)
  private a(Lbnt;Ljava/util/List;ILadz;)V
    @Ljavax/annotation/Nullable;() // parameter 3
   L0
    LINENUMBER 338 L0
    ILOAD 3
    ICONST_M1
    IF_ICMPNE L1
    ALOAD 4
    IFNULL L1
    ICONST_1
    GOTO L2
   L1
   FRAME FULL [bsu bnt java/util/List I adz] []
    ICONST_0
   L2
   FRAME FULL [bsu bnt java/util/List I adz] [I]
    ISTORE 5
   L3
    LINENUMBER 339 L3
    ICONST_0
    ISTORE 6
   L4
    LINENUMBER 341 L4
    ALOAD 2
    INVOKEINTERFACE java/util/List.size ()I
    ISTORE 7
   L5
   FRAME FULL [bsu bnt java/util/List I adz I I I] []
    ILOAD 6
    ILOAD 7
    IF_ICMPGE L6
   L7
    LINENUMBER 343 L7
    ALOAD 2
    ILOAD 6
    INVOKEINTERFACE java/util/List.get (I)Ljava/lang/Object;
    CHECKCAST boy
    ASTORE 8
   L8
    LINENUMBER 344 L8
    ILOAD 3
    ISTORE 9
   L9
    LINENUMBER 346 L9
    ILOAD 5
    IFEQ L10
    ALOAD 8
    INVOKEVIRTUAL boy.c ()Z
    IFEQ L10
   L11
    LINENUMBER 348 L11
    ALOAD 0
    GETFIELD bsu.f : Lbdj;
    ALOAD 4
    ALOAD 8
    INVOKEVIRTUAL boy.d ()I
    INVOKEVIRTUAL bdj.a (Ladz;I)I
    ISTORE 9
   L12
    LINENUMBER 350 L12
    INVOKESTATIC Config.isCustomColors ()Z
    IFEQ L13
   L14
    LINENUMBER 351 L14
    ALOAD 4
    ALOAD 8
    INVOKEVIRTUAL boy.d ()I
    ILOAD 9
    INVOKESTATIC CustomColors.getColorFromItemStack (Ladz;II)I
    ISTORE 9
   L13
    LINENUMBER 354 L13
   FRAME FULL [bsu bnt java/util/List I adz I I I boy I] []
    GETSTATIC bnz.a : Z
    IFEQ L15
   L16
    LINENUMBER 356 L16
    ILOAD 9
    INVOKESTATIC bwh.c (I)I
    ISTORE 9
   L15
    LINENUMBER 359 L15
   FRAME FULL [bsu bnt java/util/List I adz I I I boy I] []
    ILOAD 9
    LDC -16777216
    IOR
    ISTORE 9
   L10
    LINENUMBER 363 L10
   FRAME FULL [bsu bnt java/util/List I adz I I I boy I] []
    ALOAD 0
    ALOAD 1
    ALOAD 8
    ILOAD 9
    INVOKESPECIAL bsu.a (Lbnt;Lboy;I)V
   L17
    LINENUMBER 341 L17
    IINC 6 1
    GOTO L5
   L6
    LINENUMBER 365 L6
   FRAME FULL [bsu bnt java/util/List I adz I I I] []
    RETURN
   L18
    LOCALVARIABLE bakedquad Lboy; L8 L17 8
    LOCALVARIABLE k I L9 L17 9
    LOCALVARIABLE j I L5 L6 7
    LOCALVARIABLE this Lbsu; L0 L18 0
    LOCALVARIABLE renderer Lbnt; L0 L18 1
    LOCALVARIABLE quads Ljava/util/List; L0 L18 2
    // signature Ljava/util/List<Lboy;>;
    // declaration: java.util.List<boy>
    LOCALVARIABLE color I L0 L18 3
    LOCALVARIABLE stack Ladz; L0 L18 4
    LOCALVARIABLE flag Z L3 L18 5
    LOCALVARIABLE i I L4 L18 6
    MAXSTACK = 4
    MAXLOCALS = 10

  // access flags 0x1
  public a(Ladz;)Z
   L0
    LINENUMBER 369 L0
    ALOAD 0
    GETFIELD bsu.d : Lboe;
    ALOAD 1
    INVOKEVIRTUAL boe.a (Ladz;)Lbyl;
    ASTORE 2
   L1
    LINENUMBER 370 L1
    ALOAD 2
    IFNONNULL L2
    ICONST_0
    GOTO L3
   L2
   FRAME FULL [bsu adz byl] []
    ALOAD 2
    INVOKEINTERFACE byl.b ()Z
   L3
   FRAME FULL [bsu adz byl] [I]
    IRETURN
   L4
    LOCALVARIABLE this Lbsu; L0 L4 0
    LOCALVARIABLE stack Ladz; L0 L4 1
    LOCALVARIABLE ibakedmodel Lbyl; L1 L4 2
    MAXSTACK = 2
    MAXLOCALS = 3

  // access flags 0x1
  public a(Ladz;Lbpl$b;)V
   L0
    LINENUMBER 375 L0
    ALOAD 1
    IFNULL L1
   L2
    LINENUMBER 377 L2
    ALOAD 0
    ALOAD 1
    ACONST_NULL
    CHECKCAST aid
    ACONST_NULL
    CHECKCAST sf
    INVOKEVIRTUAL bsu.a (Ladz;Laid;Lsf;)Lbyl;
    ASTORE 3
   L3
    LINENUMBER 378 L3
    ALOAD 0
    ALOAD 1
    ALOAD 3
    ALOAD 2
    ICONST_0
    INVOKEVIRTUAL bsu.a (Ladz;Lbyl;Lbpl$b;Z)V
   L1
    LINENUMBER 380 L1
   FRAME FULL [bsu adz bpl$b] []
    RETURN
   L4
    LOCALVARIABLE ibakedmodel Lbyl; L3 L1 3
    LOCALVARIABLE this Lbsu; L0 L4 0
    LOCALVARIABLE stack Ladz; L0 L4 1
    LOCALVARIABLE cameraTransformType Lbpl$b; L0 L4 2
    MAXSTACK = 5
    MAXLOCALS = 4

  // access flags 0x1
  public a(Ladz;Laid;Lsf;)Lbyl;
    @Ljavax/annotation/Nullable;() // parameter 1
    @Ljavax/annotation/Nullable;() // parameter 2
   L0
    LINENUMBER 384 L0
    ALOAD 0
    GETFIELD bsu.d : Lboe;
    ALOAD 1
    INVOKEVIRTUAL boe.a (Ladz;)Lbyl;
    ASTORE 4
   L1
    LINENUMBER 385 L1
    ALOAD 1
    INVOKEVIRTUAL adz.b ()Ladx;
    ASTORE 5
   L2
    LINENUMBER 387 L2
    INVOKESTATIC Config.isCustomItems ()Z
    IFEQ L3
   L4
    LINENUMBER 390 L4
    ALOAD 5
    IFNULL L5
    ALOAD 5
    INVOKEVIRTUAL adx.i ()Z
    IFEQ L5
   L6
    LINENUMBER 391 L6
    ALOAD 0
    ALOAD 4
    INVOKEINTERFACE byl.f ()Lbpj;
    ALOAD 1
    ALOAD 2
    ALOAD 3
    INVOKEVIRTUAL bpj.a (Ladz;Laid;Lsf;)Lkn;
    PUTFIELD bsu.modelLocation : Lkn;
   L5
    LINENUMBER 393 L5
   FRAME FULL [bsu adz aid sf byl adx] []
    ALOAD 1
    ALOAD 4
    ALOAD 0
    GETFIELD bsu.modelLocation : Lkn;
    ICONST_1
    INVOKESTATIC CustomItems.getCustomItemModel (Ladz;Lbyl;Lkn;Z)Lbyl;
    ASTORE 6
   L7
    LINENUMBER 394 L7
    ALOAD 6
    ALOAD 4
    IF_ACMPEQ L3
   L8
    LINENUMBER 395 L8
    ALOAD 6
    ARETURN
   L3
    LINENUMBER 398 L3
   FRAME FULL [bsu adz aid sf byl adx] []
    GETSTATIC Reflector.ForgeItemOverrideList_handleItemState : LReflectorMethod;
    INVOKEVIRTUAL ReflectorMethod.exists ()Z
    IFEQ L9
   L10
    LINENUMBER 399 L10
    ALOAD 4
    INVOKEINTERFACE byl.f ()Lbpj;
    GETSTATIC Reflector.ForgeItemOverrideList_handleItemState : LReflectorMethod;
    ICONST_4
    ANEWARRAY java/lang/Object
    DUP
    ICONST_0
    ALOAD 4
    AASTORE
    DUP
    ICONST_1
    ALOAD 1
    AASTORE
    DUP
    ICONST_2
    ALOAD 2
    AASTORE
    DUP
    ICONST_3
    ALOAD 3
    AASTORE
    INVOKESTATIC Reflector.call (Ljava/lang/Object;LReflectorMethod;[Ljava/lang/Object;)Ljava/lang/Object;
    CHECKCAST byl
    ARETURN
   L9
    LINENUMBER 401 L9
   FRAME FULL [bsu adz aid sf byl adx] []
    ALOAD 5
    IFNULL L11
    ALOAD 5
    INVOKEVIRTUAL adx.i ()Z
    IFEQ L11
   L12
    LINENUMBER 403 L12
    ALOAD 4
    INVOKEINTERFACE byl.f ()Lbpj;
    ALOAD 1
    ALOAD 2
    ALOAD 3
    INVOKEVIRTUAL bpj.a (Ladz;Laid;Lsf;)Lkn;
    ASTORE 6
   L13
    LINENUMBER 404 L13
    ALOAD 6
    IFNONNULL L14
    ALOAD 4
    GOTO L15
   L14
   FRAME FULL [bsu adz aid sf byl adx kn] []
    ALOAD 0
    GETFIELD bsu.d : Lboe;
    INVOKEVIRTUAL boe.a ()Lbyp;
    NEW byq
    DUP
    ALOAD 6
    LDC "inventory"
    INVOKESPECIAL byq.<init> (Lkn;Ljava/lang/String;)V
    INVOKEVIRTUAL byp.a (Lbyq;)Lbyl;
   L15
   FRAME FULL [bsu adz aid sf byl adx kn] [byl]
    ARETURN
   L11
    LINENUMBER 408 L11
   FRAME FULL [bsu adz aid sf byl adx] []
    ALOAD 4
    ARETURN
   L16
    LOCALVARIABLE modelFull Lbyl; L7 L3 6
    LOCALVARIABLE resourcelocation Lkn; L13 L11 6
    LOCALVARIABLE this Lbsu; L0 L16 0
    LOCALVARIABLE stack Ladz; L0 L16 1
    LOCALVARIABLE worldIn Laid; L0 L16 2
    LOCALVARIABLE entitylivingbaseIn Lsf; L0 L16 3
    LOCALVARIABLE ibakedmodel Lbyl; L1 L16 4
    LOCALVARIABLE item Ladx; L2 L16 5
    MAXSTACK = 6
    MAXLOCALS = 7

  // access flags 0x1
  public a(Ladz;Lsf;Lbpl$b;Z)V
   L0
    LINENUMBER 414 L0
    ALOAD 1
    IFNULL L1
    ALOAD 2
    IFNULL L1
    ALOAD 1
    INVOKEVIRTUAL adz.b ()Ladx;
    IFNULL L1
   L2
    LINENUMBER 416 L2
    ALOAD 0
    ALOAD 1
    ALOAD 2
    GETFIELD sf.l : Laid;
    ALOAD 2
    INVOKEVIRTUAL bsu.a (Ladz;Laid;Lsf;)Lbyl;
    ASTORE 5
   L3
    LINENUMBER 417 L3
    ALOAD 0
    ALOAD 1
    ALOAD 5
    ALOAD 3
    ILOAD 4
    INVOKEVIRTUAL bsu.a (Ladz;Lbyl;Lbpl$b;Z)V
   L1
    LINENUMBER 419 L1
   FRAME FULL [bsu adz sf bpl$b I] []
    RETURN
   L4
    LOCALVARIABLE ibakedmodel Lbyl; L3 L1 5
    LOCALVARIABLE this Lbsu; L0 L4 0
    LOCALVARIABLE stack Ladz; L0 L4 1
    LOCALVARIABLE entitylivingbaseIn Lsf; L0 L4 2
    LOCALVARIABLE transform Lbpl$b; L0 L4 3
    LOCALVARIABLE leftHanded Z L0 L4 4
    MAXSTACK = 5
    MAXLOCALS = 6

  // access flags 0x4
  protected a(Ladz;Lbyl;Lbpl$b;Z)V
   L0
    LINENUMBER 423 L0
    ALOAD 1
    INVOKEVIRTUAL adz.b ()Ladx;
    IFNULL L1
   L2
    LINENUMBER 425 L2
    ALOAD 0
    GETFIELD bsu.e : Lbwf;
    GETSTATIC bwd.g : Lkn;
    INVOKEVIRTUAL bwf.a (Lkn;)V
   L3
    LINENUMBER 426 L3
    ALOAD 0
    GETFIELD bsu.e : Lbwf;
    GETSTATIC bwd.g : Lkn;
    INVOKEVIRTUAL bwf.b (Lkn;)Lbwg;
    ICONST_0
    ICONST_0
    INVOKEINTERFACE bwg.b (ZZ)V
   L4
    LINENUMBER 427 L4
    FCONST_1
    FCONST_1
    FCONST_1
    FCONST_1
    INVOKESTATIC bob.c (FFFF)V
   L5
    LINENUMBER 428 L5
    INVOKESTATIC bob.D ()V
   L6
    LINENUMBER 429 L6
    SIPUSH 516
    LDC 0.1
    INVOKESTATIC bob.a (IF)V
   L7
    LINENUMBER 430 L7
    INVOKESTATIC bob.m ()V
   L8
    LINENUMBER 431 L8
    GETSTATIC bob$r.l : Lbob$r;
    GETSTATIC bob$l.j : Lbob$l;
    GETSTATIC bob$r.e : Lbob$r;
    GETSTATIC bob$l.n : Lbob$l;
    INVOKESTATIC bob.a (Lbob$r;Lbob$l;Lbob$r;Lbob$l;)V
   L9
    LINENUMBER 432 L9
    INVOKESTATIC bob.G ()V
   L10
    LINENUMBER 434 L10
    GETSTATIC Reflector.ForgeHooksClient_handleCameraTransforms : LReflectorMethod;
    INVOKEVIRTUAL ReflectorMethod.exists ()Z
    IFEQ L11
   L12
    LINENUMBER 437 L12
    GETSTATIC Reflector.ForgeHooksClient_handleCameraTransforms : LReflectorMethod;
    ICONST_3
    ANEWARRAY java/lang/Object
    DUP
    ICONST_0
    ALOAD 2
    AASTORE
    DUP
    ICONST_1
    ALOAD 3
    AASTORE
    DUP
    ICONST_2
    ILOAD 4
    INVOKESTATIC java/lang/Boolean.valueOf (Z)Ljava/lang/Boolean;
    AASTORE
    INVOKESTATIC Reflector.call (LReflectorMethod;[Ljava/lang/Object;)Ljava/lang/Object;
    CHECKCAST byl
    ASTORE 2
    GOTO L13
   L11
    LINENUMBER 442 L11
   FRAME FULL [bsu adz byl bpl$b I] []
    ALOAD 2
    INVOKEINTERFACE byl.e ()Lbpl;
    ASTORE 5
   L14
    LINENUMBER 443 L14
    ALOAD 5
    ALOAD 3
    INVOKEVIRTUAL bpl.b (Lbpl$b;)Lbpk;
    ILOAD 4
    INVOKESTATIC bpl.a (Lbpk;Z)V
   L15
    LINENUMBER 445 L15
    ALOAD 0
    ALOAD 5
    ALOAD 3
    INVOKEVIRTUAL bpl.b (Lbpl$b;)Lbpk;
    INVOKESPECIAL bsu.a (Lbpk;)Z
    IFEQ L13
   L16
    LINENUMBER 447 L16
    GETSTATIC bob$i.a : Lbob$i;
    INVOKESTATIC bob.a (Lbob$i;)V
   L13
    LINENUMBER 452 L13
   FRAME FULL [bsu adz byl bpl$b I] []
    ILOAD 4
    INVOKESTATIC CustomItems.setRenderOffHand (Z)V
   L17
    LINENUMBER 454 L17
    ALOAD 0
    ALOAD 1
    ALOAD 2
    INVOKEVIRTUAL bsu.a (Ladz;Lbyl;)V
   L18
    LINENUMBER 456 L18
    ICONST_0
    INVOKESTATIC CustomItems.setRenderOffHand (Z)V
   L19
    LINENUMBER 458 L19
    GETSTATIC bob$i.b : Lbob$i;
    INVOKESTATIC bob.a (Lbob$i;)V
   L20
    LINENUMBER 459 L20
    INVOKESTATIC bob.H ()V
   L21
    LINENUMBER 460 L21
    INVOKESTATIC bob.E ()V
   L22
    LINENUMBER 461 L22
    INVOKESTATIC bob.l ()V
   L23
    LINENUMBER 462 L23
    ALOAD 0
    GETFIELD bsu.e : Lbwf;
    GETSTATIC bwd.g : Lkn;
    INVOKEVIRTUAL bwf.a (Lkn;)V
   L24
    LINENUMBER 463 L24
    ALOAD 0
    GETFIELD bsu.e : Lbwf;
    GETSTATIC bwd.g : Lkn;
    INVOKEVIRTUAL bwf.b (Lkn;)Lbwg;
    INVOKEINTERFACE bwg.a ()V
   L1
    LINENUMBER 465 L1
   FRAME FULL [bsu adz byl bpl$b I] []
    RETURN
   L25
    LOCALVARIABLE itemcameratransforms Lbpl; L14 L13 5
    LOCALVARIABLE this Lbsu; L0 L25 0
    LOCALVARIABLE stack Ladz; L0 L25 1
    LOCALVARIABLE bakedmodel Lbyl; L0 L25 2
    LOCALVARIABLE transform Lbpl$b; L0 L25 3
    LOCALVARIABLE leftHanded Z L0 L25 4
    MAXSTACK = 5
    MAXLOCALS = 6

  // access flags 0x2
  private a(Lbpk;)Z
   L0
    LINENUMBER 472 L0
    ALOAD 1
    GETFIELD bpk.d : Lorg/lwjgl/util/vector/Vector3f;
    GETFIELD org/lwjgl/util/vector/Vector3f.x : F
    FCONST_0
    FCMPG
    IFGE L1
    ICONST_1
    GOTO L2
   L1
   FRAME FULL [bsu bpk] []
    ICONST_0
   L2
   FRAME FULL [bsu bpk] [I]
    ALOAD 1
    GETFIELD bpk.d : Lorg/lwjgl/util/vector/Vector3f;
    GETFIELD org/lwjgl/util/vector/Vector3f.y : F
    FCONST_0
    FCMPG
    IFGE L3
    ICONST_1
    GOTO L4
   L3
   FRAME FULL [bsu bpk] [I]
    ICONST_0
   L4
   FRAME FULL [bsu bpk] [I I]
    IXOR
    ALOAD 1
    GETFIELD bpk.d : Lorg/lwjgl/util/vector/Vector3f;
    GETFIELD org/lwjgl/util/vector/Vector3f.z : F
    FCONST_0
    FCMPG
    IFGE L5
    ICONST_1
    GOTO L6
   L5
   FRAME FULL [bsu bpk] [I]
    ICONST_0
   L6
   FRAME FULL [bsu bpk] [I I]
    IXOR
    IRETURN
   L7
    LOCALVARIABLE this Lbsu; L0 L7 0
    LOCALVARIABLE itemTranformVec Lbpk; L0 L7 1
    MAXSTACK = 3
    MAXLOCALS = 2

  // access flags 0x1
  public a(Ladz;II)V
   L0
    LINENUMBER 477 L0
    ALOAD 0
    ALOAD 1
    ILOAD 2
    ILOAD 3
    ALOAD 0
    ALOAD 1
    ACONST_NULL
    CHECKCAST aid
    ACONST_NULL
    CHECKCAST sf
    INVOKEVIRTUAL bsu.a (Ladz;Laid;Lsf;)Lbyl;
    INVOKEVIRTUAL bsu.a (Ladz;IILbyl;)V
   L1
    LINENUMBER 478 L1
    RETURN
   L2
    LOCALVARIABLE this Lbsu; L0 L2 0
    LOCALVARIABLE stack Ladz; L0 L2 1
    LOCALVARIABLE x I L0 L2 2
    LOCALVARIABLE y I L0 L2 3
    MAXSTACK = 8
    MAXLOCALS = 4

  // access flags 0x4
  protected a(Ladz;IILbyl;)V
   L0
    LINENUMBER 483 L0
    ALOAD 0
    ICONST_1
    PUTFIELD bsu.renderItemGui : Z
   L1
    LINENUMBER 485 L1
    INVOKESTATIC bob.G ()V
   L2
    LINENUMBER 486 L2
    ALOAD 0
    GETFIELD bsu.e : Lbwf;
    GETSTATIC bwd.g : Lkn;
    INVOKEVIRTUAL bwf.a (Lkn;)V
   L3
    LINENUMBER 487 L3
    ALOAD 0
    GETFIELD bsu.e : Lbwf;
    GETSTATIC bwd.g : Lkn;
    INVOKEVIRTUAL bwf.b (Lkn;)Lbwg;
    ICONST_0
    ICONST_0
    INVOKEINTERFACE bwg.b (ZZ)V
   L4
    LINENUMBER 488 L4
    INVOKESTATIC bob.D ()V
   L5
    LINENUMBER 489 L5
    INVOKESTATIC bob.e ()V
   L6
    LINENUMBER 490 L6
    SIPUSH 516
    LDC 0.1
    INVOKESTATIC bob.a (IF)V
   L7
    LINENUMBER 491 L7
    INVOKESTATIC bob.m ()V
   L8
    LINENUMBER 492 L8
    GETSTATIC bob$r.l : Lbob$r;
    GETSTATIC bob$l.j : Lbob$l;
    INVOKESTATIC bob.a (Lbob$r;Lbob$l;)V
   L9
    LINENUMBER 493 L9
    FCONST_1
    FCONST_1
    FCONST_1
    FCONST_1
    INVOKESTATIC bob.c (FFFF)V
   L10
    LINENUMBER 494 L10
    ALOAD 0
    ILOAD 2
    ILOAD 3
    ALOAD 4
    INVOKEINTERFACE byl.b ()Z
    INVOKESPECIAL bsu.a (IIZ)V
   L11
    LINENUMBER 496 L11
    GETSTATIC Reflector.ForgeHooksClient_handleCameraTransforms : LReflectorMethod;
    INVOKEVIRTUAL ReflectorMethod.exists ()Z
    IFEQ L12
   L13
    LINENUMBER 499 L13
    GETSTATIC Reflector.ForgeHooksClient_handleCameraTransforms : LReflectorMethod;
    ICONST_3
    ANEWARRAY java/lang/Object
    DUP
    ICONST_0
    ALOAD 4
    AASTORE
    DUP
    ICONST_1
    GETSTATIC bpl$b.g : Lbpl$b;
    AASTORE
    DUP
    ICONST_2
    ICONST_0
    INVOKESTATIC java/lang/Boolean.valueOf (Z)Ljava/lang/Boolean;
    AASTORE
    INVOKESTATIC Reflector.call (LReflectorMethod;[Ljava/lang/Object;)Ljava/lang/Object;
    CHECKCAST byl
    ASTORE 4
    GOTO L14
   L12
    LINENUMBER 504 L12
   FRAME FULL [bsu adz I I byl] []
    ALOAD 4
    INVOKEINTERFACE byl.e ()Lbpl;
    GETSTATIC bpl$b.g : Lbpl$b;
    INVOKEVIRTUAL bpl.a (Lbpl$b;)V
   L14
    LINENUMBER 508 L14
   FRAME FULL [bsu adz I I byl] []
    ALOAD 0
    ALOAD 1
    ALOAD 4
    INVOKEVIRTUAL bsu.a (Ladz;Lbyl;)V
   L15
    LINENUMBER 509 L15
    INVOKESTATIC bob.d ()V
   L16
    LINENUMBER 510 L16
    INVOKESTATIC bob.E ()V
   L17
    LINENUMBER 511 L17
    INVOKESTATIC bob.g ()V
   L18
    LINENUMBER 512 L18
    INVOKESTATIC bob.H ()V
   L19
    LINENUMBER 513 L19
    ALOAD 0
    GETFIELD bsu.e : Lbwf;
    GETSTATIC bwd.g : Lkn;
    INVOKEVIRTUAL bwf.a (Lkn;)V
   L20
    LINENUMBER 514 L20
    ALOAD 0
    GETFIELD bsu.e : Lbwf;
    GETSTATIC bwd.g : Lkn;
    INVOKEVIRTUAL bwf.b (Lkn;)Lbwg;
    INVOKEINTERFACE bwg.a ()V
   L21
    LINENUMBER 516 L21
    ALOAD 0
    ICONST_0
    PUTFIELD bsu.renderItemGui : Z
   L22
    LINENUMBER 518 L22
    RETURN
   L23
    LOCALVARIABLE this Lbsu; L0 L23 0
    LOCALVARIABLE stack Ladz; L0 L23 1
    LOCALVARIABLE x I L0 L23 2
    LOCALVARIABLE y I L0 L23 3
    LOCALVARIABLE bakedmodel Lbyl; L0 L23 4
    MAXSTACK = 5
    MAXLOCALS = 5

  // access flags 0x2
  private a(IIZ)V
   L0
    LINENUMBER 522 L0
    ILOAD 1
    I2F
    ILOAD 2
    I2F
    LDC 100.0
    ALOAD 0
    GETFIELD bsu.a : F
    FADD
    INVOKESTATIC bob.c (FFF)V
   L1
    LINENUMBER 523 L1
    LDC 8.0
    LDC 8.0
    FCONST_0
    INVOKESTATIC bob.c (FFF)V
   L2
    LINENUMBER 524 L2
    FCONST_1
    LDC -1.0
    FCONST_1
    INVOKESTATIC bob.b (FFF)V
   L3
    LINENUMBER 525 L3
    LDC 16.0
    LDC 16.0
    LDC 16.0
    INVOKESTATIC bob.b (FFF)V
   L4
    LINENUMBER 527 L4
    ILOAD 3
    IFEQ L5
   L6
    LINENUMBER 529 L6
    INVOKESTATIC bob.f ()V
    GOTO L7
   L5
    LINENUMBER 533 L5
   FRAME FULL [bsu I I I] []
    INVOKESTATIC bob.g ()V
   L7
    LINENUMBER 535 L7
   FRAME FULL [bsu I I I] []
    RETURN
   L8
    LOCALVARIABLE this Lbsu; L0 L8 0
    LOCALVARIABLE xPosition I L0 L8 1
    LOCALVARIABLE yPosition I L0 L8 2
    LOCALVARIABLE isGui3d Z L0 L8 3
    MAXSTACK = 4
    MAXLOCALS = 4

  // access flags 0x1
  public b(Ladz;II)V
   L0
    LINENUMBER 539 L0
    ALOAD 0
    INVOKESTATIC bcx.z ()Lbcx;
    GETFIELD bcx.h : Lbnn;
    ALOAD 1
    ILOAD 2
    ILOAD 3
    INVOKEVIRTUAL bsu.a (Lsf;Ladz;II)V
   L1
    LINENUMBER 540 L1
    RETURN
   L2
    LOCALVARIABLE this Lbsu; L0 L2 0
    LOCALVARIABLE stack Ladz; L0 L2 1
    LOCALVARIABLE xPosition I L0 L2 2
    LOCALVARIABLE yPosition I L0 L2 3
    MAXSTACK = 5
    MAXLOCALS = 4

  // access flags 0x1
  public a(Lsf;Ladz;II)V
    @Ljavax/annotation/Nullable;() // parameter 0
    TRYCATCHBLOCK L0 L1 L2 java/lang/Throwable
   L3
    LINENUMBER 544 L3
    ALOAD 2
    IFNULL L4
    ALOAD 2
    INVOKEVIRTUAL adz.b ()Ladx;
    IFNULL L4
   L5
    LINENUMBER 546 L5
    ALOAD 0
    DUP
    GETFIELD bsu.a : F
    LDC 50.0
    FADD
    PUTFIELD bsu.a : F
   L0
    LINENUMBER 550 L0
    ALOAD 0
    ALOAD 2
    ILOAD 3
    ILOAD 4
    ALOAD 0
    ALOAD 2
    ACONST_NULL
    CHECKCAST aid
    ALOAD 1
    INVOKEVIRTUAL bsu.a (Ladz;Laid;Lsf;)Lbyl;
    INVOKEVIRTUAL bsu.a (Ladz;IILbyl;)V
   L1
    LINENUMBER 585 L1
    GOTO L6
   L2
    LINENUMBER 552 L2
   FRAME FULL [bsu sf adz I I] [java/lang/Throwable]
    ASTORE 5
   L7
    LINENUMBER 554 L7
    ALOAD 5
    LDC "Rendering item"
    INVOKESTATIC b.a (Ljava/lang/Throwable;Ljava/lang/String;)Lb;
    ASTORE 6
   L8
    LINENUMBER 555 L8
    ALOAD 6
    LDC "Item being rendered"
    INVOKEVIRTUAL b.a (Ljava/lang/String;)Lc;
    ASTORE 7
   L9
    LINENUMBER 556 L9
    ALOAD 7
    LDC "Item Type"
    NEW bsu$1
    DUP
    ALOAD 0
    ALOAD 2
    INVOKESPECIAL bsu$1.<init> (Lbsu;Ladz;)V
    INVOKEVIRTUAL c.a (Ljava/lang/String;Ld;)V
   L10
    LINENUMBER 563 L10
    ALOAD 7
    LDC "Item Aux"
    NEW bsu$2
    DUP
    ALOAD 0
    ALOAD 2
    INVOKESPECIAL bsu$2.<init> (Lbsu;Ladz;)V
    INVOKEVIRTUAL c.a (Ljava/lang/String;Ld;)V
   L11
    LINENUMBER 570 L11
    ALOAD 7
    LDC "Item NBT"
    NEW bsu$3
    DUP
    ALOAD 0
    ALOAD 2
    INVOKESPECIAL bsu$3.<init> (Lbsu;Ladz;)V
    INVOKEVIRTUAL c.a (Ljava/lang/String;Ld;)V
   L12
    LINENUMBER 577 L12
    ALOAD 7
    LDC "Item Foil"
    NEW bsu$4
    DUP
    ALOAD 0
    ALOAD 2
    INVOKESPECIAL bsu$4.<init> (Lbsu;Ladz;)V
    INVOKEVIRTUAL c.a (Ljava/lang/String;Ld;)V
   L13
    LINENUMBER 584 L13
    NEW f
    DUP
    ALOAD 6
    INVOKESPECIAL f.<init> (Lb;)V
    ATHROW
   L6
    LINENUMBER 587 L6
   FRAME FULL [bsu sf adz I I] []
    ALOAD 0
    DUP
    GETFIELD bsu.a : F
    LDC 50.0
    FSUB
    PUTFIELD bsu.a : F
   L4
    LINENUMBER 589 L4
   FRAME FULL [bsu sf adz I I] []
    RETURN
   L14
    LOCALVARIABLE crashreport Lb; L8 L6 6
    LOCALVARIABLE crashreportcategory Lc; L9 L6 7
    LOCALVARIABLE throwable Ljava/lang/Throwable; L7 L6 5
    LOCALVARIABLE this Lbsu; L3 L14 0
    LOCALVARIABLE p_184391_1_ Lsf; L3 L14 1
    LOCALVARIABLE p_184391_2_ Ladz; L3 L14 2
    LOCALVARIABLE p_184391_3_ I L3 L14 3
    LOCALVARIABLE p_184391_4_ I L3 L14 4
    MAXSTACK = 8
    MAXLOCALS = 8

  // access flags 0x1
  public a(Lbdl;Ladz;II)V
   L0
    LINENUMBER 593 L0
    ALOAD 0
    ALOAD 1
    ALOAD 2
    ILOAD 3
    ILOAD 4
    ACONST_NULL
    CHECKCAST java/lang/String
    INVOKEVIRTUAL bsu.a (Lbdl;Ladz;IILjava/lang/String;)V
   L1
    LINENUMBER 594 L1
    RETURN
   L2
    LOCALVARIABLE this Lbsu; L0 L2 0
    LOCALVARIABLE fr Lbdl; L0 L2 1
    LOCALVARIABLE stack Ladz; L0 L2 2
    LOCALVARIABLE xPosition I L0 L2 3
    LOCALVARIABLE yPosition I L0 L2 4
    MAXSTACK = 6
    MAXLOCALS = 5

  // access flags 0x1
  public a(Lbdl;Ladz;IILjava/lang/String;)V
    @Ljavax/annotation/Nullable;() // parameter 4
   L0
    LINENUMBER 601 L0
    ALOAD 2
    IFNULL L1
   L2
    LINENUMBER 603 L2
    ALOAD 2
    GETFIELD adz.b : I
    ICONST_1
    IF_ICMPNE L3
    ALOAD 5
    IFNULL L4
   L3
    LINENUMBER 605 L3
   FRAME FULL [bsu bdl adz I I java/lang/String] []
    ALOAD 5
    IFNONNULL L5
    ALOAD 2
    GETFIELD adz.b : I
    INVOKESTATIC java/lang/String.valueOf (I)Ljava/lang/String;
    GOTO L6
   L5
   FRAME FULL [bsu bdl adz I I java/lang/String] []
    ALOAD 5
   L6
   FRAME FULL [bsu bdl adz I I java/lang/String] [java/lang/String]
    ASTORE 6
   L7
    LINENUMBER 607 L7
    ALOAD 5
    IFNONNULL L8
    ALOAD 2
    GETFIELD adz.b : I
    ICONST_1
    IF_ICMPGE L8
   L9
    LINENUMBER 609 L9
    NEW java/lang/StringBuilder
    DUP
    INVOKESPECIAL java/lang/StringBuilder.<init> ()V
    GETSTATIC a.m : La;
    INVOKEVIRTUAL java/lang/StringBuilder.append (Ljava/lang/Object;)Ljava/lang/StringBuilder;
    ALOAD 2
    GETFIELD adz.b : I
    INVOKESTATIC java/lang/String.valueOf (I)Ljava/lang/String;
    INVOKEVIRTUAL java/lang/StringBuilder.append (Ljava/lang/String;)Ljava/lang/StringBuilder;
    INVOKEVIRTUAL java/lang/StringBuilder.toString ()Ljava/lang/String;
    ASTORE 6
   L8
    LINENUMBER 612 L8
   FRAME FULL [bsu bdl adz I I java/lang/String java/lang/String] []
    INVOKESTATIC bob.g ()V
   L10
    LINENUMBER 613 L10
    INVOKESTATIC bob.j ()V
   L11
    LINENUMBER 614 L11
    INVOKESTATIC bob.l ()V
   L12
    LINENUMBER 615 L12
    ALOAD 1
    ALOAD 6
    ILOAD 3
    BIPUSH 19
    IADD
    ICONST_2
    ISUB
    ALOAD 1
    ALOAD 6
    INVOKEVIRTUAL bdl.a (Ljava/lang/String;)I
    ISUB
    I2F
    ILOAD 4
    BIPUSH 6
    IADD
    ICONST_3
    IADD
    I2F
    LDC 16777215
    INVOKEVIRTUAL bdl.a (Ljava/lang/String;FFI)I
    POP
   L13
    LINENUMBER 616 L13
    INVOKESTATIC bob.f ()V
   L14
    LINENUMBER 617 L14
    INVOKESTATIC bob.k ()V
   L15
    LINENUMBER 619 L15
    INVOKESTATIC bob.m ()V
   L4
    LINENUMBER 624 L4
   FRAME FULL [bsu bdl adz I I java/lang/String] []
    ALOAD 2
    INVOKESTATIC ReflectorForge.isItemDamaged (Ladz;)Z
    IFEQ L16
   L17
    LINENUMBER 626 L17
    LDC 13.0
    ALOAD 2
    INVOKEVIRTUAL adz.h ()I
    I2D
    LDC 13.0
    DMUL
    ALOAD 2
    INVOKEVIRTUAL adz.j ()I
    I2D
    DDIV
    DSUB
    INVOKESTATIC java/lang/Math.round (D)J
    L2I
    ISTORE 6
   L18
    LINENUMBER 627 L18
    LDC 255.0
    ALOAD 2
    INVOKEVIRTUAL adz.h ()I
    I2D
    LDC 255.0
    DMUL
    ALOAD 2
    INVOKEVIRTUAL adz.j ()I
    I2D
    DDIV
    DSUB
    INVOKESTATIC java/lang/Math.round (D)J
    L2I
    ISTORE 7
   L19
    LINENUMBER 629 L19
    GETSTATIC Reflector.ForgeItem_getDurabilityForDisplay : LReflectorMethod;
    INVOKEVIRTUAL ReflectorMethod.exists ()Z
    IFEQ L20
   L21
    LINENUMBER 631 L21
    ALOAD 2
    INVOKEVIRTUAL adz.b ()Ladx;
    GETSTATIC Reflector.ForgeItem_getDurabilityForDisplay : LReflectorMethod;
    ICONST_1
    ANEWARRAY java/lang/Object
    DUP
    ICONST_0
    ALOAD 2
    AASTORE
    INVOKESTATIC Reflector.callDouble (Ljava/lang/Object;LReflectorMethod;[Ljava/lang/Object;)D
    DSTORE 8
   L22
    LINENUMBER 632 L22
    LDC 13.0
    DLOAD 8
    LDC 13.0
    DMUL
    DSUB
    INVOKESTATIC java/lang/Math.round (D)J
    L2I
    ISTORE 6
   L23
    LINENUMBER 633 L23
    LDC 255.0
    DLOAD 8
    LDC 255.0
    DMUL
    DSUB
    INVOKESTATIC java/lang/Math.round (D)J
    L2I
    ISTORE 7
   L20
    LINENUMBER 636 L20
   FRAME FULL [bsu bdl adz I I java/lang/String I I] []
    INVOKESTATIC bob.g ()V
   L24
    LINENUMBER 637 L24
    INVOKESTATIC bob.j ()V
   L25
    LINENUMBER 638 L25
    INVOKESTATIC bob.z ()V
   L26
    LINENUMBER 639 L26
    INVOKESTATIC bob.d ()V
   L27
    LINENUMBER 640 L27
    INVOKESTATIC bob.l ()V
   L28
    LINENUMBER 641 L28
    INVOKESTATIC bon.a ()Lbon;
    ASTORE 8
   L29
    LINENUMBER 642 L29
    ALOAD 8
    INVOKEVIRTUAL bon.c ()Lbnt;
    ASTORE 9
   L30
    LINENUMBER 643 L30
    ALOAD 0
    ALOAD 9
    ILOAD 3
    ICONST_2
    IADD
    ILOAD 4
    BIPUSH 13
    IADD
    BIPUSH 13
    ICONST_2
    ICONST_0
    ICONST_0
    ICONST_0
    SIPUSH 255
    INVOKESPECIAL bsu.a (Lbnt;IIIIIIII)V
   L31
    LINENUMBER 644 L31
    ALOAD 0
    ALOAD 9
    ILOAD 3
    ICONST_2
    IADD
    ILOAD 4
    BIPUSH 13
    IADD
    BIPUSH 12
    ICONST_1
    SIPUSH 255
    ILOAD 7
    ISUB
    ICONST_4
    IDIV
    BIPUSH 64
    ICONST_0
    SIPUSH 255
    INVOKESPECIAL bsu.a (Lbnt;IIIIIIII)V
   L32
    LINENUMBER 646 L32
    SIPUSH 255
    ILOAD 7
    ISUB
    ISTORE 10
   L33
    LINENUMBER 647 L33
    ILOAD 7
    ISTORE 11
   L34
    LINENUMBER 648 L34
    ICONST_0
    ISTORE 12
   L35
    LINENUMBER 649 L35
    INVOKESTATIC Config.isCustomColors ()Z
    IFEQ L36
   L37
    LINENUMBER 651 L37
    ILOAD 7
    INVOKESTATIC CustomColors.getDurabilityColor (I)I
    ISTORE 13
   L38
    LINENUMBER 652 L38
    ILOAD 13
    IFLT L36
   L39
    LINENUMBER 654 L39
    ILOAD 13
    BIPUSH 16
    ISHR
    SIPUSH 255
    IAND
    ISTORE 10
   L40
    LINENUMBER 655 L40
    ILOAD 13
    BIPUSH 8
    ISHR
    SIPUSH 255
    IAND
    ISTORE 11
   L41
    LINENUMBER 656 L41
    ILOAD 13
    ICONST_0
    ISHR
    SIPUSH 255
    IAND
    ISTORE 12
   L36
    LINENUMBER 660 L36
   FRAME FULL [bsu bdl adz I I java/lang/String I I bon bnt I I I] []
    ALOAD 0
    ALOAD 9
    ILOAD 3
    ICONST_2
    IADD
    ILOAD 4
    BIPUSH 13
    IADD
    ILOAD 6
    ICONST_1
    ILOAD 10
    ILOAD 11
    ILOAD 12
    SIPUSH 255
    INVOKESPECIAL bsu.a (Lbnt;IIIIIIII)V
   L42
    LINENUMBER 661 L42
    INVOKESTATIC bob.m ()V
   L43
    LINENUMBER 662 L43
    INVOKESTATIC bob.e ()V
   L44
    LINENUMBER 663 L44
    INVOKESTATIC bob.y ()V
   L45
    LINENUMBER 664 L45
    INVOKESTATIC bob.f ()V
   L46
    LINENUMBER 665 L46
    INVOKESTATIC bob.k ()V
   L16
    LINENUMBER 668 L16
   FRAME FULL [bsu bdl adz I I java/lang/String] []
    INVOKESTATIC bcx.z ()Lbcx;
    GETFIELD bcx.h : Lbnn;
    ASTORE 6
   L47
    LINENUMBER 669 L47
    ALOAD 6
    IFNONNULL L48
    FCONST_0
    GOTO L49
   L48
   FRAME FULL [bsu bdl adz I I java/lang/String bnn] []
    ALOAD 6
    INVOKEVIRTUAL bnn.df ()Lady;
    ALOAD 2
    INVOKEVIRTUAL adz.b ()Ladx;
    INVOKESTATIC bcx.z ()Lbcx;
    INVOKEVIRTUAL bcx.aj ()F
    INVOKEVIRTUAL ady.a (Ladx;F)F
   L49
   FRAME FULL [bsu bdl adz I I java/lang/String bnn] [F]
    FSTORE 7
   L50
    LINENUMBER 671 L50
    FLOAD 7
    FCONST_0
    FCMPL
    IFLE L1
   L51
    LINENUMBER 673 L51
    INVOKESTATIC bob.g ()V
   L52
    LINENUMBER 674 L52
    INVOKESTATIC bob.j ()V
   L53
    LINENUMBER 675 L53
    INVOKESTATIC bob.z ()V
   L54
    LINENUMBER 676 L54
    INVOKESTATIC bon.a ()Lbon;
    ASTORE 8
   L55
    LINENUMBER 677 L55
    ALOAD 8
    INVOKEVIRTUAL bon.c ()Lbnt;
    ASTORE 9
   L56
    LINENUMBER 678 L56
    ALOAD 0
    ALOAD 9
    ILOAD 3
    ILOAD 4
    LDC 16.0
    FCONST_1
    FLOAD 7
    FSUB
    FMUL
    INVOKESTATIC op.d (F)I
    IADD
    BIPUSH 16
    LDC 16.0
    FLOAD 7
    FMUL
    INVOKESTATIC op.f (F)I
    SIPUSH 255
    SIPUSH 255
    SIPUSH 255
    BIPUSH 127
    INVOKESPECIAL bsu.a (Lbnt;IIIIIIII)V
   L57
    LINENUMBER 679 L57
    INVOKESTATIC bob.y ()V
   L58
    LINENUMBER 680 L58
    INVOKESTATIC bob.f ()V
   L59
    LINENUMBER 681 L59
    INVOKESTATIC bob.k ()V
   L1
    LINENUMBER 684 L1
   FRAME FULL [bsu bdl adz I I java/lang/String] []
    RETURN
   L60
    LOCALVARIABLE s Ljava/lang/String; L7 L4 6
    LOCALVARIABLE health D L22 L20 8
    LOCALVARIABLE col I L38 L36 13
    LOCALVARIABLE j I L18 L16 6
    LOCALVARIABLE i I L19 L16 7
    LOCALVARIABLE tessellator Lbon; L29 L16 8
    LOCALVARIABLE vertexbuffer Lbnt; L30 L16 9
    LOCALVARIABLE red I L33 L16 10
    LOCALVARIABLE green I L34 L16 11
    LOCALVARIABLE blue I L35 L16 12
    LOCALVARIABLE tessellator1 Lbon; L55 L1 8
    LOCALVARIABLE vertexbuffer1 Lbnt; L56 L1 9
    LOCALVARIABLE entityplayersp Lbnn; L47 L1 6
    LOCALVARIABLE f F L50 L1 7
    LOCALVARIABLE this Lbsu; L0 L60 0
    LOCALVARIABLE fr Lbdl; L0 L60 1
    LOCALVARIABLE stack Ladz; L0 L60 2
    LOCALVARIABLE xPosition I L0 L60 3
    LOCALVARIABLE yPosition I L0 L60 4
    LOCALVARIABLE text Ljava/lang/String; L0 L60 5
    MAXSTACK = 10
    MAXLOCALS = 14

  // access flags 0x2
  private a(Lbnt;IIIIIIII)V
   L0
    LINENUMBER 691 L0
    ALOAD 1
    BIPUSH 7
    GETSTATIC bwm.f : Lbwo;
    INVOKEVIRTUAL bnt.a (ILbwo;)V
   L1
    LINENUMBER 692 L1
    ALOAD 1
    ILOAD 2
    ICONST_0
    IADD
    I2D
    ILOAD 3
    ICONST_0
    IADD
    I2D
    DCONST_0
    INVOKEVIRTUAL bnt.b (DDD)Lbnt;
    ILOAD 6
    ILOAD 7
    ILOAD 8
    ILOAD 9
    INVOKEVIRTUAL bnt.b (IIII)Lbnt;
    INVOKEVIRTUAL bnt.d ()V
   L2
    LINENUMBER 693 L2
    ALOAD 1
    ILOAD 2
    ICONST_0
    IADD
    I2D
    ILOAD 3
    ILOAD 5
    IADD
    I2D
    DCONST_0
    INVOKEVIRTUAL bnt.b (DDD)Lbnt;
    ILOAD 6
    ILOAD 7
    ILOAD 8
    ILOAD 9
    INVOKEVIRTUAL bnt.b (IIII)Lbnt;
    INVOKEVIRTUAL bnt.d ()V
   L3
    LINENUMBER 694 L3
    ALOAD 1
    ILOAD 2
    ILOAD 4
    IADD
    I2D
    ILOAD 3
    ILOAD 5
    IADD
    I2D
    DCONST_0
    INVOKEVIRTUAL bnt.b (DDD)Lbnt;
    ILOAD 6
    ILOAD 7
    ILOAD 8
    ILOAD 9
    INVOKEVIRTUAL bnt.b (IIII)Lbnt;
    INVOKEVIRTUAL bnt.d ()V
   L4
    LINENUMBER 695 L4
    ALOAD 1
    ILOAD 2
    ILOAD 4
    IADD
    I2D
    ILOAD 3
    ICONST_0
    IADD
    I2D
    DCONST_0
    INVOKEVIRTUAL bnt.b (DDD)Lbnt;
    ILOAD 6
    ILOAD 7
    ILOAD 8
    ILOAD 9
    INVOKEVIRTUAL bnt.b (IIII)Lbnt;
    INVOKEVIRTUAL bnt.d ()V
   L5
    LINENUMBER 696 L5
    INVOKESTATIC bon.a ()Lbon;
    INVOKEVIRTUAL bon.b ()V
   L6
    LINENUMBER 697 L6
    RETURN
   L7
    LOCALVARIABLE this Lbsu; L0 L7 0
    LOCALVARIABLE renderer Lbnt; L0 L7 1
    LOCALVARIABLE x I L0 L7 2
    LOCALVARIABLE y I L0 L7 3
    LOCALVARIABLE width I L0 L7 4
    LOCALVARIABLE height I L0 L7 5
    LOCALVARIABLE red I L0 L7 6
    LOCALVARIABLE green I L0 L7 7
    LOCALVARIABLE blue I L0 L7 8
    LOCALVARIABLE alpha I L0 L7 9
    MAXSTACK = 7
    MAXLOCALS = 10

  // access flags 0x2
  private b()V
   L0
    LINENUMBER 701 L0
    ALOAD 0
    GETSTATIC akg.cf : Lakf;
    LDC "anvil_intact"
    INVOKESPECIAL bsu.a (Lakf;Ljava/lang/String;)V
   L1
    LINENUMBER 702 L1
    ALOAD 0
    GETSTATIC akg.cf : Lakf;
    ICONST_1
    LDC "anvil_slightly_damaged"
    INVOKEVIRTUAL bsu.a (Lakf;ILjava/lang/String;)V
   L2
    LINENUMBER 703 L2
    ALOAD 0
    GETSTATIC akg.cf : Lakf;
    ICONST_2
    LDC "anvil_very_damaged"
    INVOKEVIRTUAL bsu.a (Lakf;ILjava/lang/String;)V
   L3
    LINENUMBER 704 L3
    ALOAD 0
    GETSTATIC akg.cy : Lakf;
    GETSTATIC adc.p : Ladc;
    INVOKEVIRTUAL adc.a ()I
    LDC "black_carpet"
    INVOKEVIRTUAL bsu.a (Lakf;ILjava/lang/String;)V
   L4
    LINENUMBER 705 L4
    ALOAD 0
    GETSTATIC akg.cy : Lakf;
    GETSTATIC adc.l : Ladc;
    INVOKEVIRTUAL adc.a ()I
    LDC "blue_carpet"
    INVOKEVIRTUAL bsu.a (Lakf;ILjava/lang/String;)V
   L5
    LINENUMBER 706 L5
    ALOAD 0
    GETSTATIC akg.cy : Lakf;
    GETSTATIC adc.m : Ladc;
    INVOKEVIRTUAL adc.a ()I
    LDC "brown_carpet"
    INVOKEVIRTUAL bsu.a (Lakf;ILjava/lang/String;)V
   L6
    LINENUMBER 707 L6
    ALOAD 0
    GETSTATIC akg.cy : Lakf;
    GETSTATIC adc.j : Ladc;
    INVOKEVIRTUAL adc.a ()I
    LDC "cyan_carpet"
    INVOKEVIRTUAL bsu.a (Lakf;ILjava/lang/String;)V
   L7
    LINENUMBER 708 L7
    ALOAD 0
    GETSTATIC akg.cy : Lakf;
    GETSTATIC adc.h : Ladc;
    INVOKEVIRTUAL adc.a ()I
    LDC "gray_carpet"
    INVOKEVIRTUAL bsu.a (Lakf;ILjava/lang/String;)V
   L8
    LINENUMBER 709 L8
    ALOAD 0
    GETSTATIC akg.cy : Lakf;
    GETSTATIC adc.n : Ladc;
    INVOKEVIRTUAL adc.a ()I
    LDC "green_carpet"
    INVOKEVIRTUAL bsu.a (Lakf;ILjava/lang/String;)V
   L9
    LINENUMBER 710 L9
    ALOAD 0
    GETSTATIC akg.cy : Lakf;
    GETSTATIC adc.d : Ladc;
    INVOKEVIRTUAL adc.a ()I
    LDC "light_blue_carpet"
    INVOKEVIRTUAL bsu.a (Lakf;ILjava/lang/String;)V
   L10
    LINENUMBER 711 L10
    ALOAD 0
    GETSTATIC akg.cy : Lakf;
    GETSTATIC adc.f : Ladc;
    INVOKEVIRTUAL adc.a ()I
    LDC "lime_carpet"
    INVOKEVIRTUAL bsu.a (Lakf;ILjava/lang/String;)V
   L11
    LINENUMBER 712 L11
    ALOAD 0
    GETSTATIC akg.cy : Lakf;
    GETSTATIC adc.c : Ladc;
    INVOKEVIRTUAL adc.a ()I
    LDC "magenta_carpet"
    INVOKEVIRTUAL bsu.a (Lakf;ILjava/lang/String;)V
   L12
    LINENUMBER 713 L12
    ALOAD 0
    GETSTATIC akg.cy : Lakf;
    GETSTATIC adc.b : Ladc;
    INVOKEVIRTUAL adc.a ()I
    LDC "orange_carpet"
    INVOKEVIRTUAL bsu.a (Lakf;ILjava/lang/String;)V
   L13
    LINENUMBER 714 L13
    ALOAD 0
    GETSTATIC akg.cy : Lakf;
    GETSTATIC adc.g : Ladc;
    INVOKEVIRTUAL adc.a ()I
    LDC "pink_carpet"
    INVOKEVIRTUAL bsu.a (Lakf;ILjava/lang/String;)V
   L14
    LINENUMBER 715 L14
    ALOAD 0
    GETSTATIC akg.cy : Lakf;
    GETSTATIC adc.k : Ladc;
    INVOKEVIRTUAL adc.a ()I
    LDC "purple_carpet"
    INVOKEVIRTUAL bsu.a (Lakf;ILjava/lang/String;)V
   L15
    LINENUMBER 716 L15
    ALOAD 0
    GETSTATIC akg.cy : Lakf;
    GETSTATIC adc.o : Ladc;
    INVOKEVIRTUAL adc.a ()I
    LDC "red_carpet"
    INVOKEVIRTUAL bsu.a (Lakf;ILjava/lang/String;)V
   L16
    LINENUMBER 717 L16
    ALOAD 0
    GETSTATIC akg.cy : Lakf;
    GETSTATIC adc.i : Ladc;
    INVOKEVIRTUAL adc.a ()I
    LDC "silver_carpet"
    INVOKEVIRTUAL bsu.a (Lakf;ILjava/lang/String;)V
   L17
    LINENUMBER 718 L17
    ALOAD 0
    GETSTATIC akg.cy : Lakf;
    GETSTATIC adc.a : Ladc;
    INVOKEVIRTUAL adc.a ()I
    LDC "white_carpet"
    INVOKEVIRTUAL bsu.a (Lakf;ILjava/lang/String;)V
   L18
    LINENUMBER 719 L18
    ALOAD 0
    GETSTATIC akg.cy : Lakf;
    GETSTATIC adc.e : Ladc;
    INVOKEVIRTUAL adc.a ()I
    LDC "yellow_carpet"
    INVOKEVIRTUAL bsu.a (Lakf;ILjava/lang/String;)V
   L19
    LINENUMBER 720 L19
    ALOAD 0
    GETSTATIC akg.bZ : Lakf;
    GETSTATIC apz$a.b : Lapz$a;
    INVOKEVIRTUAL apz$a.a ()I
    LDC "mossy_cobblestone_wall"
    INVOKEVIRTUAL bsu.a (Lakf;ILjava/lang/String;)V
   L20
    LINENUMBER 721 L20
    ALOAD 0
    GETSTATIC akg.bZ : Lakf;
    GETSTATIC apz$a.a : Lapz$a;
    INVOKEVIRTUAL apz$a.a ()I
    LDC "cobblestone_wall"
    INVOKEVIRTUAL bsu.a (Lakf;ILjava/lang/String;)V
   L21
    LINENUMBER 722 L21
    ALOAD 0
    GETSTATIC akg.d : Lakf;
    GETSTATIC alg$a.b : Lalg$a;
    INVOKEVIRTUAL alg$a.a ()I
    LDC "coarse_dirt"
    INVOKEVIRTUAL bsu.a (Lakf;ILjava/lang/String;)V
   L22
    LINENUMBER 723 L22
    ALOAD 0
    GETSTATIC akg.d : Lakf;
    GETSTATIC alg$a.a : Lalg$a;
    INVOKEVIRTUAL alg$a.a ()I
    LDC "dirt"
    INVOKEVIRTUAL bsu.a (Lakf;ILjava/lang/String;)V
   L23
    LINENUMBER 724 L23
    ALOAD 0
    GETSTATIC akg.d : Lakf;
    GETSTATIC alg$a.c : Lalg$a;
    INVOKEVIRTUAL alg$a.a ()I
    LDC "podzol"
    INVOKEVIRTUAL bsu.a (Lakf;ILjava/lang/String;)V
   L24
    LINENUMBER 725 L24
    ALOAD 0
    GETSTATIC akg.cF : Lalj;
    GETSTATIC alj$b.d : Lalj$b;
    INVOKEVIRTUAL alj$b.a ()I
    LDC "double_fern"
    INVOKEVIRTUAL bsu.a (Lakf;ILjava/lang/String;)V
   L25
    LINENUMBER 726 L25
    ALOAD 0
    GETSTATIC akg.cF : Lalj;
    GETSTATIC alj$b.c : Lalj$b;
    INVOKEVIRTUAL alj$b.a ()I
    LDC "double_grass"
    INVOKEVIRTUAL bsu.a (Lakf;ILjava/lang/String;)V
   L26
    LINENUMBER 727 L26
    ALOAD 0
    GETSTATIC akg.cF : Lalj;
    GETSTATIC alj$b.f : Lalj$b;
    INVOKEVIRTUAL alj$b.a ()I
    LDC "paeonia"
    INVOKEVIRTUAL bsu.a (Lakf;ILjava/lang/String;)V
   L27
    LINENUMBER 728 L27
    ALOAD 0
    GETSTATIC akg.cF : Lalj;
    GETSTATIC alj$b.e : Lalj$b;
    INVOKEVIRTUAL alj$b.a ()I
    LDC "double_rose"
    INVOKEVIRTUAL bsu.a (Lakf;ILjava/lang/String;)V
   L28
    LINENUMBER 729 L28
    ALOAD 0
    GETSTATIC akg.cF : Lalj;
    GETSTATIC alj$b.a : Lalj$b;
    INVOKEVIRTUAL alj$b.a ()I
    LDC "sunflower"
    INVOKEVIRTUAL bsu.a (Lakf;ILjava/lang/String;)V
   L29
    LINENUMBER 730 L29
    ALOAD 0
    GETSTATIC akg.cF : Lalj;
    GETSTATIC alj$b.b : Lalj$b;
    INVOKEVIRTUAL alj$b.a ()I
    LDC "syringa"
    INVOKEVIRTUAL bsu.a (Lakf;ILjava/lang/String;)V
   L30
    LINENUMBER 731 L30
    ALOAD 0
    GETSTATIC akg.t : Lamy;
    GETSTATIC anx$a.c : Lanx$a;
    INVOKEVIRTUAL anx$a.a ()I
    LDC "birch_leaves"
    INVOKEVIRTUAL bsu.a (Lakf;ILjava/lang/String;)V
   L31
    LINENUMBER 732 L31
    ALOAD 0
    GETSTATIC akg.t : Lamy;
    GETSTATIC anx$a.d : Lanx$a;
    INVOKEVIRTUAL anx$a.a ()I
    LDC "jungle_leaves"
    INVOKEVIRTUAL bsu.a (Lakf;ILjava/lang/String;)V
   L32
    LINENUMBER 733 L32
    ALOAD 0
    GETSTATIC akg.t : Lamy;
    GETSTATIC anx$a.a : Lanx$a;
    INVOKEVIRTUAL anx$a.a ()I
    LDC "oak_leaves"
    INVOKEVIRTUAL bsu.a (Lakf;ILjava/lang/String;)V
   L33
    LINENUMBER 734 L33
    ALOAD 0
    GETSTATIC akg.t : Lamy;
    GETSTATIC anx$a.b : Lanx$a;
    INVOKEVIRTUAL anx$a.a ()I
    LDC "spruce_leaves"
    INVOKEVIRTUAL bsu.a (Lakf;ILjava/lang/String;)V
   L34
    LINENUMBER 735 L34
    ALOAD 0
    GETSTATIC akg.u : Lamy;
    GETSTATIC anx$a.e : Lanx$a;
    INVOKEVIRTUAL anx$a.a ()I
    ICONST_4
    ISUB
    LDC "acacia_leaves"
    INVOKEVIRTUAL bsu.a (Lakf;ILjava/lang/String;)V
   L35
    LINENUMBER 736 L35
    ALOAD 0
    GETSTATIC akg.u : Lamy;
    GETSTATIC anx$a.f : Lanx$a;
    INVOKEVIRTUAL anx$a.a ()I
    ICONST_4
    ISUB
    LDC "dark_oak_leaves"
    INVOKEVIRTUAL bsu.a (Lakf;ILjava/lang/String;)V
   L36
    LINENUMBER 737 L36
    ALOAD 0
    GETSTATIC akg.r : Lakf;
    GETSTATIC anx$a.c : Lanx$a;
    INVOKEVIRTUAL anx$a.a ()I
    LDC "birch_log"
    INVOKEVIRTUAL bsu.a (Lakf;ILjava/lang/String;)V
   L37
    LINENUMBER 738 L37
    ALOAD 0
    GETSTATIC akg.r : Lakf;
    GETSTATIC anx$a.d : Lanx$a;
    INVOKEVIRTUAL anx$a.a ()I
    LDC "jungle_log"
    INVOKEVIRTUAL bsu.a (Lakf;ILjava/lang/String;)V
   L38
    LINENUMBER 739 L38
    ALOAD 0
    GETSTATIC akg.r : Lakf;
    GETSTATIC anx$a.a : Lanx$a;
    INVOKEVIRTUAL anx$a.a ()I
    LDC "oak_log"
    INVOKEVIRTUAL bsu.a (Lakf;ILjava/lang/String;)V
   L39
    LINENUMBER 740 L39
    ALOAD 0
    GETSTATIC akg.r : Lakf;
    GETSTATIC anx$a.b : Lanx$a;
    INVOKEVIRTUAL anx$a.a ()I
    LDC "spruce_log"
    INVOKEVIRTUAL bsu.a (Lakf;ILjava/lang/String;)V
   L40
    LINENUMBER 741 L40
    ALOAD 0
    GETSTATIC akg.s : Lakf;
    GETSTATIC anx$a.e : Lanx$a;
    INVOKEVIRTUAL anx$a.a ()I
    ICONST_4
    ISUB
    LDC "acacia_log"
    INVOKEVIRTUAL bsu.a (Lakf;ILjava/lang/String;)V
   L41
    LINENUMBER 742 L41
    ALOAD 0
    GETSTATIC akg.s : Lakf;
    GETSTATIC anx$a.f : Lanx$a;
    INVOKEVIRTUAL anx$a.a ()I
    ICONST_4
    ISUB
    LDC "dark_oak_log"
    INVOKEVIRTUAL bsu.a (Lakf;ILjava/lang/String;)V
   L42
    LINENUMBER 743 L42
    ALOAD 0
    GETSTATIC akg.be : Lakf;
    GETSTATIC anh$a.f : Lanh$a;
    INVOKEVIRTUAL anh$a.a ()I
    LDC "chiseled_brick_monster_egg"
    INVOKEVIRTUAL bsu.a (Lakf;ILjava/lang/String;)V
   L43
    LINENUMBER 744 L43
    ALOAD 0
    GETSTATIC akg.be : Lakf;
    GETSTATIC anh$a.b : Lanh$a;
    INVOKEVIRTUAL anh$a.a ()I
    LDC "cobblestone_monster_egg"
    INVOKEVIRTUAL bsu.a (Lakf;ILjava/lang/String;)V
   L44
    LINENUMBER 745 L44
    ALOAD 0
    GETSTATIC akg.be : Lakf;
    GETSTATIC anh$a.e : Lanh$a;
    INVOKEVIRTUAL anh$a.a ()I
    LDC "cracked_brick_monster_egg"
    INVOKEVIRTUAL bsu.a (Lakf;ILjava/lang/String;)V
   L45
    LINENUMBER 746 L45
    ALOAD 0
    GETSTATIC akg.be : Lakf;
    GETSTATIC anh$a.d : Lanh$a;
    INVOKEVIRTUAL anh$a.a ()I
    LDC "mossy_brick_monster_egg"
    INVOKEVIRTUAL bsu.a (Lakf;ILjava/lang/String;)V
   L46
    LINENUMBER 747 L46
    ALOAD 0
    GETSTATIC akg.be : Lakf;
    GETSTATIC anh$a.a : Lanh$a;
    INVOKEVIRTUAL anh$a.a ()I
    LDC "stone_monster_egg"
    INVOKEVIRTUAL bsu.a (Lakf;ILjava/lang/String;)V
   L47
    LINENUMBER 748 L47
    ALOAD 0
    GETSTATIC akg.be : Lakf;
    GETSTATIC anh$a.c : Lanh$a;
    INVOKEVIRTUAL anh$a.a ()I
    LDC "stone_brick_monster_egg"
    INVOKEVIRTUAL bsu.a (Lakf;ILjava/lang/String;)V
   L48
    LINENUMBER 749 L48
    ALOAD 0
    GETSTATIC akg.f : Lakf;
    GETSTATIC anx$a.e : Lanx$a;
    INVOKEVIRTUAL anx$a.a ()I
    LDC "acacia_planks"
    INVOKEVIRTUAL bsu.a (Lakf;ILjava/lang/String;)V
   L49
    LINENUMBER 750 L49
    ALOAD 0
    GETSTATIC akg.f : Lakf;
    GETSTATIC anx$a.c : Lanx$a;
    INVOKEVIRTUAL anx$a.a ()I
    LDC "birch_planks"
    INVOKEVIRTUAL bsu.a (Lakf;ILjava/lang/String;)V
   L50
    LINENUMBER 751 L50
    ALOAD 0
    GETSTATIC akg.f : Lakf;
    GETSTATIC anx$a.f : Lanx$a;
    INVOKEVIRTUAL anx$a.a ()I
    LDC "dark_oak_planks"
    INVOKEVIRTUAL bsu.a (Lakf;ILjava/lang/String;)V
   L51
    LINENUMBER 752 L51
    ALOAD 0
    GETSTATIC akg.f : Lakf;
    GETSTATIC anx$a.d : Lanx$a;
    INVOKEVIRTUAL anx$a.a ()I
    LDC "jungle_planks"
    INVOKEVIRTUAL bsu.a (Lakf;ILjava/lang/String;)V
   L52
    LINENUMBER 753 L52
    ALOAD 0
    GETSTATIC akg.f : Lakf;
    GETSTATIC anx$a.a : Lanx$a;
    INVOKEVIRTUAL anx$a.a ()I
    LDC "oak_planks"
    INVOKEVIRTUAL bsu.a (Lakf;ILjava/lang/String;)V
   L53
    LINENUMBER 754 L53
    ALOAD 0
    GETSTATIC akg.f : Lakf;
    GETSTATIC anx$a.b : Lanx$a;
    INVOKEVIRTUAL anx$a.a ()I
    LDC "spruce_planks"
    INVOKEVIRTUAL bsu.a (Lakf;ILjava/lang/String;)V
   L54
    LINENUMBER 755 L54
    ALOAD 0
    GETSTATIC akg.cI : Lakf;
    GETSTATIC aod$a.b : Laod$a;
    INVOKEVIRTUAL aod$a.a ()I
    LDC "prismarine_bricks"
    INVOKEVIRTUAL bsu.a (Lakf;ILjava/lang/String;)V
   L55
    LINENUMBER 756 L55
    ALOAD 0
    GETSTATIC akg.cI : Lakf;
    GETSTATIC aod$a.c : Laod$a;
    INVOKEVIRTUAL aod$a.a ()I
    LDC "dark_prismarine"
    INVOKEVIRTUAL bsu.a (Lakf;ILjava/lang/String;)V
   L56
    LINENUMBER 757 L56
    ALOAD 0
    GETSTATIC akg.cI : Lakf;
    GETSTATIC aod$a.a : Laod$a;
    INVOKEVIRTUAL aod$a.a ()I
    LDC "prismarine"
    INVOKEVIRTUAL bsu.a (Lakf;ILjava/lang/String;)V
   L57
    LINENUMBER 758 L57
    ALOAD 0
    GETSTATIC akg.cq : Lakf;
    GETSTATIC aog$a.b : Laog$a;
    INVOKEVIRTUAL aog$a.a ()I
    LDC "chiseled_quartz_block"
    INVOKEVIRTUAL bsu.a (Lakf;ILjava/lang/String;)V
   L58
    LINENUMBER 759 L58
    ALOAD 0
    GETSTATIC akg.cq : Lakf;
    GETSTATIC aog$a.a : Laog$a;
    INVOKEVIRTUAL aog$a.a ()I
    LDC "quartz_block"
    INVOKEVIRTUAL bsu.a (Lakf;ILjava/lang/String;)V
   L59
    LINENUMBER 760 L59
    ALOAD 0
    GETSTATIC akg.cq : Lakf;
    GETSTATIC aog$a.c : Laog$a;
    INVOKEVIRTUAL aog$a.a ()I
    LDC "quartz_column"
    INVOKEVIRTUAL bsu.a (Lakf;ILjava/lang/String;)V
   L60
    LINENUMBER 761 L60
    ALOAD 0
    GETSTATIC akg.O : Lalz;
    GETSTATIC alz$a.d : Lalz$a;
    INVOKEVIRTUAL alz$a.b ()I
    LDC "allium"
    INVOKEVIRTUAL bsu.a (Lakf;ILjava/lang/String;)V
   L61
    LINENUMBER 762 L61
    ALOAD 0
    GETSTATIC akg.O : Lalz;
    GETSTATIC alz$a.c : Lalz$a;
    INVOKEVIRTUAL alz$a.b ()I
    LDC "blue_orchid"
    INVOKEVIRTUAL bsu.a (Lakf;ILjava/lang/String;)V
   L62
    LINENUMBER 763 L62
    ALOAD 0
    GETSTATIC akg.O : Lalz;
    GETSTATIC alz$a.e : Lalz$a;
    INVOKEVIRTUAL alz$a.b ()I
    LDC "houstonia"
    INVOKEVIRTUAL bsu.a (Lakf;ILjava/lang/String;)V
   L63
    LINENUMBER 764 L63
    ALOAD 0
    GETSTATIC akg.O : Lalz;
    GETSTATIC alz$a.g : Lalz$a;
    INVOKEVIRTUAL alz$a.b ()I
    LDC "orange_tulip"
    INVOKEVIRTUAL bsu.a (Lakf;ILjava/lang/String;)V
   L64
    LINENUMBER 765 L64
    ALOAD 0
    GETSTATIC akg.O : Lalz;
    GETSTATIC alz$a.j : Lalz$a;
    INVOKEVIRTUAL alz$a.b ()I
    LDC "oxeye_daisy"
    INVOKEVIRTUAL bsu.a (Lakf;ILjava/lang/String;)V
   L65
    LINENUMBER 766 L65
    ALOAD 0
    GETSTATIC akg.O : Lalz;
    GETSTATIC alz$a.i : Lalz$a;
    INVOKEVIRTUAL alz$a.b ()I
    LDC "pink_tulip"
    INVOKEVIRTUAL bsu.a (Lakf;ILjava/lang/String;)V
   L66
    LINENUMBER 767 L66
    ALOAD 0
    GETSTATIC akg.O : Lalz;
    GETSTATIC alz$a.b : Lalz$a;
    INVOKEVIRTUAL alz$a.b ()I
    LDC "poppy"
    INVOKEVIRTUAL bsu.a (Lakf;ILjava/lang/String;)V
   L67
    LINENUMBER 768 L67
    ALOAD 0
    GETSTATIC akg.O : Lalz;
    GETSTATIC alz$a.f : Lalz$a;
    INVOKEVIRTUAL alz$a.b ()I
    LDC "red_tulip"
    INVOKEVIRTUAL bsu.a (Lakf;ILjava/lang/String;)V
   L68
    LINENUMBER 769 L68
    ALOAD 0
    GETSTATIC akg.O : Lalz;
    GETSTATIC alz$a.h : Lalz$a;
    INVOKEVIRTUAL alz$a.b ()I
    LDC "white_tulip"
    INVOKEVIRTUAL bsu.a (Lakf;ILjava/lang/String;)V
   L69
    LINENUMBER 770 L69
    ALOAD 0
    GETSTATIC akg.m : Laot;
    GETSTATIC aot$a.b : Laot$a;
    INVOKEVIRTUAL aot$a.b ()I
    LDC "red_sand"
    INVOKEVIRTUAL bsu.a (Lakf;ILjava/lang/String;)V
   L70
    LINENUMBER 771 L70
    ALOAD 0
    GETSTATIC akg.m : Laot;
    GETSTATIC aot$a.a : Laot$a;
    INVOKEVIRTUAL aot$a.b ()I
    LDC "sand"
    INVOKEVIRTUAL bsu.a (Lakf;ILjava/lang/String;)V
   L71
    LINENUMBER 772 L71
    ALOAD 0
    GETSTATIC akg.A : Lakf;
    GETSTATIC aou$a.b : Laou$a;
    INVOKEVIRTUAL aou$a.a ()I
    LDC "chiseled_sandstone"
    INVOKEVIRTUAL bsu.a (Lakf;ILjava/lang/String;)V
   L72
    LINENUMBER 773 L72
    ALOAD 0
    GETSTATIC akg.A : Lakf;
    GETSTATIC aou$a.a : Laou$a;
    INVOKEVIRTUAL aou$a.a ()I
    LDC "sandstone"
    INVOKEVIRTUAL bsu.a (Lakf;ILjava/lang/String;)V
   L73
    LINENUMBER 774 L73
    ALOAD 0
    GETSTATIC akg.A : Lakf;
    GETSTATIC aou$a.c : Laou$a;
    INVOKEVIRTUAL aou$a.a ()I
    LDC "smooth_sandstone"
    INVOKEVIRTUAL bsu.a (Lakf;ILjava/lang/String;)V
   L74
    LINENUMBER 775 L74
    ALOAD 0
    GETSTATIC akg.cM : Lakf;
    GETSTATIC aoj$a.b : Laoj$a;
    INVOKEVIRTUAL aoj$a.a ()I
    LDC "chiseled_red_sandstone"
    INVOKEVIRTUAL bsu.a (Lakf;ILjava/lang/String;)V
   L75
    LINENUMBER 776 L75
    ALOAD 0
    GETSTATIC akg.cM : Lakf;
    GETSTATIC aoj$a.a : Laoj$a;
    INVOKEVIRTUAL aoj$a.a ()I
    LDC "red_sandstone"
    INVOKEVIRTUAL bsu.a (Lakf;ILjava/lang/String;)V
   L76
    LINENUMBER 777 L76
    ALOAD 0
    GETSTATIC akg.cM : Lakf;
    GETSTATIC aoj$a.c : Laoj$a;
    INVOKEVIRTUAL aoj$a.a ()I
    LDC "smooth_red_sandstone"
    INVOKEVIRTUAL bsu.a (Lakf;ILjava/lang/String;)V
   L77
    LINENUMBER 778 L77
    ALOAD 0
    GETSTATIC akg.g : Lakf;
    GETSTATIC anx$a.e : Lanx$a;
    INVOKEVIRTUAL anx$a.a ()I
    LDC "acacia_sapling"
    INVOKEVIRTUAL bsu.a (Lakf;ILjava/lang/String;)V
   L78
    LINENUMBER 779 L78
    ALOAD 0
    GETSTATIC akg.g : Lakf;
    GETSTATIC anx$a.c : Lanx$a;
    INVOKEVIRTUAL anx$a.a ()I
    LDC "birch_sapling"
    INVOKEVIRTUAL bsu.a (Lakf;ILjava/lang/String;)V
   L79
    LINENUMBER 780 L79
    ALOAD 0
    GETSTATIC akg.g : Lakf;
    GETSTATIC anx$a.f : Lanx$a;
    INVOKEVIRTUAL anx$a.a ()I
    LDC "dark_oak_sapling"
    INVOKEVIRTUAL bsu.a (Lakf;ILjava/lang/String;)V
   L80
    LINENUMBER 781 L80
    ALOAD 0
    GETSTATIC akg.g : Lakf;
    GETSTATIC anx$a.d : Lanx$a;
    INVOKEVIRTUAL anx$a.a ()I
    LDC "jungle_sapling"
    INVOKEVIRTUAL bsu.a (Lakf;ILjava/lang/String;)V
   L81
    LINENUMBER 782 L81
    ALOAD 0
    GETSTATIC akg.g : Lakf;
    GETSTATIC anx$a.a : Lanx$a;
    INVOKEVIRTUAL anx$a.a ()I
    LDC "oak_sapling"
    INVOKEVIRTUAL bsu.a (Lakf;ILjava/lang/String;)V
   L82
    LINENUMBER 783 L82
    ALOAD 0
    GETSTATIC akg.g : Lakf;
    GETSTATIC anx$a.b : Lanx$a;
    INVOKEVIRTUAL anx$a.a ()I
    LDC "spruce_sapling"
    INVOKEVIRTUAL bsu.a (Lakf;ILjava/lang/String;)V
   L83
    LINENUMBER 784 L83
    ALOAD 0
    GETSTATIC akg.v : Lakf;
    ICONST_0
    LDC "sponge"
    INVOKEVIRTUAL bsu.a (Lakf;ILjava/lang/String;)V
   L84
    LINENUMBER 785 L84
    ALOAD 0
    GETSTATIC akg.v : Lakf;
    ICONST_1
    LDC "sponge_wet"
    INVOKEVIRTUAL bsu.a (Lakf;ILjava/lang/String;)V
   L85
    LINENUMBER 786 L85
    ALOAD 0
    GETSTATIC akg.cG : Lapf;
    GETSTATIC adc.p : Ladc;
    INVOKEVIRTUAL adc.a ()I
    LDC "black_stained_glass"
    INVOKEVIRTUAL bsu.a (Lakf;ILjava/lang/String;)V
   L86
    LINENUMBER 787 L86
    ALOAD 0
    GETSTATIC akg.cG : Lapf;
    GETSTATIC adc.l : Ladc;
    INVOKEVIRTUAL adc.a ()I
    LDC "blue_stained_glass"
    INVOKEVIRTUAL bsu.a (Lakf;ILjava/lang/String;)V
   L87
    LINENUMBER 788 L87
    ALOAD 0
    GETSTATIC akg.cG : Lapf;
    GETSTATIC adc.m : Ladc;
    INVOKEVIRTUAL adc.a ()I
    LDC "brown_stained_glass"
    INVOKEVIRTUAL bsu.a (Lakf;ILjava/lang/String;)V
   L88
    LINENUMBER 789 L88
    ALOAD 0
    GETSTATIC akg.cG : Lapf;
    GETSTATIC adc.j : Ladc;
    INVOKEVIRTUAL adc.a ()I
    LDC "cyan_stained_glass"
    INVOKEVIRTUAL bsu.a (Lakf;ILjava/lang/String;)V
   L89
    LINENUMBER 790 L89
    ALOAD 0
    GETSTATIC akg.cG : Lapf;
    GETSTATIC adc.h : Ladc;
    INVOKEVIRTUAL adc.a ()I
    LDC "gray_stained_glass"
    INVOKEVIRTUAL bsu.a (Lakf;ILjava/lang/String;)V
   L90
    LINENUMBER 791 L90
    ALOAD 0
    GETSTATIC akg.cG : Lapf;
    GETSTATIC adc.n : Ladc;
    INVOKEVIRTUAL adc.a ()I
    LDC "green_stained_glass"
    INVOKEVIRTUAL bsu.a (Lakf;ILjava/lang/String;)V
   L91
    LINENUMBER 792 L91
    ALOAD 0
    GETSTATIC akg.cG : Lapf;
    GETSTATIC adc.d : Ladc;
    INVOKEVIRTUAL adc.a ()I
    LDC "light_blue_stained_glass"
    INVOKEVIRTUAL bsu.a (Lakf;ILjava/lang/String;)V
   L92
    LINENUMBER 793 L92
    ALOAD 0
    GETSTATIC akg.cG : Lapf;
    GETSTATIC adc.f : Ladc;
    INVOKEVIRTUAL adc.a ()I
    LDC "lime_stained_glass"
    INVOKEVIRTUAL bsu.a (Lakf;ILjava/lang/String;)V
   L93
    LINENUMBER 794 L93
    ALOAD 0
    GETSTATIC akg.cG : Lapf;
    GETSTATIC adc.c : Ladc;
    INVOKEVIRTUAL adc.a ()I
    LDC "magenta_stained_glass"
    INVOKEVIRTUAL bsu.a (Lakf;ILjava/lang/String;)V
   L94
    LINENUMBER 795 L94
    ALOAD 0
    GETSTATIC akg.cG : Lapf;
    GETSTATIC adc.b : Ladc;
    INVOKEVIRTUAL adc.a ()I
    LDC "orange_stained_glass"
    INVOKEVIRTUAL bsu.a (Lakf;ILjava/lang/String;)V
   L95
    LINENUMBER 796 L95
    ALOAD 0
    GETSTATIC akg.cG : Lapf;
    GETSTATIC adc.g : Ladc;
    INVOKEVIRTUAL adc.a ()I
    LDC "pink_stained_glass"
    INVOKEVIRTUAL bsu.a (Lakf;ILjava/lang/String;)V
   L96
    LINENUMBER 797 L96
    ALOAD 0
    GETSTATIC akg.cG : Lapf;
    GETSTATIC adc.k : Ladc;
    INVOKEVIRTUAL adc.a ()I
    LDC "purple_stained_glass"
    INVOKEVIRTUAL bsu.a (Lakf;ILjava/lang/String;)V
   L97
    LINENUMBER 798 L97
    ALOAD 0
    GETSTATIC akg.cG : Lapf;
    GETSTATIC adc.o : Ladc;
    INVOKEVIRTUAL adc.a ()I
    LDC "red_stained_glass"
    INVOKEVIRTUAL bsu.a (Lakf;ILjava/lang/String;)V
   L98
    LINENUMBER 799 L98
    ALOAD 0
    GETSTATIC akg.cG : Lapf;
    GETSTATIC adc.i : Ladc;
    INVOKEVIRTUAL adc.a ()I
    LDC "silver_stained_glass"
    INVOKEVIRTUAL bsu.a (Lakf;ILjava/lang/String;)V
   L99
    LINENUMBER 800 L99
    ALOAD 0
    GETSTATIC akg.cG : Lapf;
    GETSTATIC adc.a : Ladc;
    INVOKEVIRTUAL adc.a ()I
    LDC "white_stained_glass"
    INVOKEVIRTUAL bsu.a (Lakf;ILjava/lang/String;)V
   L100
    LINENUMBER 801 L100
    ALOAD 0
    GETSTATIC akg.cG : Lapf;
    GETSTATIC adc.e : Ladc;
    INVOKEVIRTUAL adc.a ()I
    LDC "yellow_stained_glass"
    INVOKEVIRTUAL bsu.a (Lakf;ILjava/lang/String;)V
   L101
    LINENUMBER 802 L101
    ALOAD 0
    GETSTATIC akg.cH : Lapg;
    GETSTATIC adc.p : Ladc;
    INVOKEVIRTUAL adc.a ()I
    LDC "black_stained_glass_pane"
    INVOKEVIRTUAL bsu.a (Lakf;ILjava/lang/String;)V
   L102
    LINENUMBER 803 L102
    ALOAD 0
    GETSTATIC akg.cH : Lapg;
    GETSTATIC adc.l : Ladc;
    INVOKEVIRTUAL adc.a ()I
    LDC "blue_stained_glass_pane"
    INVOKEVIRTUAL bsu.a (Lakf;ILjava/lang/String;)V
   L103
    LINENUMBER 804 L103
    ALOAD 0
    GETSTATIC akg.cH : Lapg;
    GETSTATIC adc.m : Ladc;
    INVOKEVIRTUAL adc.a ()I
    LDC "brown_stained_glass_pane"
    INVOKEVIRTUAL bsu.a (Lakf;ILjava/lang/String;)V
   L104
    LINENUMBER 805 L104
    ALOAD 0
    GETSTATIC akg.cH : Lapg;
    GETSTATIC adc.j : Ladc;
    INVOKEVIRTUAL adc.a ()I
    LDC "cyan_stained_glass_pane"
    INVOKEVIRTUAL bsu.a (Lakf;ILjava/lang/String;)V
   L105
    LINENUMBER 806 L105
    ALOAD 0
    GETSTATIC akg.cH : Lapg;
    GETSTATIC adc.h : Ladc;
    INVOKEVIRTUAL adc.a ()I
    LDC "gray_stained_glass_pane"
    INVOKEVIRTUAL bsu.a (Lakf;ILjava/lang/String;)V
   L106
    LINENUMBER 807 L106
    ALOAD 0
    GETSTATIC akg.cH : Lapg;
    GETSTATIC adc.n : Ladc;
    INVOKEVIRTUAL adc.a ()I
    LDC "green_stained_glass_pane"
    INVOKEVIRTUAL bsu.a (Lakf;ILjava/lang/String;)V
   L107
    LINENUMBER 808 L107
    ALOAD 0
    GETSTATIC akg.cH : Lapg;
    GETSTATIC adc.d : Ladc;
    INVOKEVIRTUAL adc.a ()I
    LDC "light_blue_stained_glass_pane"
    INVOKEVIRTUAL bsu.a (Lakf;ILjava/lang/String;)V
   L108
    LINENUMBER 809 L108
    ALOAD 0
    GETSTATIC akg.cH : Lapg;
    GETSTATIC adc.f : Ladc;
    INVOKEVIRTUAL adc.a ()I
    LDC "lime_stained_glass_pane"
    INVOKEVIRTUAL bsu.a (Lakf;ILjava/lang/String;)V
   L109
    LINENUMBER 810 L109
    ALOAD 0
    GETSTATIC akg.cH : Lapg;
    GETSTATIC adc.c : Ladc;
    INVOKEVIRTUAL adc.a ()I
    LDC "magenta_stained_glass_pane"
    INVOKEVIRTUAL bsu.a (Lakf;ILjava/lang/String;)V
   L110
    LINENUMBER 811 L110
    ALOAD 0
    GETSTATIC akg.cH : Lapg;
    GETSTATIC adc.b : Ladc;
    INVOKEVIRTUAL adc.a ()I
    LDC "orange_stained_glass_pane"
    INVOKEVIRTUAL bsu.a (Lakf;ILjava/lang/String;)V
   L111
    LINENUMBER 812 L111
    ALOAD 0
    GETSTATIC akg.cH : Lapg;
    GETSTATIC adc.g : Ladc;
    INVOKEVIRTUAL adc.a ()I
    LDC "pink_stained_glass_pane"
    INVOKEVIRTUAL bsu.a (Lakf;ILjava/lang/String;)V
   L112
    LINENUMBER 813 L112
    ALOAD 0
    GETSTATIC akg.cH : Lapg;
    GETSTATIC adc.k : Ladc;
    INVOKEVIRTUAL adc.a ()I
    LDC "purple_stained_glass_pane"
    INVOKEVIRTUAL bsu.a (Lakf;ILjava/lang/String;)V
   L113
    LINENUMBER 814 L113
    ALOAD 0
    GETSTATIC akg.cH : Lapg;
    GETSTATIC adc.o : Ladc;
    INVOKEVIRTUAL adc.a ()I
    LDC "red_stained_glass_pane"
    INVOKEVIRTUAL bsu.a (Lakf;ILjava/lang/String;)V
   L114
    LINENUMBER 815 L114
    ALOAD 0
    GETSTATIC akg.cH : Lapg;
    GETSTATIC adc.i : Ladc;
    INVOKEVIRTUAL adc.a ()I
    LDC "silver_stained_glass_pane"
    INVOKEVIRTUAL bsu.a (Lakf;ILjava/lang/String;)V
   L115
    LINENUMBER 816 L115
    ALOAD 0
    GETSTATIC akg.cH : Lapg;
    GETSTATIC adc.a : Ladc;
    INVOKEVIRTUAL adc.a ()I
    LDC "white_stained_glass_pane"
    INVOKEVIRTUAL bsu.a (Lakf;ILjava/lang/String;)V
   L116
    LINENUMBER 817 L116
    ALOAD 0
    GETSTATIC akg.cH : Lapg;
    GETSTATIC adc.e : Ladc;
    INVOKEVIRTUAL adc.a ()I
    LDC "yellow_stained_glass_pane"
    INVOKEVIRTUAL bsu.a (Lakf;ILjava/lang/String;)V
   L117
    LINENUMBER 818 L117
    ALOAD 0
    GETSTATIC akg.cu : Lakf;
    GETSTATIC adc.p : Ladc;
    INVOKEVIRTUAL adc.a ()I
    LDC "black_stained_hardened_clay"
    INVOKEVIRTUAL bsu.a (Lakf;ILjava/lang/String;)V
   L118
    LINENUMBER 819 L118
    ALOAD 0
    GETSTATIC akg.cu : Lakf;
    GETSTATIC adc.l : Ladc;
    INVOKEVIRTUAL adc.a ()I
    LDC "blue_stained_hardened_clay"
    INVOKEVIRTUAL bsu.a (Lakf;ILjava/lang/String;)V
   L119
    LINENUMBER 820 L119
    ALOAD 0
    GETSTATIC akg.cu : Lakf;
    GETSTATIC adc.m : Ladc;
    INVOKEVIRTUAL adc.a ()I
    LDC "brown_stained_hardened_clay"
    INVOKEVIRTUAL bsu.a (Lakf;ILjava/lang/String;)V
   L120
    LINENUMBER 821 L120
    ALOAD 0
    GETSTATIC akg.cu : Lakf;
    GETSTATIC adc.j : Ladc;
    INVOKEVIRTUAL adc.a ()I
    LDC "cyan_stained_hardened_clay"
    INVOKEVIRTUAL bsu.a (Lakf;ILjava/lang/String;)V
   L121
    LINENUMBER 822 L121
    ALOAD 0
    GETSTATIC akg.cu : Lakf;
    GETSTATIC adc.h : Ladc;
    INVOKEVIRTUAL adc.a ()I
    LDC "gray_stained_hardened_clay"
    INVOKEVIRTUAL bsu.a (Lakf;ILjava/lang/String;)V
   L122
    LINENUMBER 823 L122
    ALOAD 0
    GETSTATIC akg.cu : Lakf;
    GETSTATIC adc.n : Ladc;
    INVOKEVIRTUAL adc.a ()I
    LDC "green_stained_hardened_clay"
    INVOKEVIRTUAL bsu.a (Lakf;ILjava/lang/String;)V
   L123
    LINENUMBER 824 L123
    ALOAD 0
    GETSTATIC akg.cu : Lakf;
    GETSTATIC adc.d : Ladc;
    INVOKEVIRTUAL adc.a ()I
    LDC "light_blue_stained_hardened_clay"
    INVOKEVIRTUAL bsu.a (Lakf;ILjava/lang/String;)V
   L124
    LINENUMBER 825 L124
    ALOAD 0
    GETSTATIC akg.cu : Lakf;
    GETSTATIC adc.f : Ladc;
    INVOKEVIRTUAL adc.a ()I
    LDC "lime_stained_hardened_clay"
    INVOKEVIRTUAL bsu.a (Lakf;ILjava/lang/String;)V
   L125
    LINENUMBER 826 L125
    ALOAD 0
    GETSTATIC akg.cu : Lakf;
    GETSTATIC adc.c : Ladc;
    INVOKEVIRTUAL adc.a ()I
    LDC "magenta_stained_hardened_clay"
    INVOKEVIRTUAL bsu.a (Lakf;ILjava/lang/String;)V
   L126
    LINENUMBER 827 L126
    ALOAD 0
    GETSTATIC akg.cu : Lakf;
    GETSTATIC adc.b : Ladc;
    INVOKEVIRTUAL adc.a ()I
    LDC "orange_stained_hardened_clay"
    INVOKEVIRTUAL bsu.a (Lakf;ILjava/lang/String;)V
   L127
    LINENUMBER 828 L127
    ALOAD 0
    GETSTATIC akg.cu : Lakf;
    GETSTATIC adc.g : Ladc;
    INVOKEVIRTUAL adc.a ()I
    LDC "pink_stained_hardened_clay"
    INVOKEVIRTUAL bsu.a (Lakf;ILjava/lang/String;)V
   L128
    LINENUMBER 829 L128
    ALOAD 0
    GETSTATIC akg.cu : Lakf;
    GETSTATIC adc.k : Ladc;
    INVOKEVIRTUAL adc.a ()I
    LDC "purple_stained_hardened_clay"
    INVOKEVIRTUAL bsu.a (Lakf;ILjava/lang/String;)V
   L129
    LINENUMBER 830 L129
    ALOAD 0
    GETSTATIC akg.cu : Lakf;
    GETSTATIC adc.o : Ladc;
    INVOKEVIRTUAL adc.a ()I
    LDC "red_stained_hardened_clay"
    INVOKEVIRTUAL bsu.a (Lakf;ILjava/lang/String;)V
   L130
    LINENUMBER 831 L130
    ALOAD 0
    GETSTATIC akg.cu : Lakf;
    GETSTATIC adc.i : Ladc;
    INVOKEVIRTUAL adc.a ()I
    LDC "silver_stained_hardened_clay"
    INVOKEVIRTUAL bsu.a (Lakf;ILjava/lang/String;)V
   L131
    LINENUMBER 832 L131
    ALOAD 0
    GETSTATIC akg.cu : Lakf;
    GETSTATIC adc.a : Ladc;
    INVOKEVIRTUAL adc.a ()I
    LDC "white_stained_hardened_clay"
    INVOKEVIRTUAL bsu.a (Lakf;ILjava/lang/String;)V
   L132
    LINENUMBER 833 L132
    ALOAD 0
    GETSTATIC akg.cu : Lakf;
    GETSTATIC adc.e : Ladc;
    INVOKEVIRTUAL adc.a ()I
    LDC "yellow_stained_hardened_clay"
    INVOKEVIRTUAL bsu.a (Lakf;ILjava/lang/String;)V
   L133
    LINENUMBER 834 L133
    ALOAD 0
    GETSTATIC akg.b : Lakf;
    GETSTATIC apl$a.f : Lapl$a;
    INVOKEVIRTUAL apl$a.a ()I
    LDC "andesite"
    INVOKEVIRTUAL bsu.a (Lakf;ILjava/lang/String;)V
   L134
    LINENUMBER 835 L134
    ALOAD 0
    GETSTATIC akg.b : Lakf;
    GETSTATIC apl$a.g : Lapl$a;
    INVOKEVIRTUAL apl$a.a ()I
    LDC "andesite_smooth"
    INVOKEVIRTUAL bsu.a (Lakf;ILjava/lang/String;)V
   L135
    LINENUMBER 836 L135
    ALOAD 0
    GETSTATIC akg.b : Lakf;
    GETSTATIC apl$a.d : Lapl$a;
    INVOKEVIRTUAL apl$a.a ()I
    LDC "diorite"
    INVOKEVIRTUAL bsu.a (Lakf;ILjava/lang/String;)V
   L136
    LINENUMBER 837 L136
    ALOAD 0
    GETSTATIC akg.b : Lakf;
    GETSTATIC apl$a.e : Lapl$a;
    INVOKEVIRTUAL apl$a.a ()I
    LDC "diorite_smooth"
    INVOKEVIRTUAL bsu.a (Lakf;ILjava/lang/String;)V
   L137
    LINENUMBER 838 L137
    ALOAD 0
    GETSTATIC akg.b : Lakf;
    GETSTATIC apl$a.b : Lapl$a;
    INVOKEVIRTUAL apl$a.a ()I
    LDC "granite"
    INVOKEVIRTUAL bsu.a (Lakf;ILjava/lang/String;)V
   L138
    LINENUMBER 839 L138
    ALOAD 0
    GETSTATIC akg.b : Lakf;
    GETSTATIC apl$a.c : Lapl$a;
    INVOKEVIRTUAL apl$a.a ()I
    LDC "granite_smooth"
    INVOKEVIRTUAL bsu.a (Lakf;ILjava/lang/String;)V
   L139
    LINENUMBER 840 L139
    ALOAD 0
    GETSTATIC akg.b : Lakf;
    GETSTATIC apl$a.a : Lapl$a;
    INVOKEVIRTUAL apl$a.a ()I
    LDC "stone"
    INVOKEVIRTUAL bsu.a (Lakf;ILjava/lang/String;)V
   L140
    LINENUMBER 841 L140
    ALOAD 0
    GETSTATIC akg.bf : Lakf;
    GETSTATIC apm$a.c : Lapm$a;
    INVOKEVIRTUAL apm$a.a ()I
    LDC "cracked_stonebrick"
    INVOKEVIRTUAL bsu.a (Lakf;ILjava/lang/String;)V
   L141
    LINENUMBER 842 L141
    ALOAD 0
    GETSTATIC akg.bf : Lakf;
    GETSTATIC apm$a.a : Lapm$a;
    INVOKEVIRTUAL apm$a.a ()I
    LDC "stonebrick"
    INVOKEVIRTUAL bsu.a (Lakf;ILjava/lang/String;)V
   L142
    LINENUMBER 843 L142
    ALOAD 0
    GETSTATIC akg.bf : Lakf;
    GETSTATIC apm$a.d : Lapm$a;
    INVOKEVIRTUAL apm$a.a ()I
    LDC "chiseled_stonebrick"
    INVOKEVIRTUAL bsu.a (Lakf;ILjava/lang/String;)V
   L143
    LINENUMBER 844 L143
    ALOAD 0
    GETSTATIC akg.bf : Lakf;
    GETSTATIC apm$a.b : Lapm$a;
    INVOKEVIRTUAL apm$a.a ()I
    LDC "mossy_stonebrick"
    INVOKEVIRTUAL bsu.a (Lakf;ILjava/lang/String;)V
   L144
    LINENUMBER 845 L144
    ALOAD 0
    GETSTATIC akg.U : Lamm;
    GETSTATIC apo$a.e : Lapo$a;
    INVOKEVIRTUAL apo$a.a ()I
    LDC "brick_slab"
    INVOKEVIRTUAL bsu.a (Lakf;ILjava/lang/String;)V
   L145
    LINENUMBER 846 L145
    ALOAD 0
    GETSTATIC akg.U : Lamm;
    GETSTATIC apo$a.d : Lapo$a;
    INVOKEVIRTUAL apo$a.a ()I
    LDC "cobblestone_slab"
    INVOKEVIRTUAL bsu.a (Lakf;ILjava/lang/String;)V
   L146
    LINENUMBER 847 L146
    ALOAD 0
    GETSTATIC akg.U : Lamm;
    GETSTATIC apo$a.c : Lapo$a;
    INVOKEVIRTUAL apo$a.a ()I
    LDC "old_wood_slab"
    INVOKEVIRTUAL bsu.a (Lakf;ILjava/lang/String;)V
   L147
    LINENUMBER 848 L147
    ALOAD 0
    GETSTATIC akg.U : Lamm;
    GETSTATIC apo$a.g : Lapo$a;
    INVOKEVIRTUAL apo$a.a ()I
    LDC "nether_brick_slab"
    INVOKEVIRTUAL bsu.a (Lakf;ILjava/lang/String;)V
   L148
    LINENUMBER 849 L148
    ALOAD 0
    GETSTATIC akg.U : Lamm;
    GETSTATIC apo$a.h : Lapo$a;
    INVOKEVIRTUAL apo$a.a ()I
    LDC "quartz_slab"
    INVOKEVIRTUAL bsu.a (Lakf;ILjava/lang/String;)V
   L149
    LINENUMBER 850 L149
    ALOAD 0
    GETSTATIC akg.U : Lamm;
    GETSTATIC apo$a.b : Lapo$a;
    INVOKEVIRTUAL apo$a.a ()I
    LDC "sandstone_slab"
    INVOKEVIRTUAL bsu.a (Lakf;ILjava/lang/String;)V
   L150
    LINENUMBER 851 L150
    ALOAD 0
    GETSTATIC akg.U : Lamm;
    GETSTATIC apo$a.f : Lapo$a;
    INVOKEVIRTUAL apo$a.a ()I
    LDC "stone_brick_slab"
    INVOKEVIRTUAL bsu.a (Lakf;ILjava/lang/String;)V
   L151
    LINENUMBER 852 L151
    ALOAD 0
    GETSTATIC akg.U : Lamm;
    GETSTATIC apo$a.a : Lapo$a;
    INVOKEVIRTUAL apo$a.a ()I
    LDC "stone_slab"
    INVOKEVIRTUAL bsu.a (Lakf;ILjava/lang/String;)V
   L152
    LINENUMBER 853 L152
    ALOAD 0
    GETSTATIC akg.cP : Lamm;
    GETSTATIC anp$a.a : Lanp$a;
    INVOKEVIRTUAL anp$a.a ()I
    LDC "red_sandstone_slab"
    INVOKEVIRTUAL bsu.a (Lakf;ILjava/lang/String;)V
   L153
    LINENUMBER 854 L153
    ALOAD 0
    GETSTATIC akg.H : Lapr;
    GETSTATIC apr$a.a : Lapr$a;
    INVOKEVIRTUAL apr$a.a ()I
    LDC "dead_bush"
    INVOKEVIRTUAL bsu.a (Lakf;ILjava/lang/String;)V
   L154
    LINENUMBER 855 L154
    ALOAD 0
    GETSTATIC akg.H : Lapr;
    GETSTATIC apr$a.c : Lapr$a;
    INVOKEVIRTUAL apr$a.a ()I
    LDC "fern"
    INVOKEVIRTUAL bsu.a (Lakf;ILjava/lang/String;)V
   L155
    LINENUMBER 856 L155
    ALOAD 0
    GETSTATIC akg.H : Lapr;
    GETSTATIC apr$a.b : Lapr$a;
    INVOKEVIRTUAL apr$a.a ()I
    LDC "tall_grass"
    INVOKEVIRTUAL bsu.a (Lakf;ILjava/lang/String;)V
   L156
    LINENUMBER 857 L156
    ALOAD 0
    GETSTATIC akg.bM : Lamm;
    GETSTATIC anx$a.e : Lanx$a;
    INVOKEVIRTUAL anx$a.a ()I
    LDC "acacia_slab"
    INVOKEVIRTUAL bsu.a (Lakf;ILjava/lang/String;)V
   L157
    LINENUMBER 858 L157
    ALOAD 0
    GETSTATIC akg.bM : Lamm;
    GETSTATIC anx$a.c : Lanx$a;
    INVOKEVIRTUAL anx$a.a ()I
    LDC "birch_slab"
    INVOKEVIRTUAL bsu.a (Lakf;ILjava/lang/String;)V
   L158
    LINENUMBER 859 L158
    ALOAD 0
    GETSTATIC akg.bM : Lamm;
    GETSTATIC anx$a.f : Lanx$a;
    INVOKEVIRTUAL anx$a.a ()I
    LDC "dark_oak_slab"
    INVOKEVIRTUAL bsu.a (Lakf;ILjava/lang/String;)V
   L159
    LINENUMBER 860 L159
    ALOAD 0
    GETSTATIC akg.bM : Lamm;
    GETSTATIC anx$a.d : Lanx$a;
    INVOKEVIRTUAL anx$a.a ()I
    LDC "jungle_slab"
    INVOKEVIRTUAL bsu.a (Lakf;ILjava/lang/String;)V
   L160
    LINENUMBER 861 L160
    ALOAD 0
    GETSTATIC akg.bM : Lamm;
    GETSTATIC anx$a.a : Lanx$a;
    INVOKEVIRTUAL anx$a.a ()I
    LDC "oak_slab"
    INVOKEVIRTUAL bsu.a (Lakf;ILjava/lang/String;)V
   L161
    LINENUMBER 862 L161
    ALOAD 0
    GETSTATIC akg.bM : Lamm;
    GETSTATIC anx$a.b : Lanx$a;
    INVOKEVIRTUAL anx$a.a ()I
    LDC "spruce_slab"
    INVOKEVIRTUAL bsu.a (Lakf;ILjava/lang/String;)V
   L162
    LINENUMBER 863 L162
    ALOAD 0
    GETSTATIC akg.L : Lakf;
    GETSTATIC adc.p : Ladc;
    INVOKEVIRTUAL adc.a ()I
    LDC "black_wool"
    INVOKEVIRTUAL bsu.a (Lakf;ILjava/lang/String;)V
   L163
    LINENUMBER 864 L163
    ALOAD 0
    GETSTATIC akg.L : Lakf;
    GETSTATIC adc.l : Ladc;
    INVOKEVIRTUAL adc.a ()I
    LDC "blue_wool"
    INVOKEVIRTUAL bsu.a (Lakf;ILjava/lang/String;)V
   L164
    LINENUMBER 865 L164
    ALOAD 0
    GETSTATIC akg.L : Lakf;
    GETSTATIC adc.m : Ladc;
    INVOKEVIRTUAL adc.a ()I
    LDC "brown_wool"
    INVOKEVIRTUAL bsu.a (Lakf;ILjava/lang/String;)V
   L165
    LINENUMBER 866 L165
    ALOAD 0
    GETSTATIC akg.L : Lakf;
    GETSTATIC adc.j : Ladc;
    INVOKEVIRTUAL adc.a ()I
    LDC "cyan_wool"
    INVOKEVIRTUAL bsu.a (Lakf;ILjava/lang/String;)V
   L166
    LINENUMBER 867 L166
    ALOAD 0
    GETSTATIC akg.L : Lakf;
    GETSTATIC adc.h : Ladc;
    INVOKEVIRTUAL adc.a ()I
    LDC "gray_wool"
    INVOKEVIRTUAL bsu.a (Lakf;ILjava/lang/String;)V
   L167
    LINENUMBER 868 L167
    ALOAD 0
    GETSTATIC akg.L : Lakf;
    GETSTATIC adc.n : Ladc;
    INVOKEVIRTUAL adc.a ()I
    LDC "green_wool"
    INVOKEVIRTUAL bsu.a (Lakf;ILjava/lang/String;)V
   L168
    LINENUMBER 869 L168
    ALOAD 0
    GETSTATIC akg.L : Lakf;
    GETSTATIC adc.d : Ladc;
    INVOKEVIRTUAL adc.a ()I
    LDC "light_blue_wool"
    INVOKEVIRTUAL bsu.a (Lakf;ILjava/lang/String;)V
   L169
    LINENUMBER 870 L169
    ALOAD 0
    GETSTATIC akg.L : Lakf;
    GETSTATIC adc.f : Ladc;
    INVOKEVIRTUAL adc.a ()I
    LDC "lime_wool"
    INVOKEVIRTUAL bsu.a (Lakf;ILjava/lang/String;)V
   L170
    LINENUMBER 871 L170
    ALOAD 0
    GETSTATIC akg.L : Lakf;
    GETSTATIC adc.c : Ladc;
    INVOKEVIRTUAL adc.a ()I
    LDC "magenta_wool"
    INVOKEVIRTUAL bsu.a (Lakf;ILjava/lang/String;)V
   L171
    LINENUMBER 872 L171
    ALOAD 0
    GETSTATIC akg.L : Lakf;
    GETSTATIC adc.b : Ladc;
    INVOKEVIRTUAL adc.a ()I
    LDC "orange_wool"
    INVOKEVIRTUAL bsu.a (Lakf;ILjava/lang/String;)V
   L172
    LINENUMBER 873 L172
    ALOAD 0
    GETSTATIC akg.L : Lakf;
    GETSTATIC adc.g : Ladc;
    INVOKEVIRTUAL adc.a ()I
    LDC "pink_wool"
    INVOKEVIRTUAL bsu.a (Lakf;ILjava/lang/String;)V
   L173
    LINENUMBER 874 L173
    ALOAD 0
    GETSTATIC akg.L : Lakf;
    GETSTATIC adc.k : Ladc;
    INVOKEVIRTUAL adc.a ()I
    LDC "purple_wool"
    INVOKEVIRTUAL bsu.a (Lakf;ILjava/lang/String;)V
   L174
    LINENUMBER 875 L174
    ALOAD 0
    GETSTATIC akg.L : Lakf;
    GETSTATIC adc.o : Ladc;
    INVOKEVIRTUAL adc.a ()I
    LDC "red_wool"
    INVOKEVIRTUAL bsu.a (Lakf;ILjava/lang/String;)V
   L175
    LINENUMBER 876 L175
    ALOAD 0
    GETSTATIC akg.L : Lakf;
    GETSTATIC adc.i : Ladc;
    INVOKEVIRTUAL adc.a ()I
    LDC "silver_wool"
    INVOKEVIRTUAL bsu.a (Lakf;ILjava/lang/String;)V
   L176
    LINENUMBER 877 L176
    ALOAD 0
    GETSTATIC akg.L : Lakf;
    GETSTATIC adc.a : Ladc;
    INVOKEVIRTUAL adc.a ()I
    LDC "white_wool"
    INVOKEVIRTUAL bsu.a (Lakf;ILjava/lang/String;)V
   L177
    LINENUMBER 878 L177
    ALOAD 0
    GETSTATIC akg.L : Lakf;
    GETSTATIC adc.e : Ladc;
    INVOKEVIRTUAL adc.a ()I
    LDC "yellow_wool"
    INVOKEVIRTUAL bsu.a (Lakf;ILjava/lang/String;)V
   L178
    LINENUMBER 879 L178
    ALOAD 0
    GETSTATIC akg.ak : Lakf;
    LDC "farmland"
    INVOKESPECIAL bsu.a (Lakf;Ljava/lang/String;)V
   L179
    LINENUMBER 880 L179
    ALOAD 0
    GETSTATIC akg.cC : Lakf;
    LDC "acacia_stairs"
    INVOKESPECIAL bsu.a (Lakf;Ljava/lang/String;)V
   L180
    LINENUMBER 881 L180
    ALOAD 0
    GETSTATIC akg.cs : Lakf;
    LDC "activator_rail"
    INVOKESPECIAL bsu.a (Lakf;Ljava/lang/String;)V
   L181
    LINENUMBER 882 L181
    ALOAD 0
    GETSTATIC akg.bY : Lakc;
    LDC "beacon"
    INVOKESPECIAL bsu.a (Lakf;Ljava/lang/String;)V
   L182
    LINENUMBER 883 L182
    ALOAD 0
    GETSTATIC akg.h : Lakf;
    LDC "bedrock"
    INVOKESPECIAL bsu.a (Lakf;Ljava/lang/String;)V
   L183
    LINENUMBER 884 L183
    ALOAD 0
    GETSTATIC akg.bV : Lakf;
    LDC "birch_stairs"
    INVOKESPECIAL bsu.a (Lakf;Ljava/lang/String;)V
   L184
    LINENUMBER 885 L184
    ALOAD 0
    GETSTATIC akg.X : Lakf;
    LDC "bookshelf"
    INVOKESPECIAL bsu.a (Lakf;Ljava/lang/String;)V
   L185
    LINENUMBER 886 L185
    ALOAD 0
    GETSTATIC akg.V : Lakf;
    LDC "brick_block"
    INVOKESPECIAL bsu.a (Lakf;Ljava/lang/String;)V
   L186
    LINENUMBER 887 L186
    ALOAD 0
    GETSTATIC akg.V : Lakf;
    LDC "brick_block"
    INVOKESPECIAL bsu.a (Lakf;Ljava/lang/String;)V
   L187
    LINENUMBER 888 L187
    ALOAD 0
    GETSTATIC akg.bu : Lakf;
    LDC "brick_stairs"
    INVOKESPECIAL bsu.a (Lakf;Ljava/lang/String;)V
   L188
    LINENUMBER 889 L188
    ALOAD 0
    GETSTATIC akg.P : Lakl;
    LDC "brown_mushroom"
    INVOKESPECIAL bsu.a (Lakf;Ljava/lang/String;)V
   L189
    LINENUMBER 890 L189
    ALOAD 0
    GETSTATIC akg.aK : Lakn;
    LDC "cactus"
    INVOKESPECIAL bsu.a (Lakf;Ljava/lang/String;)V
   L190
    LINENUMBER 891 L190
    ALOAD 0
    GETSTATIC akg.aL : Lakf;
    LDC "clay"
    INVOKESPECIAL bsu.a (Lakf;Ljava/lang/String;)V
   L191
    LINENUMBER 892 L191
    ALOAD 0
    GETSTATIC akg.cA : Lakf;
    LDC "coal_block"
    INVOKESPECIAL bsu.a (Lakf;Ljava/lang/String;)V
   L192
    LINENUMBER 893 L192
    ALOAD 0
    GETSTATIC akg.q : Lakf;
    LDC "coal_ore"
    INVOKESPECIAL bsu.a (Lakf;Ljava/lang/String;)V
   L193
    LINENUMBER 894 L193
    ALOAD 0
    GETSTATIC akg.e : Lakf;
    LDC "cobblestone"
    INVOKESPECIAL bsu.a (Lakf;Ljava/lang/String;)V
   L194
    LINENUMBER 895 L194
    ALOAD 0
    GETSTATIC akg.ai : Lakf;
    LDC "crafting_table"
    INVOKESPECIAL bsu.a (Lakf;Ljava/lang/String;)V
   L195
    LINENUMBER 896 L195
    ALOAD 0
    GETSTATIC akg.cD : Lakf;
    LDC "dark_oak_stairs"
    INVOKESPECIAL bsu.a (Lakf;Ljava/lang/String;)V
   L196
    LINENUMBER 897 L196
    ALOAD 0
    GETSTATIC akg.cl : Lalb;
    LDC "daylight_detector"
    INVOKESPECIAL bsu.a (Lakf;Ljava/lang/String;)V
   L197
    LINENUMBER 898 L197
    ALOAD 0
    GETSTATIC akg.I : Lalc;
    LDC "dead_bush"
    INVOKESPECIAL bsu.a (Lakf;Ljava/lang/String;)V
   L198
    LINENUMBER 899 L198
    ALOAD 0
    GETSTATIC akg.E : Lakf;
    LDC "detector_rail"
    INVOKESPECIAL bsu.a (Lakf;Ljava/lang/String;)V
   L199
    LINENUMBER 900 L199
    ALOAD 0
    GETSTATIC akg.ah : Lakf;
    LDC "diamond_block"
    INVOKESPECIAL bsu.a (Lakf;Ljava/lang/String;)V
   L200
    LINENUMBER 901 L200
    ALOAD 0
    GETSTATIC akg.ag : Lakf;
    LDC "diamond_ore"
    INVOKESPECIAL bsu.a (Lakf;Ljava/lang/String;)V
   L201
    LINENUMBER 902 L201
    ALOAD 0
    GETSTATIC akg.z : Lakf;
    LDC "dispenser"
    INVOKESPECIAL bsu.a (Lakf;Ljava/lang/String;)V
   L202
    LINENUMBER 903 L202
    ALOAD 0
    GETSTATIC akg.ct : Lakf;
    LDC "dropper"
    INVOKESPECIAL bsu.a (Lakf;Ljava/lang/String;)V
   L203
    LINENUMBER 904 L203
    ALOAD 0
    GETSTATIC akg.bT : Lakf;
    LDC "emerald_block"
    INVOKESPECIAL bsu.a (Lakf;Ljava/lang/String;)V
   L204
    LINENUMBER 905 L204
    ALOAD 0
    GETSTATIC akg.bP : Lakf;
    LDC "emerald_ore"
    INVOKESPECIAL bsu.a (Lakf;Ljava/lang/String;)V
   L205
    LINENUMBER 906 L205
    ALOAD 0
    GETSTATIC akg.bC : Lakf;
    LDC "enchanting_table"
    INVOKESPECIAL bsu.a (Lakf;Ljava/lang/String;)V
   L206
    LINENUMBER 907 L206
    ALOAD 0
    GETSTATIC akg.bG : Lakf;
    LDC "end_portal_frame"
    INVOKESPECIAL bsu.a (Lakf;Ljava/lang/String;)V
   L207
    LINENUMBER 908 L207
    ALOAD 0
    GETSTATIC akg.bH : Lakf;
    LDC "end_stone"
    INVOKESPECIAL bsu.a (Lakf;Ljava/lang/String;)V
   L208
    LINENUMBER 909 L208
    ALOAD 0
    GETSTATIC akg.aO : Lakf;
    LDC "oak_fence"
    INVOKESPECIAL bsu.a (Lakf;Ljava/lang/String;)V
   L209
    LINENUMBER 910 L209
    ALOAD 0
    GETSTATIC akg.aP : Lakf;
    LDC "spruce_fence"
    INVOKESPECIAL bsu.a (Lakf;Ljava/lang/String;)V
   L210
    LINENUMBER 911 L210
    ALOAD 0
    GETSTATIC akg.aQ : Lakf;
    LDC "birch_fence"
    INVOKESPECIAL bsu.a (Lakf;Ljava/lang/String;)V
   L211
    LINENUMBER 912 L211
    ALOAD 0
    GETSTATIC akg.aR : Lakf;
    LDC "jungle_fence"
    INVOKESPECIAL bsu.a (Lakf;Ljava/lang/String;)V
   L212
    LINENUMBER 913 L212
    ALOAD 0
    GETSTATIC akg.aS : Lakf;
    LDC "dark_oak_fence"
    INVOKESPECIAL bsu.a (Lakf;Ljava/lang/String;)V
   L213
    LINENUMBER 914 L213
    ALOAD 0
    GETSTATIC akg.aT : Lakf;
    LDC "acacia_fence"
    INVOKESPECIAL bsu.a (Lakf;Ljava/lang/String;)V
   L214
    LINENUMBER 915 L214
    ALOAD 0
    GETSTATIC akg.bo : Lakf;
    LDC "oak_fence_gate"
    INVOKESPECIAL bsu.a (Lakf;Ljava/lang/String;)V
   L215
    LINENUMBER 916 L215
    ALOAD 0
    GETSTATIC akg.bp : Lakf;
    LDC "spruce_fence_gate"
    INVOKESPECIAL bsu.a (Lakf;Ljava/lang/String;)V
   L216
    LINENUMBER 917 L216
    ALOAD 0
    GETSTATIC akg.bq : Lakf;
    LDC "birch_fence_gate"
    INVOKESPECIAL bsu.a (Lakf;Ljava/lang/String;)V
   L217
    LINENUMBER 918 L217
    ALOAD 0
    GETSTATIC akg.br : Lakf;
    LDC "jungle_fence_gate"
    INVOKESPECIAL bsu.a (Lakf;Ljava/lang/String;)V
   L218
    LINENUMBER 919 L218
    ALOAD 0
    GETSTATIC akg.bs : Lakf;
    LDC "dark_oak_fence_gate"
    INVOKESPECIAL bsu.a (Lakf;Ljava/lang/String;)V
   L219
    LINENUMBER 920 L219
    ALOAD 0
    GETSTATIC akg.bt : Lakf;
    LDC "acacia_fence_gate"
    INVOKESPECIAL bsu.a (Lakf;Ljava/lang/String;)V
   L220
    LINENUMBER 921 L220
    ALOAD 0
    GETSTATIC akg.al : Lakf;
    LDC "furnace"
    INVOKESPECIAL bsu.a (Lakf;Ljava/lang/String;)V
   L221
    LINENUMBER 922 L221
    ALOAD 0
    GETSTATIC akg.w : Lakf;
    LDC "glass"
    INVOKESPECIAL bsu.a (Lakf;Ljava/lang/String;)V
   L222
    LINENUMBER 923 L222
    ALOAD 0
    GETSTATIC akg.bj : Lakf;
    LDC "glass_pane"
    INVOKESPECIAL bsu.a (Lakf;Ljava/lang/String;)V
   L223
    LINENUMBER 924 L223
    ALOAD 0
    GETSTATIC akg.aX : Lakf;
    LDC "glowstone"
    INVOKESPECIAL bsu.a (Lakf;Ljava/lang/String;)V
   L224
    LINENUMBER 925 L224
    ALOAD 0
    GETSTATIC akg.D : Lakf;
    LDC "golden_rail"
    INVOKESPECIAL bsu.a (Lakf;Ljava/lang/String;)V
   L225
    LINENUMBER 926 L225
    ALOAD 0
    GETSTATIC akg.R : Lakf;
    LDC "gold_block"
    INVOKESPECIAL bsu.a (Lakf;Ljava/lang/String;)V
   L226
    LINENUMBER 927 L226
    ALOAD 0
    GETSTATIC akg.o : Lakf;
    LDC "gold_ore"
    INVOKESPECIAL bsu.a (Lakf;Ljava/lang/String;)V
   L227
    LINENUMBER 928 L227
    ALOAD 0
    GETSTATIC akg.c : Lami;
    LDC "grass"
    INVOKESPECIAL bsu.a (Lakf;Ljava/lang/String;)V
   L228
    LINENUMBER 929 L228
    ALOAD 0
    GETSTATIC akg.da : Lakf;
    LDC "grass_path"
    INVOKESPECIAL bsu.a (Lakf;Ljava/lang/String;)V
   L229
    LINENUMBER 930 L229
    ALOAD 0
    GETSTATIC akg.n : Lakf;
    LDC "gravel"
    INVOKESPECIAL bsu.a (Lakf;Ljava/lang/String;)V
   L230
    LINENUMBER 931 L230
    ALOAD 0
    GETSTATIC akg.cz : Lakf;
    LDC "hardened_clay"
    INVOKESPECIAL bsu.a (Lakf;Ljava/lang/String;)V
   L231
    LINENUMBER 932 L231
    ALOAD 0
    GETSTATIC akg.cx : Lakf;
    LDC "hay_block"
    INVOKESPECIAL bsu.a (Lakf;Ljava/lang/String;)V
   L232
    LINENUMBER 933 L232
    ALOAD 0
    GETSTATIC akg.ci : Lakf;
    LDC "heavy_weighted_pressure_plate"
    INVOKESPECIAL bsu.a (Lakf;Ljava/lang/String;)V
   L233
    LINENUMBER 934 L233
    ALOAD 0
    GETSTATIC akg.cp : Lams;
    LDC "hopper"
    INVOKESPECIAL bsu.a (Lakf;Ljava/lang/String;)V
   L234
    LINENUMBER 935 L234
    ALOAD 0
    GETSTATIC akg.aI : Lakf;
    LDC "ice"
    INVOKESPECIAL bsu.a (Lakf;Ljava/lang/String;)V
   L235
    LINENUMBER 936 L235
    ALOAD 0
    GETSTATIC akg.bi : Lakf;
    LDC "iron_bars"
    INVOKESPECIAL bsu.a (Lakf;Ljava/lang/String;)V
   L236
    LINENUMBER 937 L236
    ALOAD 0
    GETSTATIC akg.S : Lakf;
    LDC "iron_block"
    INVOKESPECIAL bsu.a (Lakf;Ljava/lang/String;)V
   L237
    LINENUMBER 938 L237
    ALOAD 0
    GETSTATIC akg.p : Lakf;
    LDC "iron_ore"
    INVOKESPECIAL bsu.a (Lakf;Ljava/lang/String;)V
   L238
    LINENUMBER 939 L238
    ALOAD 0
    GETSTATIC akg.cw : Lakf;
    LDC "iron_trapdoor"
    INVOKESPECIAL bsu.a (Lakf;Ljava/lang/String;)V
   L239
    LINENUMBER 940 L239
    ALOAD 0
    GETSTATIC akg.aN : Lakf;
    LDC "jukebox"
    INVOKESPECIAL bsu.a (Lakf;Ljava/lang/String;)V
   L240
    LINENUMBER 941 L240
    ALOAD 0
    GETSTATIC akg.bW : Lakf;
    LDC "jungle_stairs"
    INVOKESPECIAL bsu.a (Lakf;Ljava/lang/String;)V
   L241
    LINENUMBER 942 L241
    ALOAD 0
    GETSTATIC akg.au : Lakf;
    LDC "ladder"
    INVOKESPECIAL bsu.a (Lakf;Ljava/lang/String;)V
   L242
    LINENUMBER 943 L242
    ALOAD 0
    GETSTATIC akg.y : Lakf;
    LDC "lapis_block"
    INVOKESPECIAL bsu.a (Lakf;Ljava/lang/String;)V
   L243
    LINENUMBER 944 L243
    ALOAD 0
    GETSTATIC akg.x : Lakf;
    LDC "lapis_ore"
    INVOKESPECIAL bsu.a (Lakf;Ljava/lang/String;)V
   L244
    LINENUMBER 945 L244
    ALOAD 0
    GETSTATIC akg.ay : Lakf;
    LDC "lever"
    INVOKESPECIAL bsu.a (Lakf;Ljava/lang/String;)V
   L245
    LINENUMBER 946 L245
    ALOAD 0
    GETSTATIC akg.ch : Lakf;
    LDC "light_weighted_pressure_plate"
    INVOKESPECIAL bsu.a (Lakf;Ljava/lang/String;)V
   L246
    LINENUMBER 947 L246
    ALOAD 0
    GETSTATIC akg.aZ : Lakf;
    LDC "lit_pumpkin"
    INVOKESPECIAL bsu.a (Lakf;Ljava/lang/String;)V
   L247
    LINENUMBER 948 L247
    ALOAD 0
    GETSTATIC akg.bk : Lakf;
    LDC "melon_block"
    INVOKESPECIAL bsu.a (Lakf;Ljava/lang/String;)V
   L248
    LINENUMBER 949 L248
    ALOAD 0
    GETSTATIC akg.Y : Lakf;
    LDC "mossy_cobblestone"
    INVOKESPECIAL bsu.a (Lakf;Ljava/lang/String;)V
   L249
    LINENUMBER 950 L249
    ALOAD 0
    GETSTATIC akg.bw : Lanj;
    LDC "mycelium"
    INVOKESPECIAL bsu.a (Lakf;Ljava/lang/String;)V
   L250
    LINENUMBER 951 L250
    ALOAD 0
    GETSTATIC akg.aV : Lakf;
    LDC "netherrack"
    INVOKESPECIAL bsu.a (Lakf;Ljava/lang/String;)V
   L251
    LINENUMBER 952 L251
    ALOAD 0
    GETSTATIC akg.by : Lakf;
    LDC "nether_brick"
    INVOKESPECIAL bsu.a (Lakf;Ljava/lang/String;)V
   L252
    LINENUMBER 953 L252
    ALOAD 0
    GETSTATIC akg.bz : Lakf;
    LDC "nether_brick_fence"
    INVOKESPECIAL bsu.a (Lakf;Ljava/lang/String;)V
   L253
    LINENUMBER 954 L253
    ALOAD 0
    GETSTATIC akg.bA : Lakf;
    LDC "nether_brick_stairs"
    INVOKESPECIAL bsu.a (Lakf;Ljava/lang/String;)V
   L254
    LINENUMBER 955 L254
    ALOAD 0
    GETSTATIC akg.B : Lakf;
    LDC "noteblock"
    INVOKESPECIAL bsu.a (Lakf;Ljava/lang/String;)V
   L255
    LINENUMBER 956 L255
    ALOAD 0
    GETSTATIC akg.ad : Lakf;
    LDC "oak_stairs"
    INVOKESPECIAL bsu.a (Lakf;Ljava/lang/String;)V
   L256
    LINENUMBER 957 L256
    ALOAD 0
    GETSTATIC akg.Z : Lakf;
    LDC "obsidian"
    INVOKESPECIAL bsu.a (Lakf;Ljava/lang/String;)V
   L257
    LINENUMBER 958 L257
    ALOAD 0
    GETSTATIC akg.cB : Lakf;
    LDC "packed_ice"
    INVOKESPECIAL bsu.a (Lakf;Ljava/lang/String;)V
   L258
    LINENUMBER 959 L258
    ALOAD 0
    GETSTATIC akg.J : Larj;
    LDC "piston"
    INVOKESPECIAL bsu.a (Lakf;Ljava/lang/String;)V
   L259
    LINENUMBER 960 L259
    ALOAD 0
    GETSTATIC akg.aU : Lakf;
    LDC "pumpkin"
    INVOKESPECIAL bsu.a (Lakf;Ljava/lang/String;)V
   L260
    LINENUMBER 961 L260
    ALOAD 0
    GETSTATIC akg.co : Lakf;
    LDC "quartz_ore"
    INVOKESPECIAL bsu.a (Lakf;Ljava/lang/String;)V
   L261
    LINENUMBER 962 L261
    ALOAD 0
    GETSTATIC akg.cr : Lakf;
    LDC "quartz_stairs"
    INVOKESPECIAL bsu.a (Lakf;Ljava/lang/String;)V
   L262
    LINENUMBER 963 L262
    ALOAD 0
    GETSTATIC akg.av : Lakf;
    LDC "rail"
    INVOKESPECIAL bsu.a (Lakf;Ljava/lang/String;)V
   L263
    LINENUMBER 964 L263
    ALOAD 0
    GETSTATIC akg.cn : Lakf;
    LDC "redstone_block"
    INVOKESPECIAL bsu.a (Lakf;Ljava/lang/String;)V
   L264
    LINENUMBER 965 L264
    ALOAD 0
    GETSTATIC akg.bJ : Lakf;
    LDC "redstone_lamp"
    INVOKESPECIAL bsu.a (Lakf;Ljava/lang/String;)V
   L265
    LINENUMBER 966 L265
    ALOAD 0
    GETSTATIC akg.aC : Lakf;
    LDC "redstone_ore"
    INVOKESPECIAL bsu.a (Lakf;Ljava/lang/String;)V
   L266
    LINENUMBER 967 L266
    ALOAD 0
    GETSTATIC akg.aF : Lakf;
    LDC "redstone_torch"
    INVOKESPECIAL bsu.a (Lakf;Ljava/lang/String;)V
   L267
    LINENUMBER 968 L267
    ALOAD 0
    GETSTATIC akg.Q : Lakl;
    LDC "red_mushroom"
    INVOKESPECIAL bsu.a (Lakf;Ljava/lang/String;)V
   L268
    LINENUMBER 969 L268
    ALOAD 0
    GETSTATIC akg.bO : Lakf;
    LDC "sandstone_stairs"
    INVOKESPECIAL bsu.a (Lakf;Ljava/lang/String;)V
   L269
    LINENUMBER 970 L269
    ALOAD 0
    GETSTATIC akg.cN : Lakf;
    LDC "red_sandstone_stairs"
    INVOKESPECIAL bsu.a (Lakf;Ljava/lang/String;)V
   L270
    LINENUMBER 971 L270
    ALOAD 0
    GETSTATIC akg.cJ : Lakf;
    LDC "sea_lantern"
    INVOKESPECIAL bsu.a (Lakf;Ljava/lang/String;)V
   L271
    LINENUMBER 972 L271
    ALOAD 0
    GETSTATIC akg.cE : Lakf;
    LDC "slime"
    INVOKESPECIAL bsu.a (Lakf;Ljava/lang/String;)V
   L272
    LINENUMBER 973 L272
    ALOAD 0
    GETSTATIC akg.aJ : Lakf;
    LDC "snow"
    INVOKESPECIAL bsu.a (Lakf;Ljava/lang/String;)V
   L273
    LINENUMBER 974 L273
    ALOAD 0
    GETSTATIC akg.aH : Lakf;
    LDC "snow_layer"
    INVOKESPECIAL bsu.a (Lakf;Ljava/lang/String;)V
   L274
    LINENUMBER 975 L274
    ALOAD 0
    GETSTATIC akg.aW : Lakf;
    LDC "soul_sand"
    INVOKESPECIAL bsu.a (Lakf;Ljava/lang/String;)V
   L275
    LINENUMBER 976 L275
    ALOAD 0
    GETSTATIC akg.bU : Lakf;
    LDC "spruce_stairs"
    INVOKESPECIAL bsu.a (Lakf;Ljava/lang/String;)V
   L276
    LINENUMBER 977 L276
    ALOAD 0
    GETSTATIC akg.F : Larj;
    LDC "sticky_piston"
    INVOKESPECIAL bsu.a (Lakf;Ljava/lang/String;)V
   L277
    LINENUMBER 978 L277
    ALOAD 0
    GETSTATIC akg.bv : Lakf;
    LDC "stone_brick_stairs"
    INVOKESPECIAL bsu.a (Lakf;Ljava/lang/String;)V
   L278
    LINENUMBER 979 L278
    ALOAD 0
    GETSTATIC akg.aG : Lakf;
    LDC "stone_button"
    INVOKESPECIAL bsu.a (Lakf;Ljava/lang/String;)V
   L279
    LINENUMBER 980 L279
    ALOAD 0
    GETSTATIC akg.az : Lakf;
    LDC "stone_pressure_plate"
    INVOKESPECIAL bsu.a (Lakf;Ljava/lang/String;)V
   L280
    LINENUMBER 981 L280
    ALOAD 0
    GETSTATIC akg.aw : Lakf;
    LDC "stone_stairs"
    INVOKESPECIAL bsu.a (Lakf;Ljava/lang/String;)V
   L281
    LINENUMBER 982 L281
    ALOAD 0
    GETSTATIC akg.W : Lakf;
    LDC "tnt"
    INVOKESPECIAL bsu.a (Lakf;Ljava/lang/String;)V
   L282
    LINENUMBER 983 L282
    ALOAD 0
    GETSTATIC akg.aa : Lakf;
    LDC "torch"
    INVOKESPECIAL bsu.a (Lakf;Ljava/lang/String;)V
   L283
    LINENUMBER 984 L283
    ALOAD 0
    GETSTATIC akg.bd : Lakf;
    LDC "trapdoor"
    INVOKESPECIAL bsu.a (Lakf;Ljava/lang/String;)V
   L284
    LINENUMBER 985 L284
    ALOAD 0
    GETSTATIC akg.bR : Lapx;
    LDC "tripwire_hook"
    INVOKESPECIAL bsu.a (Lakf;Ljava/lang/String;)V
   L285
    LINENUMBER 986 L285
    ALOAD 0
    GETSTATIC akg.bn : Lakf;
    LDC "vine"
    INVOKESPECIAL bsu.a (Lakf;Ljava/lang/String;)V
   L286
    LINENUMBER 987 L286
    ALOAD 0
    GETSTATIC akg.bx : Lakf;
    LDC "waterlily"
    INVOKESPECIAL bsu.a (Lakf;Ljava/lang/String;)V
   L287
    LINENUMBER 988 L287
    ALOAD 0
    GETSTATIC akg.G : Lakf;
    LDC "web"
    INVOKESPECIAL bsu.a (Lakf;Ljava/lang/String;)V
   L288
    LINENUMBER 989 L288
    ALOAD 0
    GETSTATIC akg.cd : Lakf;
    LDC "wooden_button"
    INVOKESPECIAL bsu.a (Lakf;Ljava/lang/String;)V
   L289
    LINENUMBER 990 L289
    ALOAD 0
    GETSTATIC akg.aB : Lakf;
    LDC "wooden_pressure_plate"
    INVOKESPECIAL bsu.a (Lakf;Ljava/lang/String;)V
   L290
    LINENUMBER 991 L290
    ALOAD 0
    GETSTATIC akg.N : Lalz;
    GETSTATIC alz$a.a : Lalz$a;
    INVOKEVIRTUAL alz$a.b ()I
    LDC "dandelion"
    INVOKEVIRTUAL bsu.a (Lakf;ILjava/lang/String;)V
   L291
    LINENUMBER 992 L291
    ALOAD 0
    GETSTATIC akg.cQ : Lakf;
    LDC "end_rod"
    INVOKESPECIAL bsu.a (Lakf;Ljava/lang/String;)V
   L292
    LINENUMBER 993 L292
    ALOAD 0
    GETSTATIC akg.cR : Lakf;
    LDC "chorus_plant"
    INVOKESPECIAL bsu.a (Lakf;Ljava/lang/String;)V
   L293
    LINENUMBER 994 L293
    ALOAD 0
    GETSTATIC akg.cS : Lakf;
    LDC "chorus_flower"
    INVOKESPECIAL bsu.a (Lakf;Ljava/lang/String;)V
   L294
    LINENUMBER 995 L294
    ALOAD 0
    GETSTATIC akg.cT : Lakf;
    LDC "purpur_block"
    INVOKESPECIAL bsu.a (Lakf;Ljava/lang/String;)V
   L295
    LINENUMBER 996 L295
    ALOAD 0
    GETSTATIC akg.cU : Lakf;
    LDC "purpur_pillar"
    INVOKESPECIAL bsu.a (Lakf;Ljava/lang/String;)V
   L296
    LINENUMBER 997 L296
    ALOAD 0
    GETSTATIC akg.cV : Lakf;
    LDC "purpur_stairs"
    INVOKESPECIAL bsu.a (Lakf;Ljava/lang/String;)V
   L297
    LINENUMBER 998 L297
    ALOAD 0
    GETSTATIC akg.cX : Lamm;
    LDC "purpur_slab"
    INVOKESPECIAL bsu.a (Lakf;Ljava/lang/String;)V
   L298
    LINENUMBER 999 L298
    ALOAD 0
    GETSTATIC akg.cW : Lamm;
    LDC "purpur_double_slab"
    INVOKESPECIAL bsu.a (Lakf;Ljava/lang/String;)V
   L299
    LINENUMBER 1000 L299
    ALOAD 0
    GETSTATIC akg.cY : Lakf;
    LDC "end_bricks"
    INVOKESPECIAL bsu.a (Lakf;Ljava/lang/String;)V
   L300
    LINENUMBER 1001 L300
    ALOAD 0
    GETSTATIC akg.df : Lakf;
    LDC "magma"
    INVOKESPECIAL bsu.a (Lakf;Ljava/lang/String;)V
   L301
    LINENUMBER 1002 L301
    ALOAD 0
    GETSTATIC akg.dg : Lakf;
    LDC "nether_wart_block"
    INVOKESPECIAL bsu.a (Lakf;Ljava/lang/String;)V
   L302
    LINENUMBER 1003 L302
    ALOAD 0
    GETSTATIC akg.dh : Lakf;
    LDC "red_nether_brick"
    INVOKESPECIAL bsu.a (Lakf;Ljava/lang/String;)V
   L303
    LINENUMBER 1004 L303
    ALOAD 0
    GETSTATIC akg.di : Lakf;
    LDC "bone_block"
    INVOKESPECIAL bsu.a (Lakf;Ljava/lang/String;)V
   L304
    LINENUMBER 1005 L304
    ALOAD 0
    GETSTATIC akg.dj : Lakf;
    LDC "structure_void"
    INVOKESPECIAL bsu.a (Lakf;Ljava/lang/String;)V
   L305
    LINENUMBER 1006 L305
    ALOAD 0
    GETSTATIC akg.ae : Lakr;
    LDC "chest"
    INVOKESPECIAL bsu.a (Lakf;Ljava/lang/String;)V
   L306
    LINENUMBER 1007 L306
    ALOAD 0
    GETSTATIC akg.cg : Lakf;
    LDC "trapped_chest"
    INVOKESPECIAL bsu.a (Lakf;Ljava/lang/String;)V
   L307
    LINENUMBER 1008 L307
    ALOAD 0
    GETSTATIC akg.bQ : Lakf;
    LDC "ender_chest"
    INVOKESPECIAL bsu.a (Lakf;Ljava/lang/String;)V
   L308
    LINENUMBER 1009 L308
    ALOAD 0
    GETSTATIC aeb.a : Ladx;
    LDC "iron_shovel"
    INVOKESPECIAL bsu.a (Ladx;Ljava/lang/String;)V
   L309
    LINENUMBER 1010 L309
    ALOAD 0
    GETSTATIC aeb.b : Ladx;
    LDC "iron_pickaxe"
    INVOKESPECIAL bsu.a (Ladx;Ljava/lang/String;)V
   L310
    LINENUMBER 1011 L310
    ALOAD 0
    GETSTATIC aeb.c : Ladx;
    LDC "iron_axe"
    INVOKESPECIAL bsu.a (Ladx;Ljava/lang/String;)V
   L311
    LINENUMBER 1012 L311
    ALOAD 0
    GETSTATIC aeb.d : Ladx;
    LDC "flint_and_steel"
    INVOKESPECIAL bsu.a (Ladx;Ljava/lang/String;)V
   L312
    LINENUMBER 1013 L312
    ALOAD 0
    GETSTATIC aeb.e : Ladx;
    LDC "apple"
    INVOKESPECIAL bsu.a (Ladx;Ljava/lang/String;)V
   L313
    LINENUMBER 1014 L313
    ALOAD 0
    GETSTATIC aeb.f : Lacq;
    LDC "bow"
    INVOKESPECIAL bsu.a (Ladx;Ljava/lang/String;)V
   L314
    LINENUMBER 1015 L314
    ALOAD 0
    GETSTATIC aeb.g : Ladx;
    LDC "arrow"
    INVOKESPECIAL bsu.a (Ladx;Ljava/lang/String;)V
   L315
    LINENUMBER 1016 L315
    ALOAD 0
    GETSTATIC aeb.h : Ladx;
    LDC "spectral_arrow"
    INVOKESPECIAL bsu.a (Ladx;Ljava/lang/String;)V
   L316
    LINENUMBER 1017 L316
    ALOAD 0
    GETSTATIC aeb.i : Ladx;
    LDC "tipped_arrow"
    INVOKESPECIAL bsu.a (Ladx;Ljava/lang/String;)V
   L317
    LINENUMBER 1018 L317
    ALOAD 0
    GETSTATIC aeb.j : Ladx;
    ICONST_0
    LDC "coal"
    INVOKEVIRTUAL bsu.a (Ladx;ILjava/lang/String;)V
   L318
    LINENUMBER 1019 L318
    ALOAD 0
    GETSTATIC aeb.j : Ladx;
    ICONST_1
    LDC "charcoal"
    INVOKEVIRTUAL bsu.a (Ladx;ILjava/lang/String;)V
   L319
    LINENUMBER 1020 L319
    ALOAD 0
    GETSTATIC aeb.k : Ladx;
    LDC "diamond"
    INVOKESPECIAL bsu.a (Ladx;Ljava/lang/String;)V
   L320
    LINENUMBER 1021 L320
    ALOAD 0
    GETSTATIC aeb.l : Ladx;
    LDC "iron_ingot"
    INVOKESPECIAL bsu.a (Ladx;Ljava/lang/String;)V
   L321
    LINENUMBER 1022 L321
    ALOAD 0
    GETSTATIC aeb.m : Ladx;
    LDC "gold_ingot"
    INVOKESPECIAL bsu.a (Ladx;Ljava/lang/String;)V
   L322
    LINENUMBER 1023 L322
    ALOAD 0
    GETSTATIC aeb.n : Ladx;
    LDC "iron_sword"
    INVOKESPECIAL bsu.a (Ladx;Ljava/lang/String;)V
   L323
    LINENUMBER 1024 L323
    ALOAD 0
    GETSTATIC aeb.o : Ladx;
    LDC "wooden_sword"
    INVOKESPECIAL bsu.a (Ladx;Ljava/lang/String;)V
   L324
    LINENUMBER 1025 L324
    ALOAD 0
    GETSTATIC aeb.p : Ladx;
    LDC "wooden_shovel"
    INVOKESPECIAL bsu.a (Ladx;Ljava/lang/String;)V
   L325
    LINENUMBER 1026 L325
    ALOAD 0
    GETSTATIC aeb.q : Ladx;
    LDC "wooden_pickaxe"
    INVOKESPECIAL bsu.a (Ladx;Ljava/lang/String;)V
   L326
    LINENUMBER 1027 L326
    ALOAD 0
    GETSTATIC aeb.r : Ladx;
    LDC "wooden_axe"
    INVOKESPECIAL bsu.a (Ladx;Ljava/lang/String;)V
   L327
    LINENUMBER 1028 L327
    ALOAD 0
    GETSTATIC aeb.s : Ladx;
    LDC "stone_sword"
    INVOKESPECIAL bsu.a (Ladx;Ljava/lang/String;)V
   L328
    LINENUMBER 1029 L328
    ALOAD 0
    GETSTATIC aeb.t : Ladx;
    LDC "stone_shovel"
    INVOKESPECIAL bsu.a (Ladx;Ljava/lang/String;)V
   L329
    LINENUMBER 1030 L329
    ALOAD 0
    GETSTATIC aeb.u : Ladx;
    LDC "stone_pickaxe"
    INVOKESPECIAL bsu.a (Ladx;Ljava/lang/String;)V
   L330
    LINENUMBER 1031 L330
    ALOAD 0
    GETSTATIC aeb.v : Ladx;
    LDC "stone_axe"
    INVOKESPECIAL bsu.a (Ladx;Ljava/lang/String;)V
   L331
    LINENUMBER 1032 L331
    ALOAD 0
    GETSTATIC aeb.w : Ladx;
    LDC "diamond_sword"
    INVOKESPECIAL bsu.a (Ladx;Ljava/lang/String;)V
   L332
    LINENUMBER 1033 L332
    ALOAD 0
    GETSTATIC aeb.x : Ladx;
    LDC "diamond_shovel"
    INVOKESPECIAL bsu.a (Ladx;Ljava/lang/String;)V
   L333
    LINENUMBER 1034 L333
    ALOAD 0
    GETSTATIC aeb.y : Ladx;
    LDC "diamond_pickaxe"
    INVOKESPECIAL bsu.a (Ladx;Ljava/lang/String;)V
   L334
    LINENUMBER 1035 L334
    ALOAD 0
    GETSTATIC aeb.z : Ladx;
    LDC "diamond_axe"
    INVOKESPECIAL bsu.a (Ladx;Ljava/lang/String;)V
   L335
    LINENUMBER 1036 L335
    ALOAD 0
    GETSTATIC aeb.A : Ladx;
    LDC "stick"
    INVOKESPECIAL bsu.a (Ladx;Ljava/lang/String;)V
   L336
    LINENUMBER 1037 L336
    ALOAD 0
    GETSTATIC aeb.B : Ladx;
    LDC "bowl"
    INVOKESPECIAL bsu.a (Ladx;Ljava/lang/String;)V
   L337
    LINENUMBER 1038 L337
    ALOAD 0
    GETSTATIC aeb.C : Ladx;
    LDC "mushroom_stew"
    INVOKESPECIAL bsu.a (Ladx;Ljava/lang/String;)V
   L338
    LINENUMBER 1039 L338
    ALOAD 0
    GETSTATIC aeb.D : Ladx;
    LDC "golden_sword"
    INVOKESPECIAL bsu.a (Ladx;Ljava/lang/String;)V
   L339
    LINENUMBER 1040 L339
    ALOAD 0
    GETSTATIC aeb.E : Ladx;
    LDC "golden_shovel"
    INVOKESPECIAL bsu.a (Ladx;Ljava/lang/String;)V
   L340
    LINENUMBER 1041 L340
    ALOAD 0
    GETSTATIC aeb.F : Ladx;
    LDC "golden_pickaxe"
    INVOKESPECIAL bsu.a (Ladx;Ljava/lang/String;)V
   L341
    LINENUMBER 1042 L341
    ALOAD 0
    GETSTATIC aeb.G : Ladx;
    LDC "golden_axe"
    INVOKESPECIAL bsu.a (Ladx;Ljava/lang/String;)V
   L342
    LINENUMBER 1043 L342
    ALOAD 0
    GETSTATIC aeb.H : Ladx;
    LDC "string"
    INVOKESPECIAL bsu.a (Ladx;Ljava/lang/String;)V
   L343
    LINENUMBER 1044 L343
    ALOAD 0
    GETSTATIC aeb.I : Ladx;
    LDC "feather"
    INVOKESPECIAL bsu.a (Ladx;Ljava/lang/String;)V
   L344
    LINENUMBER 1045 L344
    ALOAD 0
    GETSTATIC aeb.J : Ladx;
    LDC "gunpowder"
    INVOKESPECIAL bsu.a (Ladx;Ljava/lang/String;)V
   L345
    LINENUMBER 1046 L345
    ALOAD 0
    GETSTATIC aeb.K : Ladx;
    LDC "wooden_hoe"
    INVOKESPECIAL bsu.a (Ladx;Ljava/lang/String;)V
   L346
    LINENUMBER 1047 L346
    ALOAD 0
    GETSTATIC aeb.L : Ladx;
    LDC "stone_hoe"
    INVOKESPECIAL bsu.a (Ladx;Ljava/lang/String;)V
   L347
    LINENUMBER 1048 L347
    ALOAD 0
    GETSTATIC aeb.M : Ladx;
    LDC "iron_hoe"
    INVOKESPECIAL bsu.a (Ladx;Ljava/lang/String;)V
   L348
    LINENUMBER 1049 L348
    ALOAD 0
    GETSTATIC aeb.N : Ladx;
    LDC "diamond_hoe"
    INVOKESPECIAL bsu.a (Ladx;Ljava/lang/String;)V
   L349
    LINENUMBER 1050 L349
    ALOAD 0
    GETSTATIC aeb.O : Ladx;
    LDC "golden_hoe"
    INVOKESPECIAL bsu.a (Ladx;Ljava/lang/String;)V
   L350
    LINENUMBER 1051 L350
    ALOAD 0
    GETSTATIC aeb.P : Ladx;
    LDC "wheat_seeds"
    INVOKESPECIAL bsu.a (Ladx;Ljava/lang/String;)V
   L351
    LINENUMBER 1052 L351
    ALOAD 0
    GETSTATIC aeb.Q : Ladx;
    LDC "wheat"
    INVOKESPECIAL bsu.a (Ladx;Ljava/lang/String;)V
   L352
    LINENUMBER 1053 L352
    ALOAD 0
    GETSTATIC aeb.R : Ladx;
    LDC "bread"
    INVOKESPECIAL bsu.a (Ladx;Ljava/lang/String;)V
   L353
    LINENUMBER 1054 L353
    ALOAD 0
    GETSTATIC aeb.S : Lacf;
    LDC "leather_helmet"
    INVOKESPECIAL bsu.a (Ladx;Ljava/lang/String;)V
   L354
    LINENUMBER 1055 L354
    ALOAD 0
    GETSTATIC aeb.T : Lacf;
    LDC "leather_chestplate"
    INVOKESPECIAL bsu.a (Ladx;Ljava/lang/String;)V
   L355
    LINENUMBER 1056 L355
    ALOAD 0
    GETSTATIC aeb.U : Lacf;
    LDC "leather_leggings"
    INVOKESPECIAL bsu.a (Ladx;Ljava/lang/String;)V
   L356
    LINENUMBER 1057 L356
    ALOAD 0
    GETSTATIC aeb.V : Lacf;
    LDC "leather_boots"
    INVOKESPECIAL bsu.a (Ladx;Ljava/lang/String;)V
   L357
    LINENUMBER 1058 L357
    ALOAD 0
    GETSTATIC aeb.W : Lacf;
    LDC "chainmail_helmet"
    INVOKESPECIAL bsu.a (Ladx;Ljava/lang/String;)V
   L358
    LINENUMBER 1059 L358
    ALOAD 0
    GETSTATIC aeb.X : Lacf;
    LDC "chainmail_chestplate"
    INVOKESPECIAL bsu.a (Ladx;Ljava/lang/String;)V
   L359
    LINENUMBER 1060 L359
    ALOAD 0
    GETSTATIC aeb.Y : Lacf;
    LDC "chainmail_leggings"
    INVOKESPECIAL bsu.a (Ladx;Ljava/lang/String;)V
   L360
    LINENUMBER 1061 L360
    ALOAD 0
    GETSTATIC aeb.Z : Lacf;
    LDC "chainmail_boots"
    INVOKESPECIAL bsu.a (Ladx;Ljava/lang/String;)V
   L361
    LINENUMBER 1062 L361
    ALOAD 0
    GETSTATIC aeb.aa : Lacf;
    LDC "iron_helmet"
    INVOKESPECIAL bsu.a (Ladx;Ljava/lang/String;)V
   L362
    LINENUMBER 1063 L362
    ALOAD 0
    GETSTATIC aeb.ab : Lacf;
    LDC "iron_chestplate"
    INVOKESPECIAL bsu.a (Ladx;Ljava/lang/String;)V
   L363
    LINENUMBER 1064 L363
    ALOAD 0
    GETSTATIC aeb.ac : Lacf;
    LDC "iron_leggings"
    INVOKESPECIAL bsu.a (Ladx;Ljava/lang/String;)V
   L364
    LINENUMBER 1065 L364
    ALOAD 0
    GETSTATIC aeb.ad : Lacf;
    LDC "iron_boots"
    INVOKESPECIAL bsu.a (Ladx;Ljava/lang/String;)V
   L365
    LINENUMBER 1066 L365
    ALOAD 0
    GETSTATIC aeb.ae : Lacf;
    LDC "diamond_helmet"
    INVOKESPECIAL bsu.a (Ladx;Ljava/lang/String;)V
   L366
    LINENUMBER 1067 L366
    ALOAD 0
    GETSTATIC aeb.af : Lacf;
    LDC "diamond_chestplate"
    INVOKESPECIAL bsu.a (Ladx;Ljava/lang/String;)V
   L367
    LINENUMBER 1068 L367
    ALOAD 0
    GETSTATIC aeb.ag : Lacf;
    LDC "diamond_leggings"
    INVOKESPECIAL bsu.a (Ladx;Ljava/lang/String;)V
   L368
    LINENUMBER 1069 L368
    ALOAD 0
    GETSTATIC aeb.ah : Lacf;
    LDC "diamond_boots"
    INVOKESPECIAL bsu.a (Ladx;Ljava/lang/String;)V
   L369
    LINENUMBER 1070 L369
    ALOAD 0
    GETSTATIC aeb.ai : Lacf;
    LDC "golden_helmet"
    INVOKESPECIAL bsu.a (Ladx;Ljava/lang/String;)V
   L370
    LINENUMBER 1071 L370
    ALOAD 0
    GETSTATIC aeb.aj : Lacf;
    LDC "golden_chestplate"
    INVOKESPECIAL bsu.a (Ladx;Ljava/lang/String;)V
   L371
    LINENUMBER 1072 L371
    ALOAD 0
    GETSTATIC aeb.ak : Lacf;
    LDC "golden_leggings"
    INVOKESPECIAL bsu.a (Ladx;Ljava/lang/String;)V
   L372
    LINENUMBER 1073 L372
    ALOAD 0
    GETSTATIC aeb.al : Lacf;
    LDC "golden_boots"
    INVOKESPECIAL bsu.a (Ladx;Ljava/lang/String;)V
   L373
    LINENUMBER 1074 L373
    ALOAD 0
    GETSTATIC aeb.am : Ladx;
    LDC "flint"
    INVOKESPECIAL bsu.a (Ladx;Ljava/lang/String;)V
   L374
    LINENUMBER 1075 L374
    ALOAD 0
    GETSTATIC aeb.an : Ladx;
    LDC "porkchop"
    INVOKESPECIAL bsu.a (Ladx;Ljava/lang/String;)V
   L375
    LINENUMBER 1076 L375
    ALOAD 0
    GETSTATIC aeb.ao : Ladx;
    LDC "cooked_porkchop"
    INVOKESPECIAL bsu.a (Ladx;Ljava/lang/String;)V
   L376
    LINENUMBER 1077 L376
    ALOAD 0
    GETSTATIC aeb.ap : Ladx;
    LDC "painting"
    INVOKESPECIAL bsu.a (Ladx;Ljava/lang/String;)V
   L377
    LINENUMBER 1078 L377
    ALOAD 0
    GETSTATIC aeb.aq : Ladx;
    LDC "golden_apple"
    INVOKESPECIAL bsu.a (Ladx;Ljava/lang/String;)V
   L378
    LINENUMBER 1079 L378
    ALOAD 0
    GETSTATIC aeb.aq : Ladx;
    ICONST_1
    LDC "golden_apple"
    INVOKEVIRTUAL bsu.a (Ladx;ILjava/lang/String;)V
   L379
    LINENUMBER 1080 L379
    ALOAD 0
    GETSTATIC aeb.ar : Ladx;
    LDC "sign"
    INVOKESPECIAL bsu.a (Ladx;Ljava/lang/String;)V
   L380
    LINENUMBER 1081 L380
    ALOAD 0
    GETSTATIC aeb.as : Ladx;
    LDC "oak_door"
    INVOKESPECIAL bsu.a (Ladx;Ljava/lang/String;)V
   L381
    LINENUMBER 1082 L381
    ALOAD 0
    GETSTATIC aeb.at : Ladx;
    LDC "spruce_door"
    INVOKESPECIAL bsu.a (Ladx;Ljava/lang/String;)V
   L382
    LINENUMBER 1083 L382
    ALOAD 0
    GETSTATIC aeb.au : Ladx;
    LDC "birch_door"
    INVOKESPECIAL bsu.a (Ladx;Ljava/lang/String;)V
   L383
    LINENUMBER 1084 L383
    ALOAD 0
    GETSTATIC aeb.av : Ladx;
    LDC "jungle_door"
    INVOKESPECIAL bsu.a (Ladx;Ljava/lang/String;)V
   L384
    LINENUMBER 1085 L384
    ALOAD 0
    GETSTATIC aeb.aw : Ladx;
    LDC "acacia_door"
    INVOKESPECIAL bsu.a (Ladx;Ljava/lang/String;)V
   L385
    LINENUMBER 1086 L385
    ALOAD 0
    GETSTATIC aeb.ax : Ladx;
    LDC "dark_oak_door"
    INVOKESPECIAL bsu.a (Ladx;Ljava/lang/String;)V
   L386
    LINENUMBER 1087 L386
    ALOAD 0
    GETSTATIC aeb.ay : Ladx;
    LDC "bucket"
    INVOKESPECIAL bsu.a (Ladx;Ljava/lang/String;)V
   L387
    LINENUMBER 1088 L387
    ALOAD 0
    GETSTATIC aeb.az : Ladx;
    LDC "water_bucket"
    INVOKESPECIAL bsu.a (Ladx;Ljava/lang/String;)V
   L388
    LINENUMBER 1089 L388
    ALOAD 0
    GETSTATIC aeb.aA : Ladx;
    LDC "lava_bucket"
    INVOKESPECIAL bsu.a (Ladx;Ljava/lang/String;)V
   L389
    LINENUMBER 1090 L389
    ALOAD 0
    GETSTATIC aeb.aB : Ladx;
    LDC "minecart"
    INVOKESPECIAL bsu.a (Ladx;Ljava/lang/String;)V
   L390
    LINENUMBER 1091 L390
    ALOAD 0
    GETSTATIC aeb.aC : Ladx;
    LDC "saddle"
    INVOKESPECIAL bsu.a (Ladx;Ljava/lang/String;)V
   L391
    LINENUMBER 1092 L391
    ALOAD 0
    GETSTATIC aeb.aD : Ladx;
    LDC "iron_door"
    INVOKESPECIAL bsu.a (Ladx;Ljava/lang/String;)V
   L392
    LINENUMBER 1093 L392
    ALOAD 0
    GETSTATIC aeb.aE : Ladx;
    LDC "redstone"
    INVOKESPECIAL bsu.a (Ladx;Ljava/lang/String;)V
   L393
    LINENUMBER 1094 L393
    ALOAD 0
    GETSTATIC aeb.aF : Ladx;
    LDC "snowball"
    INVOKESPECIAL bsu.a (Ladx;Ljava/lang/String;)V
   L394
    LINENUMBER 1095 L394
    ALOAD 0
    GETSTATIC aeb.aG : Ladx;
    LDC "oak_boat"
    INVOKESPECIAL bsu.a (Ladx;Ljava/lang/String;)V
   L395
    LINENUMBER 1096 L395
    ALOAD 0
    GETSTATIC aeb.aH : Ladx;
    LDC "spruce_boat"
    INVOKESPECIAL bsu.a (Ladx;Ljava/lang/String;)V
   L396
    LINENUMBER 1097 L396
    ALOAD 0
    GETSTATIC aeb.aI : Ladx;
    LDC "birch_boat"
    INVOKESPECIAL bsu.a (Ladx;Ljava/lang/String;)V
   L397
    LINENUMBER 1098 L397
    ALOAD 0
    GETSTATIC aeb.aJ : Ladx;
    LDC "jungle_boat"
    INVOKESPECIAL bsu.a (Ladx;Ljava/lang/String;)V
   L398
    LINENUMBER 1099 L398
    ALOAD 0
    GETSTATIC aeb.aK : Ladx;
    LDC "acacia_boat"
    INVOKESPECIAL bsu.a (Ladx;Ljava/lang/String;)V
   L399
    LINENUMBER 1100 L399
    ALOAD 0
    GETSTATIC aeb.aL : Ladx;
    LDC "dark_oak_boat"
    INVOKESPECIAL bsu.a (Ladx;Ljava/lang/String;)V
   L400
    LINENUMBER 1101 L400
    ALOAD 0
    GETSTATIC aeb.aM : Ladx;
    LDC "leather"
    INVOKESPECIAL bsu.a (Ladx;Ljava/lang/String;)V
   L401
    LINENUMBER 1102 L401
    ALOAD 0
    GETSTATIC aeb.aN : Ladx;
    LDC "milk_bucket"
    INVOKESPECIAL bsu.a (Ladx;Ljava/lang/String;)V
   L402
    LINENUMBER 1103 L402
    ALOAD 0
    GETSTATIC aeb.aO : Ladx;
    LDC "brick"
    INVOKESPECIAL bsu.a (Ladx;Ljava/lang/String;)V
   L403
    LINENUMBER 1104 L403
    ALOAD 0
    GETSTATIC aeb.aP : Ladx;
    LDC "clay_ball"
    INVOKESPECIAL bsu.a (Ladx;Ljava/lang/String;)V
   L404
    LINENUMBER 1105 L404
    ALOAD 0
    GETSTATIC aeb.aQ : Ladx;
    LDC "reeds"
    INVOKESPECIAL bsu.a (Ladx;Ljava/lang/String;)V
   L405
    LINENUMBER 1106 L405
    ALOAD 0
    GETSTATIC aeb.aR : Ladx;
    LDC "paper"
    INVOKESPECIAL bsu.a (Ladx;Ljava/lang/String;)V
   L406
    LINENUMBER 1107 L406
    ALOAD 0
    GETSTATIC aeb.aS : Ladx;
    LDC "book"
    INVOKESPECIAL bsu.a (Ladx;Ljava/lang/String;)V
   L407
    LINENUMBER 1108 L407
    ALOAD 0
    GETSTATIC aeb.aT : Ladx;
    LDC "slime_ball"
    INVOKESPECIAL bsu.a (Ladx;Ljava/lang/String;)V
   L408
    LINENUMBER 1109 L408
    ALOAD 0
    GETSTATIC aeb.aU : Ladx;
    LDC "chest_minecart"
    INVOKESPECIAL bsu.a (Ladx;Ljava/lang/String;)V
   L409
    LINENUMBER 1110 L409
    ALOAD 0
    GETSTATIC aeb.aV : Ladx;
    LDC "furnace_minecart"
    INVOKESPECIAL bsu.a (Ladx;Ljava/lang/String;)V
   L410
    LINENUMBER 1111 L410
    ALOAD 0
    GETSTATIC aeb.aW : Ladx;
    LDC "egg"
    INVOKESPECIAL bsu.a (Ladx;Ljava/lang/String;)V
   L411
    LINENUMBER 1112 L411
    ALOAD 0
    GETSTATIC aeb.aX : Ladx;
    LDC "compass"
    INVOKESPECIAL bsu.a (Ladx;Ljava/lang/String;)V
   L412
    LINENUMBER 1113 L412
    ALOAD 0
    GETSTATIC aeb.aY : Ladr;
    LDC "fishing_rod"
    INVOKESPECIAL bsu.a (Ladx;Ljava/lang/String;)V
   L413
    LINENUMBER 1114 L413
    ALOAD 0
    GETSTATIC aeb.aZ : Ladx;
    LDC "clock"
    INVOKESPECIAL bsu.a (Ladx;Ljava/lang/String;)V
   L414
    LINENUMBER 1115 L414
    ALOAD 0
    GETSTATIC aeb.ba : Ladx;
    LDC "glowstone_dust"
    INVOKESPECIAL bsu.a (Ladx;Ljava/lang/String;)V
   L415
    LINENUMBER 1116 L415
    ALOAD 0
    GETSTATIC aeb.bb : Ladx;
    GETSTATIC adq$a.a : Ladq$a;
    INVOKEVIRTUAL adq$a.a ()I
    LDC "cod"
    INVOKEVIRTUAL bsu.a (Ladx;ILjava/lang/String;)V
   L416
    LINENUMBER 1117 L416
    ALOAD 0
    GETSTATIC aeb.bb : Ladx;
    GETSTATIC adq$a.b : Ladq$a;
    INVOKEVIRTUAL adq$a.a ()I
    LDC "salmon"
    INVOKEVIRTUAL bsu.a (Ladx;ILjava/lang/String;)V
   L417
    LINENUMBER 1118 L417
    ALOAD 0
    GETSTATIC aeb.bb : Ladx;
    GETSTATIC adq$a.c : Ladq$a;
    INVOKEVIRTUAL adq$a.a ()I
    LDC "clownfish"
    INVOKEVIRTUAL bsu.a (Ladx;ILjava/lang/String;)V
   L418
    LINENUMBER 1119 L418
    ALOAD 0
    GETSTATIC aeb.bb : Ladx;
    GETSTATIC adq$a.d : Ladq$a;
    INVOKEVIRTUAL adq$a.a ()I
    LDC "pufferfish"
    INVOKEVIRTUAL bsu.a (Ladx;ILjava/lang/String;)V
   L419
    LINENUMBER 1120 L419
    ALOAD 0
    GETSTATIC aeb.bc : Ladx;
    GETSTATIC adq$a.a : Ladq$a;
    INVOKEVIRTUAL adq$a.a ()I
    LDC "cooked_cod"
    INVOKEVIRTUAL bsu.a (Ladx;ILjava/lang/String;)V
   L420
    LINENUMBER 1121 L420
    ALOAD 0
    GETSTATIC aeb.bc : Ladx;
    GETSTATIC adq$a.b : Ladq$a;
    INVOKEVIRTUAL adq$a.a ()I
    LDC "cooked_salmon"
    INVOKEVIRTUAL bsu.a (Ladx;ILjava/lang/String;)V
   L421
    LINENUMBER 1122 L421
    ALOAD 0
    GETSTATIC aeb.bd : Ladx;
    GETSTATIC adc.p : Ladc;
    INVOKEVIRTUAL adc.b ()I
    LDC "dye_black"
    INVOKEVIRTUAL bsu.a (Ladx;ILjava/lang/String;)V
   L422
    LINENUMBER 1123 L422
    ALOAD 0
    GETSTATIC aeb.bd : Ladx;
    GETSTATIC adc.o : Ladc;
    INVOKEVIRTUAL adc.b ()I
    LDC "dye_red"
    INVOKEVIRTUAL bsu.a (Ladx;ILjava/lang/String;)V
   L423
    LINENUMBER 1124 L423
    ALOAD 0
    GETSTATIC aeb.bd : Ladx;
    GETSTATIC adc.n : Ladc;
    INVOKEVIRTUAL adc.b ()I
    LDC "dye_green"
    INVOKEVIRTUAL bsu.a (Ladx;ILjava/lang/String;)V
   L424
    LINENUMBER 1125 L424
    ALOAD 0
    GETSTATIC aeb.bd : Ladx;
    GETSTATIC adc.m : Ladc;
    INVOKEVIRTUAL adc.b ()I
    LDC "dye_brown"
    INVOKEVIRTUAL bsu.a (Ladx;ILjava/lang/String;)V
   L425
    LINENUMBER 1126 L425
    ALOAD 0
    GETSTATIC aeb.bd : Ladx;
    GETSTATIC adc.l : Ladc;
    INVOKEVIRTUAL adc.b ()I
    LDC "dye_blue"
    INVOKEVIRTUAL bsu.a (Ladx;ILjava/lang/String;)V
   L426
    LINENUMBER 1127 L426
    ALOAD 0
    GETSTATIC aeb.bd : Ladx;
    GETSTATIC adc.k : Ladc;
    INVOKEVIRTUAL adc.b ()I
    LDC "dye_purple"
    INVOKEVIRTUAL bsu.a (Ladx;ILjava/lang/String;)V
   L427
    LINENUMBER 1128 L427
    ALOAD 0
    GETSTATIC aeb.bd : Ladx;
    GETSTATIC adc.j : Ladc;
    INVOKEVIRTUAL adc.b ()I
    LDC "dye_cyan"
    INVOKEVIRTUAL bsu.a (Ladx;ILjava/lang/String;)V
   L428
    LINENUMBER 1129 L428
    ALOAD 0
    GETSTATIC aeb.bd : Ladx;
    GETSTATIC adc.i : Ladc;
    INVOKEVIRTUAL adc.b ()I
    LDC "dye_silver"
    INVOKEVIRTUAL bsu.a (Ladx;ILjava/lang/String;)V
   L429
    LINENUMBER 1130 L429
    ALOAD 0
    GETSTATIC aeb.bd : Ladx;
    GETSTATIC adc.h : Ladc;
    INVOKEVIRTUAL adc.b ()I
    LDC "dye_gray"
    INVOKEVIRTUAL bsu.a (Ladx;ILjava/lang/String;)V
   L430
    LINENUMBER 1131 L430
    ALOAD 0
    GETSTATIC aeb.bd : Ladx;
    GETSTATIC adc.g : Ladc;
    INVOKEVIRTUAL adc.b ()I
    LDC "dye_pink"
    INVOKEVIRTUAL bsu.a (Ladx;ILjava/lang/String;)V
   L431
    LINENUMBER 1132 L431
    ALOAD 0
    GETSTATIC aeb.bd : Ladx;
    GETSTATIC adc.f : Ladc;
    INVOKEVIRTUAL adc.b ()I
    LDC "dye_lime"
    INVOKEVIRTUAL bsu.a (Ladx;ILjava/lang/String;)V
   L432
    LINENUMBER 1133 L432
    ALOAD 0
    GETSTATIC aeb.bd : Ladx;
    GETSTATIC adc.e : Ladc;
    INVOKEVIRTUAL adc.b ()I
    LDC "dye_yellow"
    INVOKEVIRTUAL bsu.a (Ladx;ILjava/lang/String;)V
   L433
    LINENUMBER 1134 L433
    ALOAD 0
    GETSTATIC aeb.bd : Ladx;
    GETSTATIC adc.d : Ladc;
    INVOKEVIRTUAL adc.b ()I
    LDC "dye_light_blue"
    INVOKEVIRTUAL bsu.a (Ladx;ILjava/lang/String;)V
   L434
    LINENUMBER 1135 L434
    ALOAD 0
    GETSTATIC aeb.bd : Ladx;
    GETSTATIC adc.c : Ladc;
    INVOKEVIRTUAL adc.b ()I
    LDC "dye_magenta"
    INVOKEVIRTUAL bsu.a (Ladx;ILjava/lang/String;)V
   L435
    LINENUMBER 1136 L435
    ALOAD 0
    GETSTATIC aeb.bd : Ladx;
    GETSTATIC adc.b : Ladc;
    INVOKEVIRTUAL adc.b ()I
    LDC "dye_orange"
    INVOKEVIRTUAL bsu.a (Ladx;ILjava/lang/String;)V
   L436
    LINENUMBER 1137 L436
    ALOAD 0
    GETSTATIC aeb.bd : Ladx;
    GETSTATIC adc.a : Ladc;
    INVOKEVIRTUAL adc.b ()I
    LDC "dye_white"
    INVOKEVIRTUAL bsu.a (Ladx;ILjava/lang/String;)V
   L437
    LINENUMBER 1138 L437
    ALOAD 0
    GETSTATIC aeb.be : Ladx;
    LDC "bone"
    INVOKESPECIAL bsu.a (Ladx;Ljava/lang/String;)V
   L438
    LINENUMBER 1139 L438
    ALOAD 0
    GETSTATIC aeb.bf : Ladx;
    LDC "sugar"
    INVOKESPECIAL bsu.a (Ladx;Ljava/lang/String;)V
   L439
    LINENUMBER 1140 L439
    ALOAD 0
    GETSTATIC aeb.bg : Ladx;
    LDC "cake"
    INVOKESPECIAL bsu.a (Ladx;Ljava/lang/String;)V
   L440
    LINENUMBER 1141 L440
    ALOAD 0
    GETSTATIC aeb.bh : Ladx;
    LDC "bed"
    INVOKESPECIAL bsu.a (Ladx;Ljava/lang/String;)V
   L441
    LINENUMBER 1142 L441
    ALOAD 0
    GETSTATIC aeb.bi : Ladx;
    LDC "repeater"
    INVOKESPECIAL bsu.a (Ladx;Ljava/lang/String;)V
   L442
    LINENUMBER 1143 L442
    ALOAD 0
    GETSTATIC aeb.bj : Ladx;
    LDC "cookie"
    INVOKESPECIAL bsu.a (Ladx;Ljava/lang/String;)V
   L443
    LINENUMBER 1144 L443
    ALOAD 0
    GETSTATIC aeb.bl : Laeu;
    LDC "shears"
    INVOKESPECIAL bsu.a (Ladx;Ljava/lang/String;)V
   L444
    LINENUMBER 1145 L444
    ALOAD 0
    GETSTATIC aeb.bm : Ladx;
    LDC "melon"
    INVOKESPECIAL bsu.a (Ladx;Ljava/lang/String;)V
   L445
    LINENUMBER 1146 L445
    ALOAD 0
    GETSTATIC aeb.bn : Ladx;
    LDC "pumpkin_seeds"
    INVOKESPECIAL bsu.a (Ladx;Ljava/lang/String;)V
   L446
    LINENUMBER 1147 L446
    ALOAD 0
    GETSTATIC aeb.bo : Ladx;
    LDC "melon_seeds"
    INVOKESPECIAL bsu.a (Ladx;Ljava/lang/String;)V
   L447
    LINENUMBER 1148 L447
    ALOAD 0
    GETSTATIC aeb.bp : Ladx;
    LDC "beef"
    INVOKESPECIAL bsu.a (Ladx;Ljava/lang/String;)V
   L448
    LINENUMBER 1149 L448
    ALOAD 0
    GETSTATIC aeb.bq : Ladx;
    LDC "cooked_beef"
    INVOKESPECIAL bsu.a (Ladx;Ljava/lang/String;)V
   L449
    LINENUMBER 1150 L449
    ALOAD 0
    GETSTATIC aeb.br : Ladx;
    LDC "chicken"
    INVOKESPECIAL bsu.a (Ladx;Ljava/lang/String;)V
   L450
    LINENUMBER 1151 L450
    ALOAD 0
    GETSTATIC aeb.bs : Ladx;
    LDC "cooked_chicken"
    INVOKESPECIAL bsu.a (Ladx;Ljava/lang/String;)V
   L451
    LINENUMBER 1152 L451
    ALOAD 0
    GETSTATIC aeb.bv : Ladx;
    LDC "rabbit"
    INVOKESPECIAL bsu.a (Ladx;Ljava/lang/String;)V
   L452
    LINENUMBER 1153 L452
    ALOAD 0
    GETSTATIC aeb.bw : Ladx;
    LDC "cooked_rabbit"
    INVOKESPECIAL bsu.a (Ladx;Ljava/lang/String;)V
   L453
    LINENUMBER 1154 L453
    ALOAD 0
    GETSTATIC aeb.bt : Ladx;
    LDC "mutton"
    INVOKESPECIAL bsu.a (Ladx;Ljava/lang/String;)V
   L454
    LINENUMBER 1155 L454
    ALOAD 0
    GETSTATIC aeb.bu : Ladx;
    LDC "cooked_mutton"
    INVOKESPECIAL bsu.a (Ladx;Ljava/lang/String;)V
   L455
    LINENUMBER 1156 L455
    ALOAD 0
    GETSTATIC aeb.by : Ladx;
    LDC "rabbit_foot"
    INVOKESPECIAL bsu.a (Ladx;Ljava/lang/String;)V
   L456
    LINENUMBER 1157 L456
    ALOAD 0
    GETSTATIC aeb.bz : Ladx;
    LDC "rabbit_hide"
    INVOKESPECIAL bsu.a (Ladx;Ljava/lang/String;)V
   L457
    LINENUMBER 1158 L457
    ALOAD 0
    GETSTATIC aeb.bx : Ladx;
    LDC "rabbit_stew"
    INVOKESPECIAL bsu.a (Ladx;Ljava/lang/String;)V
   L458
    LINENUMBER 1159 L458
    ALOAD 0
    GETSTATIC aeb.bA : Ladx;
    LDC "rotten_flesh"
    INVOKESPECIAL bsu.a (Ladx;Ljava/lang/String;)V
   L459
    LINENUMBER 1160 L459
    ALOAD 0
    GETSTATIC aeb.bB : Ladx;
    LDC "ender_pearl"
    INVOKESPECIAL bsu.a (Ladx;Ljava/lang/String;)V
   L460
    LINENUMBER 1161 L460
    ALOAD 0
    GETSTATIC aeb.bC : Ladx;
    LDC "blaze_rod"
    INVOKESPECIAL bsu.a (Ladx;Ljava/lang/String;)V
   L461
    LINENUMBER 1162 L461
    ALOAD 0
    GETSTATIC aeb.bD : Ladx;
    LDC "ghast_tear"
    INVOKESPECIAL bsu.a (Ladx;Ljava/lang/String;)V
   L462
    LINENUMBER 1163 L462
    ALOAD 0
    GETSTATIC aeb.bE : Ladx;
    LDC "gold_nugget"
    INVOKESPECIAL bsu.a (Ladx;Ljava/lang/String;)V
   L463
    LINENUMBER 1164 L463
    ALOAD 0
    GETSTATIC aeb.bF : Ladx;
    LDC "nether_wart"
    INVOKESPECIAL bsu.a (Ladx;Ljava/lang/String;)V
   L464
    LINENUMBER 1165 L464
    ALOAD 0
    GETSTATIC aeb.cV : Ladx;
    LDC "beetroot"
    INVOKESPECIAL bsu.a (Ladx;Ljava/lang/String;)V
   L465
    LINENUMBER 1166 L465
    ALOAD 0
    GETSTATIC aeb.cU : Ladx;
    LDC "beetroot_seeds"
    INVOKESPECIAL bsu.a (Ladx;Ljava/lang/String;)V
   L466
    LINENUMBER 1167 L466
    ALOAD 0
    GETSTATIC aeb.cW : Ladx;
    LDC "beetroot_soup"
    INVOKESPECIAL bsu.a (Ladx;Ljava/lang/String;)V
   L467
    LINENUMBER 1168 L467
    ALOAD 0
    GETSTATIC aeb.bG : Laem;
    LDC "bottle_drinkable"
    INVOKESPECIAL bsu.a (Ladx;Ljava/lang/String;)V
   L468
    LINENUMBER 1169 L468
    ALOAD 0
    GETSTATIC aeb.bH : Laem;
    LDC "bottle_splash"
    INVOKESPECIAL bsu.a (Ladx;Ljava/lang/String;)V
   L469
    LINENUMBER 1170 L469
    ALOAD 0
    GETSTATIC aeb.bI : Laem;
    LDC "bottle_lingering"
    INVOKESPECIAL bsu.a (Ladx;Ljava/lang/String;)V
   L470
    LINENUMBER 1171 L470
    ALOAD 0
    GETSTATIC aeb.bJ : Ladx;
    LDC "glass_bottle"
    INVOKESPECIAL bsu.a (Ladx;Ljava/lang/String;)V
   L471
    LINENUMBER 1172 L471
    ALOAD 0
    GETSTATIC aeb.bK : Ladx;
    LDC "dragon_breath"
    INVOKESPECIAL bsu.a (Ladx;Ljava/lang/String;)V
   L472
    LINENUMBER 1173 L472
    ALOAD 0
    GETSTATIC aeb.bL : Ladx;
    LDC "spider_eye"
    INVOKESPECIAL bsu.a (Ladx;Ljava/lang/String;)V
   L473
    LINENUMBER 1174 L473
    ALOAD 0
    GETSTATIC aeb.bM : Ladx;
    LDC "fermented_spider_eye"
    INVOKESPECIAL bsu.a (Ladx;Ljava/lang/String;)V
   L474
    LINENUMBER 1175 L474
    ALOAD 0
    GETSTATIC aeb.bN : Ladx;
    LDC "blaze_powder"
    INVOKESPECIAL bsu.a (Ladx;Ljava/lang/String;)V
   L475
    LINENUMBER 1176 L475
    ALOAD 0
    GETSTATIC aeb.bO : Ladx;
    LDC "magma_cream"
    INVOKESPECIAL bsu.a (Ladx;Ljava/lang/String;)V
   L476
    LINENUMBER 1177 L476
    ALOAD 0
    GETSTATIC aeb.bP : Ladx;
    LDC "brewing_stand"
    INVOKESPECIAL bsu.a (Ladx;Ljava/lang/String;)V
   L477
    LINENUMBER 1178 L477
    ALOAD 0
    GETSTATIC aeb.bQ : Ladx;
    LDC "cauldron"
    INVOKESPECIAL bsu.a (Ladx;Ljava/lang/String;)V
   L478
    LINENUMBER 1179 L478
    ALOAD 0
    GETSTATIC aeb.bR : Ladx;
    LDC "ender_eye"
    INVOKESPECIAL bsu.a (Ladx;Ljava/lang/String;)V
   L479
    LINENUMBER 1180 L479
    ALOAD 0
    GETSTATIC aeb.bS : Ladx;
    LDC "speckled_melon"
    INVOKESPECIAL bsu.a (Ladx;Ljava/lang/String;)V
   L480
    LINENUMBER 1181 L480
    ALOAD 0
    GETFIELD bsu.d : Lboe;
    GETSTATIC aeb.bT : Ladx;
    NEW bsu$5
    DUP
    ALOAD 0
    INVOKESPECIAL bsu$5.<init> (Lbsu;)V
    INVOKEVIRTUAL boe.a (Ladx;Lbof;)V
   L481
    LINENUMBER 1188 L481
    ALOAD 0
    GETSTATIC aeb.bU : Ladx;
    LDC "experience_bottle"
    INVOKESPECIAL bsu.a (Ladx;Ljava/lang/String;)V
   L482
    LINENUMBER 1189 L482
    ALOAD 0
    GETSTATIC aeb.bV : Ladx;
    LDC "fire_charge"
    INVOKESPECIAL bsu.a (Ladx;Ljava/lang/String;)V
   L483
    LINENUMBER 1190 L483
    ALOAD 0
    GETSTATIC aeb.bW : Ladx;
    LDC "writable_book"
    INVOKESPECIAL bsu.a (Ladx;Ljava/lang/String;)V
   L484
    LINENUMBER 1191 L484
    ALOAD 0
    GETSTATIC aeb.bY : Ladx;
    LDC "emerald"
    INVOKESPECIAL bsu.a (Ladx;Ljava/lang/String;)V
   L485
    LINENUMBER 1192 L485
    ALOAD 0
    GETSTATIC aeb.bZ : Ladx;
    LDC "item_frame"
    INVOKESPECIAL bsu.a (Ladx;Ljava/lang/String;)V
   L486
    LINENUMBER 1193 L486
    ALOAD 0
    GETSTATIC aeb.ca : Ladx;
    LDC "flower_pot"
    INVOKESPECIAL bsu.a (Ladx;Ljava/lang/String;)V
   L487
    LINENUMBER 1194 L487
    ALOAD 0
    GETSTATIC aeb.cb : Ladx;
    LDC "carrot"
    INVOKESPECIAL bsu.a (Ladx;Ljava/lang/String;)V
   L488
    LINENUMBER 1195 L488
    ALOAD 0
    GETSTATIC aeb.cc : Ladx;
    LDC "potato"
    INVOKESPECIAL bsu.a (Ladx;Ljava/lang/String;)V
   L489
    LINENUMBER 1196 L489
    ALOAD 0
    GETSTATIC aeb.cd : Ladx;
    LDC "baked_potato"
    INVOKESPECIAL bsu.a (Ladx;Ljava/lang/String;)V
   L490
    LINENUMBER 1197 L490
    ALOAD 0
    GETSTATIC aeb.ce : Ladx;
    LDC "poisonous_potato"
    INVOKESPECIAL bsu.a (Ladx;Ljava/lang/String;)V
   L491
    LINENUMBER 1198 L491
    ALOAD 0
    GETSTATIC aeb.cf : Ladh;
    LDC "map"
    INVOKESPECIAL bsu.a (Ladx;Ljava/lang/String;)V
   L492
    LINENUMBER 1199 L492
    ALOAD 0
    GETSTATIC aeb.cg : Ladx;
    LDC "golden_carrot"
    INVOKESPECIAL bsu.a (Ladx;Ljava/lang/String;)V
   L493
    LINENUMBER 1200 L493
    ALOAD 0
    GETSTATIC aeb.ch : Ladx;
    ICONST_0
    LDC "skull_skeleton"
    INVOKEVIRTUAL bsu.a (Ladx;ILjava/lang/String;)V
   L494
    LINENUMBER 1201 L494
    ALOAD 0
    GETSTATIC aeb.ch : Ladx;
    ICONST_1
    LDC "skull_wither"
    INVOKEVIRTUAL bsu.a (Ladx;ILjava/lang/String;)V
   L495
    LINENUMBER 1202 L495
    ALOAD 0
    GETSTATIC aeb.ch : Ladx;
    ICONST_2
    LDC "skull_zombie"
    INVOKEVIRTUAL bsu.a (Ladx;ILjava/lang/String;)V
   L496
    LINENUMBER 1203 L496
    ALOAD 0
    GETSTATIC aeb.ch : Ladx;
    ICONST_3
    LDC "skull_char"
    INVOKEVIRTUAL bsu.a (Ladx;ILjava/lang/String;)V
   L497
    LINENUMBER 1204 L497
    ALOAD 0
    GETSTATIC aeb.ch : Ladx;
    ICONST_4
    LDC "skull_creeper"
    INVOKEVIRTUAL bsu.a (Ladx;ILjava/lang/String;)V
   L498
    LINENUMBER 1205 L498
    ALOAD 0
    GETSTATIC aeb.ch : Ladx;
    ICONST_5
    LDC "skull_dragon"
    INVOKEVIRTUAL bsu.a (Ladx;ILjava/lang/String;)V
   L499
    LINENUMBER 1206 L499
    ALOAD 0
    GETSTATIC aeb.ci : Ladx;
    LDC "carrot_on_a_stick"
    INVOKESPECIAL bsu.a (Ladx;Ljava/lang/String;)V
   L500
    LINENUMBER 1207 L500
    ALOAD 0
    GETSTATIC aeb.cj : Ladx;
    LDC "nether_star"
    INVOKESPECIAL bsu.a (Ladx;Ljava/lang/String;)V
   L501
    LINENUMBER 1208 L501
    ALOAD 0
    GETSTATIC aeb.cP : Ladx;
    LDC "end_crystal"
    INVOKESPECIAL bsu.a (Ladx;Ljava/lang/String;)V
   L502
    LINENUMBER 1209 L502
    ALOAD 0
    GETSTATIC aeb.ck : Ladx;
    LDC "pumpkin_pie"
    INVOKESPECIAL bsu.a (Ladx;Ljava/lang/String;)V
   L503
    LINENUMBER 1210 L503
    ALOAD 0
    GETSTATIC aeb.cm : Ladx;
    LDC "firework_charge"
    INVOKESPECIAL bsu.a (Ladx;Ljava/lang/String;)V
   L504
    LINENUMBER 1211 L504
    ALOAD 0
    GETSTATIC aeb.co : Ladx;
    LDC "comparator"
    INVOKESPECIAL bsu.a (Ladx;Ljava/lang/String;)V
   L505
    LINENUMBER 1212 L505
    ALOAD 0
    GETSTATIC aeb.cp : Ladx;
    LDC "netherbrick"
    INVOKESPECIAL bsu.a (Ladx;Ljava/lang/String;)V
   L506
    LINENUMBER 1213 L506
    ALOAD 0
    GETSTATIC aeb.cq : Ladx;
    LDC "quartz"
    INVOKESPECIAL bsu.a (Ladx;Ljava/lang/String;)V
   L507
    LINENUMBER 1214 L507
    ALOAD 0
    GETSTATIC aeb.cr : Ladx;
    LDC "tnt_minecart"
    INVOKESPECIAL bsu.a (Ladx;Ljava/lang/String;)V
   L508
    LINENUMBER 1215 L508
    ALOAD 0
    GETSTATIC aeb.cs : Ladx;
    LDC "hopper_minecart"
    INVOKESPECIAL bsu.a (Ladx;Ljava/lang/String;)V
   L509
    LINENUMBER 1216 L509
    ALOAD 0
    GETSTATIC aeb.ct : Lacg;
    LDC "armor_stand"
    INVOKESPECIAL bsu.a (Ladx;Ljava/lang/String;)V
   L510
    LINENUMBER 1217 L510
    ALOAD 0
    GETSTATIC aeb.cu : Ladx;
    LDC "iron_horse_armor"
    INVOKESPECIAL bsu.a (Ladx;Ljava/lang/String;)V
   L511
    LINENUMBER 1218 L511
    ALOAD 0
    GETSTATIC aeb.cv : Ladx;
    LDC "golden_horse_armor"
    INVOKESPECIAL bsu.a (Ladx;Ljava/lang/String;)V
   L512
    LINENUMBER 1219 L512
    ALOAD 0
    GETSTATIC aeb.cw : Ladx;
    LDC "diamond_horse_armor"
    INVOKESPECIAL bsu.a (Ladx;Ljava/lang/String;)V
   L513
    LINENUMBER 1220 L513
    ALOAD 0
    GETSTATIC aeb.cx : Ladx;
    LDC "lead"
    INVOKESPECIAL bsu.a (Ladx;Ljava/lang/String;)V
   L514
    LINENUMBER 1221 L514
    ALOAD 0
    GETSTATIC aeb.cy : Ladx;
    LDC "name_tag"
    INVOKESPECIAL bsu.a (Ladx;Ljava/lang/String;)V
   L515
    LINENUMBER 1222 L515
    ALOAD 0
    GETFIELD bsu.d : Lboe;
    GETSTATIC aeb.cO : Ladx;
    NEW bsu$6
    DUP
    ALOAD 0
    INVOKESPECIAL bsu$6.<init> (Lbsu;)V
    INVOKEVIRTUAL boe.a (Ladx;Lbof;)V
   L516
    LINENUMBER 1229 L516
    ALOAD 0
    GETFIELD bsu.d : Lboe;
    GETSTATIC aeb.cQ : Ladx;
    NEW bsu$7
    DUP
    ALOAD 0
    INVOKESPECIAL bsu$7.<init> (Lbsu;)V
    INVOKEVIRTUAL boe.a (Ladx;Lbof;)V
   L517
    LINENUMBER 1236 L517
    ALOAD 0
    GETSTATIC aeb.cR : Ladx;
    LDC "elytra"
    INVOKESPECIAL bsu.a (Ladx;Ljava/lang/String;)V
   L518
    LINENUMBER 1237 L518
    ALOAD 0
    GETSTATIC aeb.cS : Ladx;
    LDC "chorus_fruit"
    INVOKESPECIAL bsu.a (Ladx;Ljava/lang/String;)V
   L519
    LINENUMBER 1238 L519
    ALOAD 0
    GETSTATIC aeb.cT : Ladx;
    LDC "chorus_fruit_popped"
    INVOKESPECIAL bsu.a (Ladx;Ljava/lang/String;)V
   L520
    LINENUMBER 1239 L520
    ALOAD 0
    GETSTATIC aeb.cA : Ladx;
    LDC "record_13"
    INVOKESPECIAL bsu.a (Ladx;Ljava/lang/String;)V
   L521
    LINENUMBER 1240 L521
    ALOAD 0
    GETSTATIC aeb.cB : Ladx;
    LDC "record_cat"
    INVOKESPECIAL bsu.a (Ladx;Ljava/lang/String;)V
   L522
    LINENUMBER 1241 L522
    ALOAD 0
    GETSTATIC aeb.cC : Ladx;
    LDC "record_blocks"
    INVOKESPECIAL bsu.a (Ladx;Ljava/lang/String;)V
   L523
    LINENUMBER 1242 L523
    ALOAD 0
    GETSTATIC aeb.cD : Ladx;
    LDC "record_chirp"
    INVOKESPECIAL bsu.a (Ladx;Ljava/lang/String;)V
   L524
    LINENUMBER 1243 L524
    ALOAD 0
    GETSTATIC aeb.cE : Ladx;
    LDC "record_far"
    INVOKESPECIAL bsu.a (Ladx;Ljava/lang/String;)V
   L525
    LINENUMBER 1244 L525
    ALOAD 0
    GETSTATIC aeb.cF : Ladx;
    LDC "record_mall"
    INVOKESPECIAL bsu.a (Ladx;Ljava/lang/String;)V
   L526
    LINENUMBER 1245 L526
    ALOAD 0
    GETSTATIC aeb.cG : Ladx;
    LDC "record_mellohi"
    INVOKESPECIAL bsu.a (Ladx;Ljava/lang/String;)V
   L527
    LINENUMBER 1246 L527
    ALOAD 0
    GETSTATIC aeb.cH : Ladx;
    LDC "record_stal"
    INVOKESPECIAL bsu.a (Ladx;Ljava/lang/String;)V
   L528
    LINENUMBER 1247 L528
    ALOAD 0
    GETSTATIC aeb.cI : Ladx;
    LDC "record_strad"
    INVOKESPECIAL bsu.a (Ladx;Ljava/lang/String;)V
   L529
    LINENUMBER 1248 L529
    ALOAD 0
    GETSTATIC aeb.cJ : Ladx;
    LDC "record_ward"
    INVOKESPECIAL bsu.a (Ladx;Ljava/lang/String;)V
   L530
    LINENUMBER 1249 L530
    ALOAD 0
    GETSTATIC aeb.cK : Ladx;
    LDC "record_11"
    INVOKESPECIAL bsu.a (Ladx;Ljava/lang/String;)V
   L531
    LINENUMBER 1250 L531
    ALOAD 0
    GETSTATIC aeb.cL : Ladx;
    LDC "record_wait"
    INVOKESPECIAL bsu.a (Ladx;Ljava/lang/String;)V
   L532
    LINENUMBER 1251 L532
    ALOAD 0
    GETSTATIC aeb.cM : Ladx;
    LDC "prismarine_shard"
    INVOKESPECIAL bsu.a (Ladx;Ljava/lang/String;)V
   L533
    LINENUMBER 1252 L533
    ALOAD 0
    GETSTATIC aeb.cN : Ladx;
    LDC "prismarine_crystals"
    INVOKESPECIAL bsu.a (Ladx;Ljava/lang/String;)V
   L534
    LINENUMBER 1253 L534
    ALOAD 0
    GETFIELD bsu.d : Lboe;
    GETSTATIC aeb.cn : Ladi;
    NEW bsu$8
    DUP
    ALOAD 0
    INVOKESPECIAL bsu$8.<init> (Lbsu;)V
    INVOKEVIRTUAL boe.a (Ladx;Lbof;)V
   L535
    LINENUMBER 1260 L535
    ALOAD 0
    GETFIELD bsu.d : Lboe;
    GETSTATIC aeb.bk : Laef;
    NEW bsu$9
    DUP
    ALOAD 0
    INVOKESPECIAL bsu$9.<init> (Lbsu;)V
    INVOKEVIRTUAL boe.a (Ladx;Lbof;)V
   L536
    LINENUMBER 1267 L536
    ALOAD 0
    GETSTATIC akg.bX : Lakf;
    LDC "command_block"
    INVOKESPECIAL bsu.a (Lakf;Ljava/lang/String;)V
   L537
    LINENUMBER 1268 L537
    ALOAD 0
    GETSTATIC aeb.cl : Ladx;
    LDC "fireworks"
    INVOKESPECIAL bsu.a (Ladx;Ljava/lang/String;)V
   L538
    LINENUMBER 1269 L538
    ALOAD 0
    GETSTATIC aeb.cz : Ladx;
    LDC "command_block_minecart"
    INVOKESPECIAL bsu.a (Ladx;Ljava/lang/String;)V
   L539
    LINENUMBER 1270 L539
    ALOAD 0
    GETSTATIC akg.cv : Lakf;
    LDC "barrier"
    INVOKESPECIAL bsu.a (Lakf;Ljava/lang/String;)V
   L540
    LINENUMBER 1271 L540
    ALOAD 0
    GETSTATIC akg.ac : Lakf;
    LDC "mob_spawner"
    INVOKESPECIAL bsu.a (Lakf;Ljava/lang/String;)V
   L541
    LINENUMBER 1272 L541
    ALOAD 0
    GETSTATIC aeb.bX : Ladx;
    LDC "written_book"
    INVOKESPECIAL bsu.a (Ladx;Ljava/lang/String;)V
   L542
    LINENUMBER 1273 L542
    ALOAD 0
    GETSTATIC akg.bg : Lakf;
    GETSTATIC amu$a.k : Lamu$a;
    INVOKEVIRTUAL amu$a.a ()I
    LDC "brown_mushroom_block"
    INVOKEVIRTUAL bsu.a (Lakf;ILjava/lang/String;)V
   L543
    LINENUMBER 1274 L543
    ALOAD 0
    GETSTATIC akg.bh : Lakf;
    GETSTATIC amu$a.k : Lamu$a;
    INVOKEVIRTUAL amu$a.a ()I
    LDC "red_mushroom_block"
    INVOKEVIRTUAL bsu.a (Lakf;ILjava/lang/String;)V
   L544
    LINENUMBER 1275 L544
    ALOAD 0
    GETSTATIC akg.bI : Lakf;
    LDC "dragon_egg"
    INVOKESPECIAL bsu.a (Lakf;Ljava/lang/String;)V
   L545
    LINENUMBER 1276 L545
    ALOAD 0
    GETSTATIC akg.dc : Lakf;
    LDC "repeating_command_block"
    INVOKESPECIAL bsu.a (Lakf;Ljava/lang/String;)V
   L546
    LINENUMBER 1277 L546
    ALOAD 0
    GETSTATIC akg.dd : Lakf;
    LDC "chain_command_block"
    INVOKESPECIAL bsu.a (Lakf;Ljava/lang/String;)V
   L547
    LINENUMBER 1278 L547
    ALOAD 0
    GETSTATIC akg.dk : Lakf;
    GETSTATIC are$a.a : Lare$a;
    INVOKEVIRTUAL are$a.a ()I
    LDC "structure_block"
    INVOKEVIRTUAL bsu.a (Lakf;ILjava/lang/String;)V
   L548
    LINENUMBER 1279 L548
    ALOAD 0
    GETSTATIC akg.dk : Lakf;
    GETSTATIC are$a.b : Lare$a;
    INVOKEVIRTUAL are$a.a ()I
    LDC "structure_block"
    INVOKEVIRTUAL bsu.a (Lakf;ILjava/lang/String;)V
   L549
    LINENUMBER 1280 L549
    ALOAD 0
    GETSTATIC akg.dk : Lakf;
    GETSTATIC are$a.c : Lare$a;
    INVOKEVIRTUAL are$a.a ()I
    LDC "structure_block"
    INVOKEVIRTUAL bsu.a (Lakf;ILjava/lang/String;)V
   L550
    LINENUMBER 1281 L550
    ALOAD 0
    GETSTATIC akg.dk : Lakf;
    GETSTATIC are$a.d : Lare$a;
    INVOKEVIRTUAL are$a.a ()I
    LDC "structure_block"
    INVOKEVIRTUAL bsu.a (Lakf;ILjava/lang/String;)V
   L551
    LINENUMBER 1283 L551
    GETSTATIC Reflector.ModelLoader_onRegisterItems : LReflectorMethod;
    INVOKEVIRTUAL ReflectorMethod.exists ()Z
    IFEQ L552
   L553
    LINENUMBER 1284 L553
    GETSTATIC Reflector.ModelLoader_onRegisterItems : LReflectorMethod;
    ICONST_1
    ANEWARRAY java/lang/Object
    DUP
    ICONST_0
    ALOAD 0
    GETFIELD bsu.d : Lboe;
    AASTORE
    INVOKESTATIC Reflector.call (LReflectorMethod;[Ljava/lang/Object;)Ljava/lang/Object;
    POP
   L552
    LINENUMBER 1286 L552
   FRAME FULL [bsu] []
    RETURN
   L554
    LOCALVARIABLE this Lbsu; L0 L554 0
    MAXSTACK = 5
    MAXLOCALS = 1

  // access flags 0x1
  public a(Lbxd;)V
   L0
    LINENUMBER 1290 L0
    ALOAD 0
    GETFIELD bsu.d : Lboe;
    INVOKEVIRTUAL boe.b ()V
   L1
    LINENUMBER 1291 L1
    RETURN
   L2
    LOCALVARIABLE this Lbsu; L0 L2 0
    LOCALVARIABLE resourceManager Lbxd; L0 L2 1
    MAXSTACK = 1
    MAXLOCALS = 2

  // access flags 0x8
  static <clinit>()V
   L0
    LINENUMBER 70 L0
    NEW kn
    DUP
    LDC "textures/misc/enchanted_item_glint.png"
    INVOKESPECIAL kn.<init> (Ljava/lang/String;)V
    PUTSTATIC bsu.b : Lkn;
    RETURN
    MAXSTACK = 3
    MAXLOCALS = 0
}
